Workbook

Sheet Surat
A2: Urutan Surat di Quran | B2: Arabic | C2: Idn | D2: Arti | E2: Jumlah Ayat | F2: Muhammad's potential personal motivations and psychological state | G2: Analisis Kritis | H2: Rev | I2: Konteks Lama | J2: kritik terisi | L2: asbabun nuzul terisi | N2: logical fallacy terisi | P2: MORAL CONCERNS | R2: SCIENTIFIC ERRORS | T2: CONTRADICTIONS
A3: 1 | B3: الفاتحة | C3: Al-Fatihah | D3: Pembukaan | E3: 7 | F3: Historical Context: Early Meccan period establishing core prayer text. Psychological State: Need to consolidate early followers Personal Goal: Establish unique religious identity Potential Motivation: - Creates dependency through required daily prayers - Positions himself as intermediary to divine guidance - Establishes ritual that centers around his teachings | G3: Al-Fatihah, meskipun singkat (tujuh ayat), berfungsi sebagai pembukaan spiritual Quran dan mengandung beberapa isu kritis yang bernilai untuk dianalisis. ## Struktur Logika yang Problematik Surah ini dimulai dengan invokasi kepada Allah ("dengan menyebut nama Allah yang Maha Pemurah lagi Maha Penyayang"). Struktur ini menetapkan fondasi teologis untuk seluruh Quran melalui asumsi monoteisme absolut tanpa justifikasi rasional. Penggunaan "Tuhan semesta alam" (rabb al-'alamin) merupakan klaim universalis yang mengecualikan perspektif non-monoteistik dan keberagaman spiritual yang nyata dalam masyarakat majemuk, tanpa menyediakan argument untuk mendukung klaim ini. ## Kontradiksi Internal Sifat Ilahi Ayat 3 menggambarkan Allah sebagai "Maha Pemurah lagi Maha Penyayang" (ar-Rahman ar-Rahim). Namun, sifat-sifat ini bertentangan secara fundamental dengan penggambaran Allah di tempat lain dalam Quran. Ayat 4:56 mendeskripsikan Allah mengganti kulit manusia yang terbakar agar mereka terus merasakan siksaan neraka — suatu tindakan yang tidak dapat didamaikan dengan belas kasih sejati. Kontradiksi ini antara sifat rahmat dan perilaku kejam menunjukkan inkonsistensi teologis yang dalam dalam penggambaran ilahi. ## Argumentum ad Baculum dan Sistem Peradilan Retributif Ayat 4 menyebutkan "hari pembalasan" (yawm ad-din) sebagai aspek fundamental kekuasaan Allah. Penekanan pada konsekuensi menghukum digunakan sebagai dasar untuk memperkuat kepercayaan, bukan melalui argumentasi rasional atau bukti empiris. Ini adalah contoh Argumentum ad Baculum — penggunaan ancaman (hukuman akhirat) untuk memvalidasi klaim keagamaan. Lebih lanjut, konsep "hari pembalasan" mengandaikan sistem keadilan retributif murni — hukuman yang setara dengan dosa — yang melampaui standar etika modern yang menekankan rehabilitasi, restorasi, dan proporsionalitas. Konteks abad ke-7 ketika Quran ditulis mewarisi tradisi hukum retributif dari budaya Semitis kuno, namun ini tidak membuatnya etis valid dalam konteks kontemporer. ## Subordinasi Agen Manusia Ayat 5 menyatakan "hanya kepada Engkaulah kami sembah, dan hanya kepada Engkaulah kami meminta pertolongan". Formulasi ini merefleksikan ketergantungan total pada entitas eksternal (ilahi) untuk keberhasilan dan pertolongan. Sementara permintaan dukungan adalah bagian alami dari pengalaman manusia, frasa "hanya kepada Engkau" membatasi konsepsi kemandirian manusia, kerja sama sosial, dan kapasitas intrinsik untuk memecahkan masalah melalui usaha kolektif. Struktur kepercayaan yang didorong oleh ayat ini berpotensi mengurangi tanggung jawab moral manusia atas tindakan mereka sendiri, dengan mengalihkan agensi ke otoritas ilahi. ## Dikotomi Moral yang Menyederhanakan Ayat 7 membagi manusia menjadi tiga kategori yang didefinisikan secara mutlak dan saling eksklusif: 1. "Orang-orang yang telah Engkau beri nikmat" — kelompok pilihan/berkah 2. "Mereka yang dimurkai" — kelompok yang menerima kemarahan ilahi 3. "Mereka yang sesat" — kelompok yang tersesat Dikotomi ini adalah contoh dari False Dichotomy atau False Dilemma. Realitas manusia jauh lebih kompleks: masyarakat terdiri dari individu dengan spektrum kepercayaan yang beragam, tingkat ketaatan yang bervariasi, komitmen moral yang berlapis, dan pengalaman spiritual yang heterogen. Pembagian sederhana menjadi tiga kategori ini mengabaikan nuansa dan kompleksitas ini. Lebih bermasalah lagi, dikotomi ini mendorong polarisasi moral dan sikap superioritas kelompok. Mereka yang mengidentifikasi diri dengan "diberi nikmat" — yaitu, Muslim yang taat — dapat mengembangkan pandangan hierarchis tentang kelompok manusia lain sebagai "dimurkai" atau "sesat". Struktur naratif ini mendukung: - Sikap superioritas terhadap kelompok non-Muslim - Stigmatisasi terhadap mereka yang dipandang "sesat" (misalnya, Muslim yang tidak taat, ateis, penganut agama lain) - Pemisahan sosial dan eksklusivisme komunal yang membatasi empati lintas kepercayaan Dalam konteks masyarakat plural, struktur dikotomi ini menjadi fondasi teologis untuk diskriminasi dan dehumanisasi "yang lain". ## Kesimpulan Meskipun Al-Fatihah sering dipandang sebagai doa sederhana dan mulia, analisis kritis mengungkapkan beberapa lapisan isu: fondasi argumentatif yang lemah, kontradiksi teologis, penggunaan ancaman sebagai alat persuasi, pengurangan agensi manusia, dan struktur moral yang mempromosikan polarisasi dan superioritas kelompok. Surah ini menetapkan tonalitas untuk interpretasi Quran secara keseluruhan, dan isu-isu ini meresonansi melalui teks yang lebih panjang. | H3: 5 | I3: Konteks Sejarah: Periode awal Mekah yang menetapkan teks doa inti. Keadaan Psikologis: Perlu mengkonsolidasikan pengikut awal Tujuan Pribadi: Membangun identitas keagamaan yang unik Motivasi Potensial: - Menciptakan ketergantungan melalui doa harian yang wajib - Memposisikan diri sebagai perantara bimbingan ilahi - Membangun ritual yang berpusat pada ajarannya | J3: =COUNTIFS(bedah!$C:$C,Surat!$B3,bedah!I:I,"<>") -> 1 | K3: =J3/$E3 -> 0.14285714 | L3: =COUNTIFS(bedah!$C:$C,Surat!$B3,bedah!J:J,"<>") -> 7 | M3: =L3/$E3 -> 1 | N3: =COUNTIFS(bedah!$C:$C,Surat!$B3,bedah!K:K,"<>") -> 2 | O3: =N3/$E3 -> 0.28571429 | P3: =COUNTIFS(bedah!$C:$C,Surat!$B3,bedah!L:L,"<>") -> 1 | Q3: =P3/$E3 -> 0.14285714 | R3: =COUNTIFS(bedah!$C:$C,Surat!$B3,bedah!M:M,"<>") -> 0 | S3: =R3/$E3 -> 0 | T3: =COUNTIFS(bedah!$C:$C,Surat!$B3,bedah!N:N,"<>") -> 1 | U3: =T3/$E3 -> 0.14285714
A4: 2 | B4: البقرة | C4: Al-Baqarah | D4: Sapi | E4: 286 | F4: Historical Context: Medina - Early community-building period, establishing laws while dealing with Jewish tribes Psychological State: Comprehensive law-giving and community organization Potential Motivations: - Using extended Jewish stories to establish new authority - Building complete social-religious framework - Creating clear boundaries with other faiths - Converting existing practices into new system - Establishing distinct religious identity | G4: Al-Baqarah: Surat terpanjang dalam Al-Quran, sekaligus yang paling penuh masalah. Ini bukan serangan — ini pembacaan teks secara apa adanya. Determinisme vs. Kehendak Bebas — Kontradiksi Fundamental: Ayat 6–7 menyatakan Allah mengunci hati orang kafir sehingga mereka tidak akan pernah beriman. Ayat 286 menyatakan Allah tidak membebani jiwa melebihi kemampuannya. Dua klaim ini tidak bisa berdiri bersamaan: kalau hati sudah dikunci Allah, atas dasar apa manusia dihukum? Ini bukan nuansa teologis — ini kontradiksi logis. Circular Reasoning sebagai Pondasi: Ayat 2 mengklaim kitab ini tidak diragukan. Ayat 23 meminta yang meragukan untuk mendatangkan satu surat "semisal" — dengan standar yang ditentukan sendiri oleh sumber yang sedang diperdebatkan. Ini bukan argumen, ini tautologi yang dibungkus tantangan. Narasi Adam yang Berantakan: Ayat 36–38 memerintahkan Adam turun dua kali dari surga. Ini bukan sastra — ini indikasi penggabungan dua versi cerita yang berbeda (dari Surat 7 dan Surat 20) secara tidak rapi. Lebih jauh: Surat 2 mencatat pengampunan Adam SETELAH perintah turun (37), sementara Surat 20 mencatat pengampunan SEBELUM perintah turun (20:122). Dua teks yang sama-sama diklaim wahyu tidak boleh saling membantah urutan kronologis. Kosmologi Abad ke-7 yang Ditetapkan sebagai Doktrin: Ayat 22 menggambarkan langit sebagai "bangunan" di atas bumi — kanopi kosmos pra-ilmiah. Ayat 29 menyatakan bumi diciptakan lebih dulu, baru langit dijadikan tujuh lapis — bertentangan dengan kosmologi modern (bumi terbentuk dari materi bintang yang sudah ada sebelumnya). Ayat 258 mengutip argumen Ibrahim "Allah mendatangkan matahari dari timur" — bahasa Arab menunjukkan matahari yang bergerak aktif. Ini bukan metafora; ini perspektif geosentris yang tidak pernah dikoreksi dalam teks. Bunuhlah Dirimu sebagai Pertobatan: Ayat 54 memerintahkan Bani Israel bertobat dengan cara "membunuh diri sendiri." Tidak ada justifikasi etis yang bisa membuat kematian menjadi syarat pengampunan dari entitas yang disebut Maha Penyayang. Ini bukan ujian — ini absurd secara moral. Perempuan: Objek, Saksi Kelas Dua, Tanpa Otonomi: Ayat 223 menyebut istri sebagai "ladang" yang dikerjakan sesuka hati. Ayat 228 menetapkan lelaki satu derajat di atas perempuan. Ayat 282 menetapkan kesaksian dua perempuan setara satu laki-laki. Ayat 230 melarang rujuk kecuali si istri menikah dulu dengan laki-laki lain (tahlil) — sebuah konstruksi hukum yang merendahkan martabat perempuan menjadi instrumen prosedur. Ini bukan soal konteks budaya abad ke-7. Ini prinsip yang dinyatakan eksplisit sebagai hukum. Tidak Ada Paksaan — Kecuali Kalau Mau Diperangi: Ayat 256 menyatakan "tidak ada paksaan dalam agama." Ayat 193 menyatakan "perangilah mereka sampai tidak ada fitnah dan agama hanya untuk Allah." Dua klaim ini tidak bisa ada dalam satu kitab yang konsisten. Salah satunya bohong, atau keduanya harus ditafsirkan sampai kehilangan makna aslinya. Riba: Taat atau Berperang dengan Tuhan: Ayat 278 memberi ultimatum: tinggalkan sisa riba atau "berperang dengan Allah dan RasulNya." Tidak ada ruang negosiasi, tidak ada gradasi, tidak ada dialog. Ini bukan hukum — ini ancaman eksistensial yang dikemas sebagai regulasi. Kisah Sapi Betina yang Tidak Koheren: Ayat 67 memerintahkan sembelih sapi. Ayat 68–71 menambah spesifikasi berlapis — warna, usia, kondisi — tanpa alasan yang dijelaskan. Ayat 72–73 tiba-tiba berubah menjadi ritual pembuktian kasus pembunuhan. Tidak ada benang naratif yang menghubungkan perintah awal dengan resolusi akhir secara logis. Fitnah Lebih Besar dari Pembunuhan: Ayat 217 menetapkan hierarki nilai yang menempatkan gangguan terhadap agama di atas hilangnya nyawa manusia. Ketika sebuah teks suci menyatakan hal itu secara eksplisit, ia telah menyediakan justifikasi teologis untuk kekerasan atas nama pertahanan agama. Sistem Koreksi Internal (Nasakh): Ayat 106 memperkenalkan konsep penggantian ayat — Allah menukar perintah dengan yang lebih baik atau sebanding. Kalau wahyu ini sempurna dari awal, untuk apa mekanisme koreksi internal? Kalau tidak sempurna, klaim kesempurnaan harus dicabut. Bani Israel sebagai Kambing Hitam Struktural: Sepanjang surat ini, Bani Israel diposisikan sebagai kelompok yang selalu membangkang, membunuh nabi, dan mengkhianati perjanjian (61, 87, 100). Ini bukan catatan sejarah — ini pola narasi yang sistematis untuk mendelegitimasi satu komunitas dan membenarkan penggantiannya oleh komunitas baru. Qishas: Keadilan Primitif Dikodifikasi: Ayat 178–179 menetapkan "mata ganti mata" sebagai sistem keadilan. Sistem hukum modern bergerak ke arah rehabilitasi dan pemulihan — bukan pembalasan setimpal yang mengunci siklus dendam. Kontradiksi Syafaat: Ayat 47 dan 123 menegaskan tidak ada syafaat yang berguna di Hari Kiamat. Ini bertentangan dengan 20:109 yang mengizinkan syafaat bagi mereka yang mendapat izin Allah — dan dengan seluruh tradisi hadis tentang syafaat Nabi. Keduanya tidak bisa sama-sama benar. Kesimpulan: Al-Baqarah lebih menyerupai konstitusi komunitas baru yang sedang membangun otoritas — penuh aturan, ancaman, dan narasi yang mengonstruksi musuh. Bukan wahyu universal yang sempurna dari entitas yang Maha Mengetahui dan Maha Adil. Kalau benar berasal dari Tuhan Yang Maha Sempurna, teks ini tidak seharusnya mengandung kontradiksi internal, kesalahan kosmologi, dan masalah etis yang tidak bisa diselesaikan dengan tafsir apapun. | H4: 87 | I4: Konteks Sejarah: Madinah - Periode awal pembangunan komunitas, menetapkan hukum sambil berurusan dengan suku-suku Yahudi Keadaan Psikologis: Pemberian hukum yang komprehensif dan organisasi komunitas Motivasi Potensial: - Menggunakan kisah-kisah Yahudi yang diperluas untuk membangun otoritas baru - Membangun kerangka kerja sosial-keagamaan yang lengkap - Menciptakan batasan yang jelas dengan agama lain - Mengubah praktik yang ada menjadi sistem baru - Membangun identitas keagamaan yang berbeda | J4: =COUNTIFS(bedah!$C:$C,Surat!$B4,bedah!I:I,"<>") -> 7 | K4: =J4/$E4 -> 0.024475524 | L4: =COUNTIFS(bedah!$C:$C,Surat!$B4,bedah!J:J,"<>") -> 286 | M4: =L4/$E4 -> 1 | N4: =COUNTIFS(bedah!$C:$C,Surat!$B4,bedah!K:K,"<>") -> 78 | O4: =N4/$E4 -> 0.27272727 | P4: =COUNTIFS(bedah!$C:$C,Surat!$B4,bedah!L:L,"<>") -> 60 | Q4: =P4/$E4 -> 0.20979021 | R4: =COUNTIFS(bedah!$C:$C,Surat!$B4,bedah!M:M,"<>") -> 14 | S4: =R4/$E4 -> 0.048951049 | T4: =COUNTIFS(bedah!$C:$C,Surat!$B4,bedah!N:N,"<>") -> 17 | U4: =T4/$E4 -> 0.059440559
A5: 3 | B5: اٰل عمران | C5: Ali 'Imran | D5: Keluarga Imran | E5: 200 | F5: Historical Context: Medina - After Uhud defeat, dealing with Christian delegation from Najran Psychological State: Building resilience after setback while engaging Christians Potential Motivations: - Using Mary/Jesus stories to engage Christians while marking differences - Building defeat into larger victory narrative - Creating martyrdom value system after losses - Converting military loss into spiritual testing - Establishing usury prohibition and economic framework | G5: Ali Imran: Konsolidasi Ideologi dan Legitimasi Kekuasaan Pasca-Badar Diturunkan di Madinah antara tahun 2-3 H, Ali Imran mencerminkan momen kritis komunitas Muslim awal — setelah kemenangan Badar dan menjelang kekalahan Uhud. Surat ini bukan sekadar instruksi teologis; ia adalah dokumen konsolidasi identitas kelompok yang mendefinisikan batas tegas antara in-group (mukmin) dan out-group (kafir, Ahli Kitab, munafik). Eksklusivisme sebagai fondasi. Ayat 19 dan 85 menegaskan bahwa hanya Islam yang diterima Allah, sementara semua agama lain adalah bathil. Ini bukan posisi inklusif yang mengakui nilai universal kebenaran — melainkan klaim monopoli keselamatan yang, secara logis, menjadikan miliaran manusia dari tradisi lain sebagai objek penolakan ilahi. Klaim ini tidak didukung argumen epistemologis — ia ditegakkan melalui otoritas wahyu (circular reasoning) dan ancaman hukuman (ad baculum). Segregasi sosial yang terlembaga. Ayat 28 dan 118 melarang secara eksplisit menjadikan non-Muslim sebagai teman dekat atau kepercayaan, dengan justifikasi bahwa mereka 'tidak menginginkan kebaikan bagi kalian'. Generalisasi ini — mengafirmasi prasangka terhadap seluruh kelompok berdasarkan keyakinan — mengondisikan ketidakpercayaan sistemik dan isolasi sosial. Dalam konteks komunitas plural modern, perintah seperti ini berpotensi menjadi fondasi diskriminasi terstruktur. Glorifikasi perang dan kematian. Ayat 157, 169, dan 195 membangun retorika mulia seputar kematian di medan perang. Syahid 'hidup di sisi Tuhan', kematian dalam perang lebih baik dari kehidupan biasa. Framing ini memuliakan pengorbanan diri dan dapat menyuburkan ideologi yang merendahkan nilai kehidupan — sebuah isu yang sangat relevan dalam konteks radikalisme modern. Kontradiksi tekstual. Surat ini mengandung setidaknya tiga kontradiksi terverifikasi: (1) 3:7 mengakui adanya ayat yang hanya Allah tahu maknanya, bertentangan dengan klaim 12:111 bahwa Quran menjelaskan segala sesuatu; (2) jumlah malaikat di Badar berbeda antara 3:124 (3.000) dan 8:9 (1.000); (3) cara penyampaian kabar kepada Maryam berbeda antara 3:45 (malaikat jamak) dan 19:17 (satu roh berbentuk manusia). Strategi retorika ancaman. Sejumlah ayat (4, 10, 56, 151) menggunakan ancaman azab sebagai instrumen utama kepatuhan. Ini adalah pola argumentum ad baculum — bukan ajakan beriman berdasarkan bukti atau kebaikan, melainkan kepatuhan berbasis ketakutan terhadap konsekuensi negatif. Allah bahkan secara aktif 'memasukkan rasa takut ke hati orang kafir' (151) — melegitimasi teror sebagai alat ilahi. Ali Imran adalah teks yang memperlihatkan bagaimana komunitas keagamaan mengkonsolidasikan identitasnya melalui pembedaan tajam antara kami dan mereka, menggunakan kombinasi ancaman, glorifikasi, dan klaim keistimewaan. Nilai historisnya sebagai rekaman mentalitas komunitas Madinah abad ke-7 tidak diragukan — namun aplikasinya secara harfiah dalam konteks modern mengundang perhatian kritis yang serius. | H5: 89 | I5: Konteks Sejarah: Madinah - Setelah kekalahan Uhud, berurusan dengan delegasi Kristen dari Najran Kondisi Psikologis: Membangun ketahanan setelah kemunduran sambil melibatkan umat Kristen Motivasi Potensial: - Menggunakan kisah Maria/Yesus untuk melibatkan umat Kristen sambil menyoroti perbedaan - Membangun kekalahan menjadi narasi kemenangan yang lebih besar - Menciptakan sistem nilai kemartiran setelah kekalahan - Mengubah kekalahan militer menjadi ujian spiritual - Menetapkan larangan riba dan kerangka ekonomi | J5: =COUNTIFS(bedah!$C:$C,Surat!$B5,bedah!I:I,"<>") -> 8 | K5: =J5/$E5 -> 0.04 | L5: =COUNTIFS(bedah!$C:$C,Surat!$B5,bedah!J:J,"<>") -> 200 | M5: =L5/$E5 -> 1 | N5: =COUNTIFS(bedah!$C:$C,Surat!$B5,bedah!K:K,"<>") -> 17 | O5: =N5/$E5 -> 0.085 | P5: =COUNTIFS(bedah!$C:$C,Surat!$B5,bedah!L:L,"<>") -> 30 | Q5: =P5/$E5 -> 0.15 | R5: =COUNTIFS(bedah!$C:$C,Surat!$B5,bedah!M:M,"<>") -> 5 | S5: =R5/$E5 -> 0.025 | T5: =COUNTIFS(bedah!$C:$C,Surat!$B5,bedah!N:N,"<>") -> 5 | U5: =T5/$E5 -> 0.025
A6: 4 | B6: النساۤء | C6: An-Nisa' | D6: Wanita | E6: 176 | F6: Historical Context: Medina - Post-Uhud, many widows/orphans, new social order needed Psychological State: Establishing comprehensive social reform Potential Motivations: - Using orphan protection to build moral authority - Building detailed women's rights framework - Creating new inheritance system - Converting tribal family customs into Islamic law - Establishing marriage and divorce regulations | G6: An-Nisa: Kitab Hukum Patriarkal, Genosida Religius, dan Kekerasan Melembaga Surat An-Nisa, dengan 176 ayat yang turun di Madinah pascaperang Uhud, adalah surat paling komprehensif sekaligus paling bermasalah dalam Al-Qur'an. Sementara judulnya "Perempuan" menjanjikan perhatian pada nasib perempuan, isi surat ini justru menjadi instrumen yang melembagakan diskriminasi gender, kekerasan domestik, perbudakan seksual, dan doktrin perang agama. Surat ini perlu dibaca secara utuh — bukan sebagai kumpulan ayat yang dapat diisolasi — untuk memahami ekosistem hukum yang dibangunnya. **I. Diskriminasi Gender yang Dikodifikasi sebagai Hukum Ilahi** Sejak ayat pertama, surat ini membangun fondasi androsentris: manusia diciptakan dari "diri yang satu" dan perempuan diciptakan darinya (4:1). Struktur penciptaan ini bukan detail kosmologis yang netral — ia menetapkan laki-laki sebagai standar kemanusiaan dan perempuan sebagai turunan. Ini adalah premis yang kemudian mengalir ke seluruh sistem hukum surat. Sistem waris di ayat 11-12 mengkodifikasi ketidaksetaraan secara matematis: "bagian seorang anak laki-laki sama dengan bagian dua anak perempuan." Tidak ada argumen rasional yang diberikan mengapa jenis kelamin menentukan kapasitas mewarisi. Yang lebih buruk, formula ini ternyata mengandung cacat matematika fatal: beberapa skenario menghasilkan total bagian melebihi 100% — misalnya ketika terdapat istri (1/8), anak perempuan (2/3), ayah (1/6), dan ibu (1/6), totalnya menjadi 27/24. Masalah ini tidak diselesaikan oleh teks sendiri, melainkan harus diperbaiki lewat inovasi post-Qur'anik yang disebut 'awl oleh Khalifah Umar. Sistem yang diklaim sempurna ternyata memerlukan perbaikan oleh manusia. Kontradiksi internal yang paling telanjang dalam surat ini adalah antara ayat 3 dan ayat 129. Ayat 3 mengizinkan poligami dengan syarat "berlaku adil." Ayat 129 mengakui: "Kamu sekali-kali tidak akan dapat berlaku adil di antara istri-istrimu, walaupun kamu sangat ingin berbuat demikian." Satu surat, dua ayat, satu izin dan satu pengakuan bahwa syarat izin tersebut mustahil dipenuhi. **II. Legalisasi Kekerasan Domestik** Ayat 34 adalah salah satu ayat paling destruktif dalam sejarah hukum agama. Ia menetapkan kepemimpinan laki-laki atas perempuan, kemudian memberi suami tiga instrumen kontrol atas istri yang "nusyuz": nasihat, pisah ranjang, dan — pemukulan. Tidak ada ambiguitas di sini. Ini bukan metafora, bukan tafsir yang diperdebatkan — ini izin legal untuk kekerasan fisik dalam rumah tangga. Alasan yang diberikan untuk kepemimpinan laki-laki pun bersifat melingkar: mereka "dipilih" karena Allah "melebihkan" mereka, tanpa kriteria "kelebihan" yang dapat diverifikasi. Ayat 15 menambahkan lapisan diskriminasi: perempuan yang terbukti "berbuat keji" harus dikurung sampai mati atau "sampai Allah memberi jalan lain." Sementara itu, ayat 16 memperlakukan "dua orang" yang melakukan perbuatan yang sama dengan hukuman yang dapat dihapus cukup dengan bertaubat. Perbedaan hukuman yang mencolok ini tidak dijelaskan — ia hanya ditetapkan. **III. Perbudakan Seksual sebagai Hukum Agama** Ayat 24 secara eksplisit mengecualikan perempuan budak dari perlindungan yang diberikan kepada perempuan merdeka: mereka boleh digunakan secara seksual oleh pemiliknya. Tidak ada kewajiban persetujuan, tidak ada mahar, tidak ada wali. Ini bukan penafsiran pinggiran — ini adalah teks yang jelas. Surat yang berjudul "Perempuan" melindungi perempuan merdeka dengan seperangkat hak, sementara menciptakan kelas perempuan yang tidak memiliki hak apapun atas tubuh mereka sendiri. Ayat 25 kemudian menambahkan bahwa budak yang berzina dihukum setengah dari perempuan merdeka — seolah jiwa manusia dapat dikuantifikasi berdasarkan status sosial. **IV. Doktrin Perang Agama dan Dehumanisasi** Separuh kedua surat ini beralih ke konteks militer Madinah, membangun doktrin jihad yang bermasalah. Ayat 89 memerintahkan: "tawan dan bunuhlah mereka di mana saja kamu menemuinya" — perintah eksplisit untuk kekerasan terhadap mereka yang "berpaling." Ayat 76 membangun dikotomi absolut: "orang beriman berperang di jalan Allah, orang kafir berperang di jalan tagut" — framing yang menghilangkan kemungkinan koeksistensi damai atau resolusi konflik non-kekerasan. Ayat 101 menyatakan "orang kafir adalah musuh yang nyata bagimu" — generalisasi yang tidak membedakan antara kelompok yang sedang berperang dan mereka yang hidup damai. Yang paling problematik secara teologis adalah ayat 88: Allah dinyatakan telah "membalikkan" orang munafik kepada kekafiran, namun mereka tetap dikecam dan diancam atas kekafiran yang ditentukan Allah sendiri. Paradoks ini — menghukum akibat dari tindakan Tuhan sendiri — merusak fondasi tanggung jawab moral seluruh sistem etika surat. **V. Antipati terhadap Yahudi sebagai Doktrin** Ayat 44-52, 155-162 membangun narasi kolektif negatif tentang Yahudi: mereka "membeli kesesatan," "mengubah perkataan dari tempatnya," "dikutuk Allah," dan "membunuh nabi-nabi." Stereotip ini tidak dibatasi pada individu atau kelompok tertentu dalam waktu tertentu — ia diterapkan secara kolektif kepada seluruh "orang Yahudi" (ayat 46, 160). Ini adalah teks yang secara historis menyumbang pada antisemitisme teologis. Ayat 157 secara khusus menyangkal penyaliban Yesus — klaim yang bertentangan dengan konsensus sejarah dari sumber Romawi (Tacitus) dan Yahudi (Josephus) abad pertama. Bukan sekadar perbedaan teologis, ini adalah klaim historis yang dapat diverifikasi dan salah. **VI. Sistem Kontrol Kosmik berbasis Ketakutan** Surat ini menggunakan surga dan neraka sebagai instrumen kontrol sosial secara berlebihan. Penolak hukum waris masuk neraka (ayat 14). Penolak Nabi sebagai hakim dinyatakan belum beriman (ayat 65). Orang yang beriman lalu kafir lalu beriman lagi tidak akan diampuni (ayat 137). Gambaran neraka yang paling mengerikan ada di ayat 56: kulit yang hangus terus diganti agar siksaan dapat dirasakan secara permanen. Ini bukan metafora — ini penggambaran sadisme yang diatribusikan kepada Allah "Yang Maha Bijaksana." Sistem ini menciptakan konformitas berbasis teror, bukan pemahaman etis yang otonom. Ketika seluruh sistem sosial, ekonomi, hukum, dan militer disandingkan dengan ancaman hukuman kosmik permanen, pertanyaan kritis menjadi tindakan pembangkangan teologis. **Kesimpulan** An-Nisa adalah surat hukum — bukan puisi spiritual atau refleksi teologis yang bisa ditafsirkan bebas. Ia menetapkan aturan konkret tentang warisan, pernikahan, perceraian, perang, dan hukuman. Aturan-aturan ini memiliki konsekuensi nyata bagi jutaan orang. Analisis kritis bukan serangan terhadap keyakinan individu, tetapi penilaian terhadap sistem hukum yang menetapkan dirinya sebagai final dan ilahi. Dari perspektif hak asasi manusia, surat ini melembagakan: kekerasan domestik (4:34), diskriminasi gender dalam warisan (4:11), perbudakan seksual (4:24), hukum ganda berbasis gender dan status sosial (4:15, 4:25), advokasi pembunuhan berbasis agama (4:89), dehumanisasi kelompok agama lain (4:46, 4:101), dan genosida teologis dalam bentuk hukuman kekal (4:56, 4:93). Bahwa semua ini diklaim sebagai perintah Tuhan yang tidak dapat diubah — itulah inti dari masalah yang dihadapi oleh setiap reformasi sosial di masyarakat yang menganut surat ini sebagai hukum. | H6: 92 | I6: Konteks Sejarah: Madinah - Pasca-Uhud, banyak janda/yatim piatu, dibutuhkan tatanan sosial baru Kondisi Psikologis: Membangun reformasi sosial yang komprehensif Motivasi Potensial: - Menggunakan perlindungan anak yatim untuk membangun otoritas moral - Membangun kerangka hak-hak perempuan yang terperinci - Menciptakan sistem warisan baru - Mengubah adat istiadat keluarga suku menjadi hukum Islam - Menetapkan peraturan perkawinan dan perceraian | J6: =COUNTIFS(bedah!$C:$C,Surat!$B6,bedah!I:I,"<>") -> 10 | K6: =J6/$E6 -> 0.056818182 | L6: =COUNTIFS(bedah!$C:$C,Surat!$B6,bedah!J:J,"<>") -> 176 | M6: =L6/$E6 -> 1 | N6: =COUNTIFS(bedah!$C:$C,Surat!$B6,bedah!K:K,"<>") -> 18 | O6: =N6/$E6 -> 0.10227273 | P6: =COUNTIFS(bedah!$C:$C,Surat!$B6,bedah!L:L,"<>") -> 27 | Q6: =P6/$E6 -> 0.15340909 | R6: =COUNTIFS(bedah!$C:$C,Surat!$B6,bedah!M:M,"<>") -> 5 | S6: =R6/$E6 -> 0.028409091 | T6: =COUNTIFS(bedah!$C:$C,Surat!$B6,bedah!N:N,"<>") -> 15 | U6: =T6/$E6 -> 0.085227273
A7: 5 | B7: الماۤئدة | C7: Al-Ma'idah | D7: Hidangan | E7: 120 | F7: Historical Context: Late Medina - Final major legislation, dealing with Jewish/Christian relations Psychological State: Completing religious law system Potential Motivations: - Using food laws to establish distinct identity - Building comprehensive contract fulfillment system - Creating clear interfaith interaction rules - Converting existing practices into final form - Establishing religious completion concept | G7: Al-Ma'idah: Hukuman Amputasi, Apartheid Agama, dan Kesalahan Teologis Surat Al-Ma'idah (Hidangan) adalah surat Madinah ke-112 dalam urutan turun wahyu, dengan 120 ayat yang mencakup hukum pidana, regulasi sosial lintas agama, narasi nabi-nabi Bani Israel, dan polemik teologis terhadap Kristen. Nama surat ini diambil dari episode "hidangan langit" (ayat 112-115) yang tidak memiliki padanan dalam tradisi Kristiani. Dari perspektif kritis, Al-Ma'idah adalah satu dokumen paling bermasalah dalam Al-Quran — menggabungkan hukuman fisik permanen, apartheid berbasis agama, stereotip kelompok, dan kesalahpahaman mendasar terhadap teologi Kristen. Hukuman Fisik Permanen: Penyaliban dan Amputasi (Ayat 33, 38) Ayat 33 menetapkan menu hukuman bagi yang "memerangi Allah dan Rasul": dibunuh, disalib, dipotong tangan dan kaki secara bersilangan, atau diasingkan. Ayat 38 memerintahkan potong tangan bagi pencuri. Keduanya bukan hukuman yang dapat dikoreksi jika kelak ditemukan kesalahan prosedural atau konteks yang meringankan. Penyaliban adalah bentuk eksekusi paling perlahan dan menyakitkan dalam sejarah — kematian bisa berlangsung berhari-hari. Bahwa sebuah teks yang mengklaim berasal dari Tuhan Yang Maha Pengasih memuatnya sebagai opsi legal adalah kontradiksi nilai yang fundamental. Lebih jauh, hukuman amputasi tangan pencuri menciptakan disabilitas permanen tanpa kemungkinan rehabilitasi, tidak membedakan konteks (mencuri karena kelaparan vs. kriminal profesional), dan tidak proporsional dengan beragam jenis pencurian. Standar hak asasi manusia internasional dengan eksplisit mengkategorikan amputasi judisial sebagai penyiksaan. Sistem Keadilan Primitif: Lex Talionis (Ayat 45) Ayat 45 menetapkan prinsip "jiwa dengan jiwa, mata dengan mata, hidung dengan hidung, telinga dengan telinga, gigi dengan gigi." Sistem ini — dikenal sebagai lex talionis — telah ada ribuan tahun sebelum Islam dalam Kode Hammurabi (sekitar 1750 SM). Bahwa ia diulang dalam teks yang diklaim wahyu Tuhan final mengindikasikan stagnasi moral, bukan kemajuan. Sistem balas dendam simetris ini tidak mempertimbangkan konteks, tidak mendorong rekonsiliasi, menutup rehabilitasi pelaku, dan mengabadikan siklus kekerasan. Hukum pidana modern telah bergerak jauh melampaui lex talionis justru karena kita memahami bahwa keadilan bukan tentang simetri balasan, melainkan tentang pencegahan, rehabilitasi, dan perlindungan masyarakat. Apartheid Berbasis Agama: Larangan Menjadikan Non-Muslim sebagai Pemimpin (Ayat 51) Ayat 51 secara eksplisit melarang orang beriman mengambil Yahudi dan Kristen sebagai "auliyā'" (pemimpin/pelindung/sekutu dekat). Mereka yang melanggar disebut "satu dari mereka" — efektif dianggap murtad atau pengkhianat. Ini bukan sekadar waspada terhadap musuh yang sedang berperang; ini adalah segregasi sistematis berdasarkan identitas agama. Larangan ini menciptakan hierarki kewargaan de facto: Muslim sebagai kelas pertama yang berhak memimpin; Yahudi dan Kristen sebagai kelas yang tidak berhak memimpin dan patut dicurigai. Dalam konteks masyarakat plural, doktrin ini — jika diterapkan secara literal — menjadi fondasi teologis diskriminasi struktural dan eksklusivisme politik. Kontradiksi Internal tentang Ahli Kitab (Ayat 51 vs. 82) Yang membuat ayat 51 semakin tidak koheren adalah kontradiksinya dengan ayat 82 dalam surat yang sama. Ayat 82 menyatakan bahwa "orang-orang yang mengatakan kami Nasrani" adalah "yang paling dekat cintanya kepada orang beriman." Ayat 51 menginstruksikan jangan menjadikan Nasrani sebagai pemimpin karena mereka bersekutu dengan Yahudi. Kedua pernyataan ini tidak bisa benar secara bersamaan: seseorang tidak mungkin sekaligus "paling dekat cintanya" dan layak dikucilkan dari kepemimpinan. Inkonsistensi ini mencerminkan teks yang berkembang dalam konteks politik berubah-ubah, bukan panduan yang koheren. Stereotip Kolektif dan Ujaran Kebencian terhadap Yahudi (Ayat 41, 64, 78, 82) Al-Ma'idah memuat narasi anti-Yahudi yang sistematik. Ayat 41 menyebut mereka "sangat suka mendengar berita bohong." Ayat 64 mengatakan mereka berkata "tangan Allah terbelenggu" lalu mengutuk "tangan mereka yang terkutuk" — penghukuman kolektif atas pernyataan yang paling tidak dilontarkan oleh segelintir orang. Ayat 78-79 menyebut mereka dilaknat oleh Daud dan Isa karena kemaksiatan. Ayat 82 menyatakan Yahudi adalah "paling keras permusuhannya" terhadap orang beriman. Penggeneralisasian ini bukan kritik atas tindakan spesifik individu atau kelompok tertentu dalam konteks historis tertentu — ini adalah atribusi sifat kolektif permanen kepada seluruh komunitas berdasarkan identitas agama mereka. Pola ini memenuhi definisi modern ujaran kebencian berbasis agama. Kesalahan Teologis: Salah Memahami Doktrin Trinitas (Ayat 72-75, 116) Ini adalah salah satu masalah paling terdokumentasi dalam Al-Quran. Ayat 72-75 mencoba membantah ketuhanan Isa dengan argumen bahwa "Al-Masih putra Maryam tidak lain adalah seorang rasul" dan bahwa ia serta ibunya "biasa memakan makanan" — namun representasi ini tidak menyentuh Trinitas Kristen yang sesungguhnya (Bapa, Anak, Roh Kudus). Lebih parah lagi, ayat 116 menggambarkan Allah bertanya kepada Isa: "Adakah kamu mengatakan kepada manusia: jadikanlah aku dan ibuku sebagai dua tuhan selain Allah?" Tidak ada sekte Kristen mainstream yang pernah memasukkan Maria sebagai anggota Trinitas. Trinitas Kristen adalah Bapa, Anak, dan Roh Kudus — bukan Bapa, Isa, dan Maria. Kesalahan ini berulang juga dalam surat lain (4:171) dan menunjukkan bahwa penyusun teks ini memiliki pemahaman yang keliru tentang doktrin Kristen yang menjadi sasaran polemiknya. Sebuah bantahan yang menggunakan straw man bukan hanya tidak efektif — ia juga membuktikan ketidaktahuan sang pembantah. Larangan Berpikir Kritis (Ayat 101) Ayat 101 berisi peringatan eksplisit: "Janganlah kamu menanyakan hal-hal yang jika diterangkan kepadamu akan menyusahkan kamu." Ini adalah instruksi untuk tidak mengajukan pertanyaan kritis tentang hukum agama — bukan karena pertanyaannya tidak valid, melainkan karena jawabannya akan "menyusahkan." Logika ini adalah argumentum ad consequentiam: menghindari pertanyaan berdasarkan akibat emosionalnya. Dalam konteks sistem nilai yang sehat, pertanyaan kritis yang menantang — bahkan yang jawabannya tidak nyaman — justru lebih berharga daripada kepatuhan buta yang tidak pernah bertanya. Inkonsistensi tentang Khamar (Ayat 90 vs. 2:219) Larangan khamar dalam surat ini juga menampilkan inkonsistensi dengan surat lain. Ayat 2:219 mengakui adanya "manfaat bagi manusia" dalam khamar meskipun dosanya besar. Ayat 5:90-91 mendefinisikan khamar murni sebagai "perbuatan setan" yang harus dihindari sepenuhnya, tanpa pengakuan manfaat apapun. Perubahan sikap ini — dari "ada manfaat tapi dosa besar" menjadi "perbuatan setan" — mencerminkan eskalasi bertahap yang wajar dalam proses legislasi manusiawi, bukan konsistensi wahyu ilahi yang tidak berubah. Kekerasan Seksual Berbasis Teks: Posisi Perempuan dalam Ritual Wudhu (Ayat 6) Ayat 6 menetapkan bahwa "menyentuh perempuan" (lāmastum al-nisā') membatalkan wudhu. Framing ini memposisikan tubuh perempuan sebagai agen pencemar ritual — sumber kenajisan yang perlu diwaspadai dalam konteks ibadah. Ini bukan sekadar aturan teknis; ini adalah ekspresi pandangan patriarkal yang meresap ke dalam regulasi keagamaan, di mana perempuan diposisikan sebagai objek yang berpotensi "mengotori" laki-laki secara ritual. Kisah Hidangan Langit: Narasi tanpa Akar Historis (Ayat 112-115) Surat ini — yang namanya diambil dari episode ini — menceritakan murid-murid Isa meminta "hidangan dari langit" sebagai tanda. Tidak ada catatan historis dalam tradisi Kristiani tentang episode semacam ini. Satu-satunya paralel yang mungkin adalah Perjamuan Malam Terakhir (Last Supper), namun narasi Quran menyimpang signifikan. Lebih bermasalah lagi: Allah mengabulkan permintaan hidangan tersebut lalu mengancam hukuman "yang tidak pernah ditimpakan kepada siapapun" bagi yang kafir sesudahnya — respons tidak proporsional yang menciptakan jebakan teologis. Kesimpulan Al-Ma'idah bukan dokumen keadilan atau kasih sayang. Ia adalah teks yang melembagakan amputasi judisial, penyaliban, apartheid agama, stereotip kolektif terhadap komunitas Yahudi dan Kristen, kesalahpahaman doktrin Trinitas, larangan berpikir kritis, dan inkonsistensi internal yang tidak dapat direkonsiliasi. Surat yang diturunkan "hampir terakhir" dan diklaim sebagai legislasi final Islam justru menampilkan beberapa masalah paling fundamental dalam keseluruhan Al-Quran. Tuhan yang memang Maha Adil dan Maha Bijaksana semestinya tidak membutuhkan penyaliban, amputasi, atau larangan bertanya untuk membangun sistem hukum yang baik. | H7: 112 | I7: Konteks Sejarah: Akhir Madinah - Legislasi utama terakhir, yang mengatur hubungan Yahudi/Kristen Kondisi Psikologis: Menyelesaikan sistem hukum keagamaan Motivasi Potensial: - Menggunakan hukum makanan untuk membangun identitas yang berbeda - Membangun sistem pemenuhan kontrak yang komprehensif - Menciptakan aturan interaksi antaragama yang jelas - Mengkonversi praktik yang ada ke bentuk akhir - Membangun konsep penyelesaian keagamaan | J7: =COUNTIFS(bedah!$C:$C,Surat!$B7,bedah!I:I,"<>") -> 4 | K7: =J7/$E7 -> 0.033333333 | L7: =COUNTIFS(bedah!$C:$C,Surat!$B7,bedah!J:J,"<>") -> 120 | M7: =L7/$E7 -> 1 | N7: =COUNTIFS(bedah!$C:$C,Surat!$B7,bedah!K:K,"<>") -> 10 | O7: =N7/$E7 -> 0.083333333 | P7: =COUNTIFS(bedah!$C:$C,Surat!$B7,bedah!L:L,"<>") -> 19 | Q7: =P7/$E7 -> 0.15833333 | R7: =COUNTIFS(bedah!$C:$C,Surat!$B7,bedah!M:M,"<>") -> 5 | S7: =R7/$E7 -> 0.041666667 | T7: =COUNTIFS(bedah!$C:$C,Surat!$B7,bedah!N:N,"<>") -> 7 | U7: =T7/$E7 -> 0.058333333
A8: 6 | B8: الأنعام | C8: Al-An'am | D8: Binatang Ternak | E8: 165 | F8: Historical Context: Intense polytheistic debate period Psychological State: Argumentative and establishing monotheistic logic Potential Motivations: - Using Abraham's story to dismantle idol worship logically - Building comprehensive argument against polytheism - Creating natural phenomena as signs framework - Converting Arabian customs into monotheistic framework - Establishing clear dietary/ritual laws against pagan practices | G8: Al-An'am adalah surat Makkiyah terpanjang, turun di tengah konfrontasi langsung antara Muhammad dan kaum musyrik Quraisy. Dengan 165 ayat, surat ini membangun argumen teologis yang sangat terstruktur — dan sekaligus memperlihatkan tumpukan persoalan logis, etis, dan ilmiah yang signifikan. PARADOKS DETERMINISME DAN HUKUMAN Persoalan paling mendasar dalam Al-An'am adalah kontradiksi teologis yang berulang: Allah diklaim secara aktif menyesatkan sebagian manusia — menutup hati mereka (6:25), mempalingkan hati dan penglihatan mereka (6:110), menjadikan dada mereka sempit sehingga tidak dapat menerima Islam (6:125) — kemudian menghukum mereka atas kesesatan yang Allah sendiri ciptakan. Ini bukan keadilan. Ini adalah sistem hukuman atas kondisi yang diciptakan oleh pihak yang menghukum. Hakim yang menciptakan kejahatan lalu mengadilinya bukan hakim — melainkan tirani yang menyelubungi diri dengan bahasa keadilan. Paradoks ini diperparah oleh ayat 35: "Jika Allah menghendaki, Dia bisa mengumpulkan mereka semua di atas petunjuk." Allah diklaim memiliki kemampuan untuk menjadikan semua orang beriman — namun memilih tidak melakukannya, lalu menghukum mereka yang tidak beriman. Ini bukan tes kebebasan berkehendak. Ini adalah permainan yang hasilnya sudah ditentukan, namun pesertanya tetap dihukum seolah-olah ada pilihan. SISTEM ANCAMAN SEBAGAI FONDASI TEOLOGIS Al-An'am menggunakan ancaman sebagai argumen utamanya. Hampir setiap segmen diisi dengan deskripsi siksa: azab dari atas dan bawah (6:65), pemusnahan sampai ke akar-akarnya (6:45), minuman dari air mendidih (6:70), gambaran penyesalan di hadapan neraka (6:27-31), dan kematian tiba-tiba (6:61). Ini bukan teologi — ini manajemen melalui teror psikologis. Keimanan yang lahir dari ancaman bukan keyakinan yang bebas. Ketika seseorang percaya karena takut siksaan bukan karena evaluasi kritis terhadap bukti, yang terbentuk adalah ketundukan paksa, bukan keyakinan yang genuine. Paradoksnya: surat yang mengklaim menawarkan petunjuk justru menutup setiap jalan menuju evaluasi bebas. PENOLAKAN BUKTI YANG TERSTRUKTUR Surat ini membangun mekanisme penolakan permintaan bukti yang elegan namun tidak jujur. Ketika orang meminta tulisan dari langit, dijawab bahwa mereka tetap akan menyebutnya sihir (6:7). Ketika orang meminta malaikat, dijawab bahwa kalau malaikat diturunkan semuanya akan dibinasakan (6:8-9). Ketika orang bersumpah bahwa dengan mukjizat mereka akan beriman, dijawab bahwa sekalipun ada mukjizat mereka tetap tidak akan beriman (6:109). Ini adalah strategi yang sistematis untuk menghindari kewajiban menghadirkan bukti yang dapat diverifikasi. Setiap permintaan bukti direspons dengan meramalkan bahwa pemohon pasti akan menolak — membuat klaim secara definitif tidak dapat difalsifikasi. Sistem kepercayaan yang tidak tahan terhadap pemeriksaan bukan sistem yang kuat; ia adalah sistem yang rapuh dan sadar akan kelemahannya. MASALAH SAINS Surat ini mengandung beberapa klaim yang bertentangan dengan pengetahuan ilmiah modern. Ayat 38 menyatakan bahwa semua hewan dan burung adalah "umat seperti kamu" — klaim yang mengabaikan fakta bahwa banyak spesies bersifat soliter dan tidak membentuk komunitas sosial. Ayat 96 mencerminkan pandangan kosmologis geosentris abad ke-7. Ayat 98 mengklaim seluruh umat manusia berasal dari "satu jiwa" — bertentangan dengan seluruh bangunan teori evolusi dan genetika populasi modern. Paling mencolok adalah ayat 125 yang mengklaim bahwa dada manusia "terasa sempit" di ketinggian tinggi karena Allah menyesatkan — sementara fisiologi modern menunjukkan sebaliknya: paru-paru mengembang dan bernapas lebih cepat untuk mengkompensasi kadar oksigen yang berkurang. KISAH IBRAHIM SEBAGAI RETROACTIVE ISLAMIZATION Narasi Ibrahim dalam surat ini (6:74-90) merupakan contoh konstruksi ulang figur historis untuk kepentingan narasi yang sedang dibangun. Ibrahim digambarkan melalui proses "mencari Tuhan" dengan menguji bintang, bulan, dan matahari — sebuah narasi yang tidak ditemukan dalam teks Ibrani yang lebih tua dan kemungkinan besar adalah penambahan dari penulis Al-Qur'an. Tujuannya jelas: membangun Ibrahim sebagai "Muslim pertama" sebelum Musa dan Yesus, sehingga Islam bukan agama baru tetapi agama yang paling tua dan otentik. Pola ini — mengklaim tokoh-tokoh tradisi lain sebagai bagian dari satu narasi tunggal — adalah strategi legitimasi, bukan pelaporan sejarah. Ketika seorang nabi kemudian mengklaim Nuh, Ibrahim, Musa, dan Isa semua sebenarnya adalah pendahulunya, ia tidak sedang merekam fakta; ia sedang mencaplok warisan. KONTRADIKSI INTERNAL Al-An'am memperlihatkan sejumlah kontradiksi yang tidak dapat diselesaikan secara internal. Tentang kesesatan: 6:12 menyatakan manusia "menzalimi diri sendiri" sementara 6:25 dan 6:39 menyatakan Allah yang menutup hati mereka. Tentang hari kiamat: 6:22-24 menyatakan orang kafir dapat melihat di akhirat, sementara 20:124-125 menyatakan mereka dibangkitkan buta. Tentang Muslim pertama: 6:14 dan 6:163 keduanya mengklaim Muhammad adalah yang pertama berserah diri, sementara narasi lain menunjukkan Nuh dan Lot sudah disebut Muslim jauh sebelumnya. Kontradiksi tentang beban dosa sangat mencolok: 6:164 dengan tegas menyatakan "setiap jiwa hanya menanggung dosanya sendiri, tidak ada jiwa yang menanggung dosa jiwa lain" — sementara 5:29 dan 16:25 menyatakan seseorang bisa menanggung dosa orang lain. Kontradiksi tentang keabadian neraka juga hadir: 6:128 memberi pengecualian "kecuali Allah menghendaki lain" — yang bertentangan dengan doktrin kekekalan neraka. ATURAN MAKANAN TANPA DASAR YANG BISA DIVERIFIKASI Bagian besar dari surat ini diisi dengan regulasi makanan halal-haram (6:118-145). Aturan-aturan ini tidak disertai penjelasan rasional yang dapat dievaluasi secara ilmiah — hanya otoritas. Yang lebih bermasalah: Allah diklaim memberikan pengharaman yang lebih ketat kepada orang Yahudi sebagai "hukuman atas kezaliman mereka" (6:146). Ini adalah diskriminasi hukum berdasarkan identitas kelompok — berbeda standar untuk kelompok berbeda bukan karena pertimbangan substantif, tetapi karena status teologis kelompok tersebut. KESIMPULAN Al-An'am adalah surat yang membangun fondasi teologis melalui intimidasi, menyumbat permintaan bukti melalui prediksi yang tidak dapat difalsifikasi, melegitimasi diskriminasi melalui otoritas ilahi, dan menciptakan paradoks etis fundamental antara kemahakuasaan Allah dan tanggung jawab manusia. Surat ini bukan wahyu tentang keadilan universal — ia adalah sistem kontrol yang canggih, yang secara sistematis menutup setiap pintu bagi evaluasi bebas sambil menuntut pertanggungjawaban penuh dari manusia atas kondisi yang sedari awal ditentukan bukan oleh mereka. | H8: 55 | I8: Konteks Sejarah: Periode perdebatan politeistik yang intens Kondisi Psikologis: Argumentatif dan membangun logika monoteistik Motivasi Potensial: - Menggunakan kisah Abraham untuk membongkar penyembahan berhala secara logis - Membangun argumen komprehensif melawan politeisme - Menciptakan fenomena alam sebagai kerangka tanda - Mengkonversi kebiasaan Arab ke dalam kerangka monoteistik - Menetapkan hukum diet/ritual yang jelas melawan praktik pagan | J8: =COUNTIFS(bedah!$C:$C,Surat!$B8,bedah!I:I,"<>") -> 9 | K8: =J8/$E8 -> 0.054545455 | L8: =COUNTIFS(bedah!$C:$C,Surat!$B8,bedah!J:J,"<>") -> 165 | M8: =L8/$E8 -> 1 | N8: =COUNTIFS(bedah!$C:$C,Surat!$B8,bedah!K:K,"<>") -> 151 | O8: =N8/$E8 -> 0.91515152 | P8: =COUNTIFS(bedah!$C:$C,Surat!$B8,bedah!L:L,"<>") -> 21 | Q8: =P8/$E8 -> 0.12727273 | R8: =COUNTIFS(bedah!$C:$C,Surat!$B8,bedah!M:M,"<>") -> 7 | S8: =R8/$E8 -> 0.042424242 | T8: =COUNTIFS(bedah!$C:$C,Surat!$B8,bedah!N:N,"<>") -> 13 | U8: =T8/$E8 -> 0.078787879
A9: 7 | B9: الأعراف | C9: Al-A'raf | D9: Tempat Tertinggi | E9: 206 | F9: Historical Context: Early detailed exposition of divine law and boundaries Psychological State: Comprehensive teaching and warning mode Potential Motivations: - Using extended Moses narrative to establish law-giving authority - Building detailed paradise/hell imagery from existing Arab concepts - Creating clear criterion between obedience and transgression - Converting existing moral concepts into structured framework - Addressing specific Jewish/Christian narratives present in Arabia | G9: Al-A'raf: Surat Panjang yang Mengekspos Fondasi Bermasalah Islam Surat Al-A'raf adalah satu dari surat terpanjang dalam Al-Quran (206 ayat) dan termasuk surat Makkiyah. Isinya mencakup kisah penciptaan Iblis, narasi Adam dan Hawa, serangkaian kisah penghukuman umat terdahulu (Nuh, 'Ad, Tsamud, Luth, Syu'aib, Musa), deskripsi hari kiamat dan sistem pakaian moral, hingga ajaran tentang tauhid. Membaca surat ini secara kritis mengungkap sejumlah persoalan serius yang tidak bisa diselesaikan dengan tafsir apologetis biasa. 1. TEODISI YANG GAGAL: ALLAH MENCIPTAKAN IBLIS UNTUK MENYESATKAN MANUSIA Salah satu isu paling fundamental dalam surat ini adalah paradoks penciptaan Iblis. Ayat 11–18 menggambarkan Allah memerintahkan malaikat sujud kepada Adam; Iblis menolak karena merasa lebih mulia (dari api, bukan tanah). Allah mengutuk Iblis — lalu secara eksplisit mengizinkan Iblis menggoda dan menyesatkan manusia sampai hari kiamat (ayat 14–18). Paradoks ini tidak bisa diselesaikan: kalau Allah mahakuasa dan mahamengetahui, Dia tahu sejak awal bahwa Iblis akan menolak dan bahwa kehadiran Iblis akan menyebabkan jutaan manusia sesat. Kalau Allah tetap menciptakan dan mengizinkan Iblis beroperasi, Allah adalah penyebab pertama (prima causa) dari kesesatan manusia. Menghukum manusia atas kesesatan yang infrastrukturnya dirancang sejak awal oleh penciptanya sendiri adalah kontradiksi moral yang mendasar. Lebih jauh, ayat 16 mencatat Iblis berkata: "Karena Engkau telah menyesatkan aku" — pernyataan yang tidak pernah dibantah Allah dalam teks. Ini mengimplikasikan bahwa bahkan Iblis mengakui dirinya adalah korban predestinasi, bukan pemberontak bebas. 2. NARASI ADAM DAN HAWA: KONTRADIKSI LINTAS SURAT DAN PEMBUKTIAN KASAR Ayat 22–25 menceritakan kisah Adam dan Hawa yang tergoda, meminta ampun, lalu diperintahkan turun ke bumi. Tapi dibandingkan dengan versi paralel dalam Surat 2:36–38 dan Surat 20:121–124, ada kontradiksi kronologis yang tidak bisa diabaikan. Dalam Surat 20, Adam diampuni sebelum diperintahkan turun. Dalam Surat 7, tidak ada pernyataan pengampunan — langsung ada perintah turun. Dalam Surat 2, perintah turun muncul dua kali (2:36 dan 2:38). Para sarjana akademis mencatat bahwa Surat 2 tampaknya menggabungkan versi Surat 7 dan Surat 20 secara tidak rapi, menciptakan narasi yang tumpang tindih. Ini bukan soal "tafsir berbeda." Ini soal apakah kronologi dalam kitab yang diklaim sempurna bisa saling bertentangan atau tidak. Jawabannya: ya, bisa — dan itu masalah. Selain itu, narasi ini mengandung persoalan moral: perempuan diposisikan sebagai yang lebih mudah tergoda (tradisi tafsir dominan). Konsep rasa malu atas tubuh (aurat) dipancarkan dari sini, dan menjadi fondasi sistem kontrol tubuh perempuan yang bertahan selama berabad-abad. 3. GENOSIDA TEOLOGIS: POLA PENGHANCURAN MASSAL SEBAGAI NARASI UTAMA Surat ini menghabiskan lebih dari separuh isinya untuk menceritakan penghancuran total umat-umat yang menolak nabinya: Kaum Nuh (ayat 59–64), Kaum 'Ad (65–72), Kaum Tsamud (73–79), Kaum Luth (80–84), Kaum Syu'aib (85–93), dan Kaum Firaun (103–136). Polanya identik dan berulang: nabi datang → umat menolak → Allah menghancurkan mereka semua. Yang perlu dikritisi adalah bukan saja kekerasan yang dinormalisasi, tapi logika di baliknya. Penghancuran bersifat kolektif — tidak ada mekanisme untuk melindungi individu yang mungkin tidak bersalah, anak-anak, atau mereka yang tidak pernah mendapat kesempatan mendengar dakwah dengan adil. Lebih jauh, dalam kasus Kaum Tsamud (ayat 78), mereka dinyatakan dibinasakan dengan gempa bumi — sementara Surat 54:31 menyebut "satu teriakan yang dahsyat" dan Surat 11:67 menyebut "suara keras yang menggelegar." Narasi yang sama dikisahkan dengan mekanisme kehancuran yang berbeda di tiga tempat berbeda — kontradiksi faktual yang mencederai klaim konsistensi teks. Post Hoc Ergo Propter Hoc adalah falasi logika yang mendominasi seluruh bagian ini: setiap bencana alam (gempa, angin topan, hujan batu, banjir) diklaim sebagai respons langsung atas penolakan agama. Tidak ada mekanisme kausalitas yang ditawarkan — hanya asersi yang diulang berkali-kali sampai terasa seperti hukum alam. 4. HOMOFOBIA YANG DIKLAIM SEBAGAI SEJARAH Ayat 80–81 menyatakan bahwa kaum Luth adalah "orang-orang yang pertama kali" melakukan hubungan sesama jenis. Klaim ini secara empiris keliru. Hubungan sesama jenis terdokumentasi dalam berbagai peradaban kuno — Mesir, Yunani, Roma, Mesopotamia — jauh sebelum kisah Luth berlangsung. Orientasi seksual juga terdokumentasi secara konsisten di ratusan spesies hewan. Namun persoalan yang lebih mendasar adalah framing moralnya: teks ini menggunakan kata "fahisyah" (perbuatan keji) dan "israf" (melampaui batas) untuk menggambarkan hubungan sesama jenis, tanpa memberikan penjelasan mengapa hubungan tersebut merusak atau merugikan pihak mana pun. Ini bukan argumen moral — ini labelisasi tanpa justifikasi, yang kemudian dijadikan dasar hukum pidana dan kekerasan sosial terhadap komunitas LGBTQ+ selama berabad-abad. 5. KOSMOLOGI YANG SALAH Ayat 54 menggambarkan "malam menutupi siang dengan cepat" — gambaran yang mencerminkan konsepsi kosmologis pra-ilmiah di mana malam dan siang adalah entitas yang saling mengejar. Ini bukan fenomena yang terjadi di seluruh alam semesta; ini adalah persepsi lokal dari permukaan bumi yang berotasi. Teks tidak pernah mengoreksi persepsi ini ke pemahaman heliosentris. Ayat 40 menyatakan tentang "gerbang-gerbang langit" — konsep kosmologi kuno yang menempatkan langit sebagai kubah berlapis dengan pintu-pintu. Ilmu astronomi modern tidak menemukan bukti keberadaan gerbang semacam itu. 6. PREDESTINASI VS. TANGGUNG JAWAB MORAL: KONTRADIKSI SISTEMIK Surat ini berulang kali menyatakan bahwa Allah menyesatkan siapa yang Dia kehendaki dan memberi petunjuk kepada siapa yang Dia kehendaki (ayat 155–156, 178, 186). Pernyataan ini tidak bisa diharmoniskan dengan konsep tanggung jawab moral yang menjadi dasar seluruh sistem hukum dan etika Islam. Kalau Allah yang menentukan siapa yang sesat dan siapa yang mendapat petunjuk, maka orang yang sesat tidak memilih kesesatannya. Menghukum mereka dengan siksa kekal di neraka atas pilihan yang bukan pilihan mereka sendiri adalah tirani, bukan keadilan. Teks tidak pernah menyelesaikan kontradiksi ini — ia hanya mengulanginya di berbagai tempat sambil mempertahankan keduanya secara bersamaan. 7. PERJANJIAN PRA-KELAHIRAN: PERSETUJUAN YANG TIDAK SAH Ayat 172 mengklaim bahwa Allah mengambil "kesaksian" dari seluruh keturunan Adam sebelum mereka lahir: "Bukankah Aku Tuhanmu?" dan mereka menjawab "Betul, kami bersaksi." Perjanjian ini kemudian dijadikan dasar mengapa manusia tidak bisa beralasan "kami tidak tahu" di hari kiamat. Ini adalah konstruksi persetujuan yang tidak bisa diterima: tidak seorang pun yang ada sekarang mengingat perjanjian tersebut, tidak ada yang bisa memverifikasinya, dan tidak ada yang bisa menolaknya. Dalam terminologi hukum modern, ini adalah kontrak yang dibuat tanpa kapasitas hukum yang memadai, tanpa informasi yang lengkap, dan tanpa kemungkinan penolakan — dengan kata lain, bukan kontrak yang sah. 8. FALASI LOGIKA YANG MENDOMINASI TEKS Surat ini adalah laboratorium falasi logika: Argumentum ad Baculum (ancaman) mendominasi: neraka digambarkan berkali-kali dengan detail yang semakin intens bukan untuk memberikan argumen, melainkan untuk menciptakan rasa takut sebagai motivator kepatuhan. Ad Hominem struktural: orang yang tidak percaya disamakan dengan "binatang ternak, bahkan lebih sesat" (ayat 179) dan anjing yang menjulurkan lidah (ayat 176) — bukan argumen yang membahas keberatan mereka, melainkan serangan terhadap martabat mereka. Post Hoc Ergo Propter Hoc: setiap bencana alam dikaitkan dengan penolakan agama tanpa mekanisme kausalitas. Petitio Principii: "terbuktilah kebenaran" setelah tongkat Musa menelan sihir penyihir (ayat 118) — mukjizat tidak bisa membuktikan klaim teologis karena standar pembuktian tidak pernah ditetapkan secara independen. 9. NARASI MUSA: KONTRADIKSI DENGAN SURAT PARALEL Kisah Musa dalam surat ini bertentangan dengan versi paralel di surat-surat lain dalam beberapa titik: Gelar yang diberikan kepada Firaun berbeda: Surat 7:104 mencatat Musa berkata "aku utusan Tuhan semesta alam," sementara Surat 20:47 mencatat instruksi yang berbeda. Reaksi para pembesar Firaun terhadap Musa berbeda antara Surat 7:109–112 dan Surat 26:34–35. Alasan Aaron saat dimarahi Musa tentang anak sapi emas berbeda antara 7:150 dan 20:90–95. Kalau ini wahyu dari sumber yang sama, narasi seharusnya konsisten. Inkonsistensi ini lebih mudah dijelaskan sebagai hasil komposisi manusia yang tidak sempurna daripada wahyu ilahi yang sempurna. 10. JANTUNG SEBAGAI PUSAT KOGNISI Ayat 179 menyatakan mereka yang tidak berpikir "memiliki hati tapi tidak digunakan untuk memahami." Ini mencerminkan pandangan pra-ilmiah yang menempatkan jantung (qalb) sebagai pusat kognisi dan inteligensi — sebuah kepercayaan umum di dunia kuno, yang telah dibantah oleh ilmu neurosains modern yang menetapkan otak sebagai pusat pemrosesan kognitif. KESIMPULAN Al-A'raf bukan sekadar surat panjang dengan kisah-kisah nabi. Ia adalah teks yang secara sistematis membangun fondasi bermasalah: teodisi yang mengizinkan kejahatan sekaligus menghukum pelakunya, narasi genosida yang disakralkan sebagai kehendak ilahi, homofobia yang diposisikan sebagai fakta sejarah, kosmologi yang salah, predestinasi yang menghancurkan tanggung jawab moral, dan perjanjian pra-kelahiran yang tidak bisa disetujui secara sadar. Surat ini didominasi oleh falasi logika (ancaman, serangan personal, generalisasi berlebihan, circular reasoning) bukan oleh argumen yang bisa diverifikasi. Kalau ini wahyu dari entitas Yang Maha Mengetahui dan Maha Adil, standar yang digunakan tidak konsisten dengan keadilan, empati, atau logika yang menjadi fondasi etika manusiawi. | H9: 39 | I9: Konteks Sejarah: Penjelasan rinci awal tentang hukum dan batasan ilahi Keadaan Psikologis: Mode pengajaran dan peringatan yang komprehensif Motivasi Potensial: - Menggunakan narasi Musa yang diperluas untuk menetapkan otoritas pemberi hukum - Membangun gambaran surga/neraka yang rinci dari konsep Arab yang ada - Menciptakan kriteria yang jelas antara ketaatan dan pelanggaran - Mengubah konsep moral yang ada menjadi kerangka kerja yang terstruktur - Menangani narasi Yahudi/Kristen spesifik yang ada di Arab | J9: =COUNTIFS(bedah!$C:$C,Surat!$B9,bedah!I:I,"<>") -> 5 | K9: =J9/$E9 -> 0.024271845 | L9: =COUNTIFS(bedah!$C:$C,Surat!$B9,bedah!J:J,"<>") -> 206 | M9: =L9/$E9 -> 1 | N9: =COUNTIFS(bedah!$C:$C,Surat!$B9,bedah!K:K,"<>") -> 45 | O9: =N9/$E9 -> 0.2184466 | P9: =COUNTIFS(bedah!$C:$C,Surat!$B9,bedah!L:L,"<>") -> 41 | Q9: =P9/$E9 -> 0.19902913 | R9: =COUNTIFS(bedah!$C:$C,Surat!$B9,bedah!M:M,"<>") -> 14 | S9: =R9/$E9 -> 0.067961165 | T9: =COUNTIFS(bedah!$C:$C,Surat!$B9,bedah!N:N,"<>") -> 10 | U9: =T9/$E9 -> 0.048543689
A10: 8 | B10: الأنفال | C10: Al-Anfal | D10: Rampasan Perang | E10: 75 | F10: Historical Context: Medina - After Badr battle, dealing with war spoils disputes Psychological State: Managing victory and internal disputes Potential Motivations: - Using battle events to establish authority - Building divine control over victory narrative - Creating clear spoils distribution system - Converting tribal customs into religious framework -Establishing obedience in conflict situations | G10: Al-Anfal: Surat ini berisi banyak aturan perang yang bermasalah kalau dilihat secara kritis. Ada beberapa masalah besar: Harta rampasan dijadikan rezeki halal: Surat ini menyatakan harta yang dirampas dari musuh dalam perang itu halal. Ini sama saja melegalkan perampokan asal atas nama agama. Ekonomi yang sehat tidak bisa dibangun dari merampok orang lain. Perintah sadis dalam perang: Ada ayat yang memerintahkan potong kepala dan pancung jari musuh. Sangat kejam — perang modern pun punya aturan untuk tidak menyiksa lawan. Menganggap non-Muslim seperti binatang: Ada ayat yang menyatakan orang kafir lebih rendah dari binatang. Ini merusak penghargaan terhadap sesama manusia dan membuka jalan bagi kekerasan terhadap yang berbeda agama. Klaim malaikat ikut berperang: Surat ini mengklaim malaikat turun membantu Muslim bertempur. Klaim seperti ini membuat perang terlihat sah secara kosmis — dan itu justru berbahaya. Melarang mundur dari perang: Ada larangan tegas untuk mundur dari pertempuran. Ini memaksa orang terus bertempur meski situasinya sudah berbahaya, dan bisa berujung pada kematian sia-sia. Membenarkan pengkhianatan perjanjian: Ada aturan yang membolehkan perjanjian damai diingkari kalau dianggap menguntungkan. Ini merusak kepercayaan dan membuat hubungan antar kelompok tidak pernah benar-benar stabil. Terorisme psikologis: Ada perintah untuk menakut-nakuti musuh sebesar mungkin. Ini bukan strategi militer biasa — ini terorisme yang disahkan teks. Template untuk kekerasan: Beberapa ayat dari surat ini sering dikutip kelompok radikal untuk membenarkan tindakan kekerasan mereka. Kesimpulan: Al-Anfal bukan wahyu tentang perdamaian — ini manual perang total yang mengajarkan perampokan, kekerasan, dan supremasi agama melalui kekuatan. Spiritualitas sejati seharusnya mengajarkan perdamaian dan menghargai sesama manusia, bukan potong kepala atau rampok harta musuh untuk "menyebarkan agama." | H10: 88 | I10: Konteks Sejarah: Madinah - Setelah Pertempuran Badr, menangani sengketa rampasan perang Kondisi Psikologis: Mengelola kemenangan dan perselisihan internal Motivasi Potensial: - Menggunakan peristiwa pertempuran untuk membangun otoritas - Membangun kendali ilahi atas narasi kemenangan - Menciptakan sistem distribusi rampasan perang yang jelas - Mengubah adat istiadat suku menjadi kerangka keagamaan - Membangun kepatuhan dalam situasi konflik | J10: =COUNTIFS(bedah!$C:$C,Surat!$B10,bedah!I:I,"<>") -> 2 | K10: =J10/$E10 -> 0.026666667 | L10: =COUNTIFS(bedah!$C:$C,Surat!$B10,bedah!J:J,"<>") -> 75 | M10: =L10/$E10 -> 1 | N10: =COUNTIFS(bedah!$C:$C,Surat!$B10,bedah!K:K,"<>") -> 61 | O10: =N10/$E10 -> 0.81333333 | P10: =COUNTIFS(bedah!$C:$C,Surat!$B10,bedah!L:L,"<>") -> 19 | Q10: =P10/$E10 -> 0.25333333 | R10: =COUNTIFS(bedah!$C:$C,Surat!$B10,bedah!M:M,"<>") -> 0 | S10: =R10/$E10 -> 0 | T10: =COUNTIFS(bedah!$C:$C,Surat!$B10,bedah!N:N,"<>") -> 3 | U10: =T10/$E10 -> 0.04
A11: 9 | B11: التوبة | C11: At-Taubah | D11: Pengampunan | E11: 129 | F11: Historical Context: Late Medina - After Mecca conquest, dealing with remaining opposition Psychological State: Establishing final authority Potential Motivations: - Using military strength to end old agreements - Building clear loyalty demands - Creating detailed hypocrite exposure - Converting tribal alliances into religious loyalty - Establishing absolute religious authority | G11: At-Taubah: Surat ini berisi banyak aturan perang yang ekstrem. Kalau dilihat secara kritis, ada beberapa masalah besar: Ayat Pedang yang memerintahkan pembunuhan: Ada ayat yang memerintahkan membunuh orang musyrik di mana saja mereka ditemukan. Ini seperti perintah pembunuhan massal terhadap orang yang berbeda agama — sangat berbahaya kalau ditafsir secara harfiah. Pajak khusus untuk non-Muslim: Non-Muslim diwajibkan membayar jizyah yang tidak dibebankan kepada Muslim. Ini diskriminasi ekonomi yang menjadikan non-Muslim warga kelas dua di negara mereka sendiri. Tujuan dominasi total: Surat ini menyatakan tujuannya adalah semua agama tunduk pada Islam. Ini tidak menghargai kebebasan beragama dan keragaman kepercayaan. Melarang berteman dengan keluarga non-Muslim: Ada larangan untuk berteman bahkan dengan orang tua atau saudara kandung yang tidak memeluk Islam. Ini memecah keluarga dan merusak hubungan darah. Tidak ada Bismillah: Surat ini satu-satunya yang tidak diawali dengan "Bismillahirrahmanirrahim" — secara tidak langsung mengakui bahwa isinya mungkin tidak selaras dengan sifat "pengasih" yang diklaim. Ancaman terhadap orang yang ragu: Ada ancaman berat bagi orang yang pura-pura beriman sementara hatinya ragu. Ini bentuk kontrol pikiran yang membuat orang takut jujur terhadap keraguan mereka sendiri. Membenarkan pengkhianatan perjanjian: Ada aturan yang membolehkan perjanjian damai dibatalkan kalau dianggap menguntungkan. Ini merusak kepercayaan dalam hubungan antar kelompok maupun antarnegara. Sistem ekonomi yang tidak adil: Ekonomi dibangun dari rampasan perang dan pajak diskriminatif, bukan dari kerja produktif yang menguntungkan semua pihak. Kesimpulan: At-Taubah bukan wahyu tentang perdamaian — ini deklarasi perang dan supremasi yang mengajarkan kekerasan sistematis, diskriminasi, dan dominasi agama sampai semua pihak tunduk. Spiritualitas sejati seharusnya mengajarkan perdamaian, toleransi, dan penghargaan terhadap perbedaan, bukan memaksa kepatuhan dengan ancaman dan kekerasan. | H11: 113 | I11: Konteks Sejarah: Madinah Akhir - Setelah penaklukan Mekah, menghadapi oposisi yang tersisa Kondisi Psikologis: Menetapkan otoritas tertinggi Motivasi Potensial: - Menggunakan kekuatan militer untuk mengakhiri perjanjian lama - Membangun tuntutan loyalitas yang jelas - Menciptakan pengungkapan kemunafikan secara rinci - Mengubah aliansi suku menjadi loyalitas agama - Menetapkan otoritas agama absolut | J11: =COUNTIFS(bedah!$C:$C,Surat!$B11,bedah!I:I,"<>") -> 3 | K11: =J11/$E11 -> 0.023255814 | L11: =COUNTIFS(bedah!$C:$C,Surat!$B11,bedah!J:J,"<>") -> 129 | M11: =L11/$E11 -> 1 | N11: =COUNTIFS(bedah!$C:$C,Surat!$B11,bedah!K:K,"<>") -> 73 | O11: =N11/$E11 -> 0.56589147 | P11: =COUNTIFS(bedah!$C:$C,Surat!$B11,bedah!L:L,"<>") -> 31 | Q11: =P11/$E11 -> 0.24031008 | R11: =COUNTIFS(bedah!$C:$C,Surat!$B11,bedah!M:M,"<>") -> 1 | S11: =R11/$E11 -> 0.007751938 | T11: =COUNTIFS(bedah!$C:$C,Surat!$B11,bedah!N:N,"<>") -> 5 | U11: =T11/$E11 -> 0.03875969
A12: 10 | B12: يونس | C12: Yunus | D12: Yunus | E12: 109 | F12: Historical Context: Period of strong opposition to message Psychological State: Defensive and argumentative about revelation Potential Motivations: - Using delayed punishment concept to explain lack of immediate signs - Building divine wisdom narrative for gradual revelation - Creating repentance opportunity framework - Converting opponent demands into theological lessons - Establishing natural phenomena as sufficient signs | G12: Yunus: Surat ini mengandung banyak masalah logis tentang keadilan. Kalau dilihat secara kritis, ada beberapa masalah besar: Allah pilih kasih dalam memberi petunjuk: Surat ini menyatakan Allah memberi petunjuk kepada siapa yang Dia kehendaki, tapi kemudian menyalahkan orang yang tidak mendapatkannya. Ini tidak adil — seperti guru yang hanya mengajari sebagian murid, lalu marah ketika yang lain tidak bisa. Al-Quran tidak bisa diubah, tapi ada sistem mansukh: Di satu sisi dinyatakan Al-Quran tidak bisa diubah, tapi di sisi lain ada sistem naskh yang membatalkan ayat-ayat tertentu. Ini kontradiksi yang jelas — mana yang benar? Semua kesalahan dibebankan pada manusia, padahal Allah yang merancang sistemnya: Setiap masalah selalu disalahkan pada manusia, sementara Allah sendiri yang menciptakan sistem predestinasi. Ini victim blaming — menyalahkan orang atas hasil dari sistem yang sudah dirancang sejak awal. Kontradiksi tentang Ahli Kitab: Di satu tempat disuruh bertanya kepada Ahli Kitab kalau ragu, tapi di tempat lain mereka diklaim sudah menyimpang. Mana yang berlaku? Tidak masuk akal menyuruh bertanya kepada pihak yang dianggap sesat. Sistem pengawasan total: Allah digambarkan memantau setiap detail kehidupan manusia. Ini seperti negara totaliter yang mengawasi seluruh aktivitas warganya — tidak ada ruang untuk privasi atau kebebasan. Paradoks kemahakuasaan: Kalau Allah mahakuasa dan bisa membuat semua orang beriman, kenapa tidak dilakukan? Kenapa membiarkan orang tersesat lalu menghukumnya? Ini tidak konsisten secara logis. Kritik agama lain yang dangkal: Ada kritik terhadap Trinitas dan kepercayaan lain, tapi dengan pemahaman yang keliru. Ini menunjukkan kurangnya pengetahuan tentang agama yang sedang dikritik. Mendorong kepasifan: Konsep bahwa segalanya sudah ditentukan Allah mendorong orang untuk pasif. Kalau nasib sudah diatur dari awal, logika "untuk apa berusaha keras" menjadi sulit dihindari. Kesimpulan: Yunus bukan wahyu tentang keadilan dan hikmat — ini sistem yang penuh kontradiksi logis, victim blaming, dan ketidakkonsistenan internal yang menunjukkan karya yang tidak sempurna. Tuhan yang benar-benar adil tidak akan merancang sistem yang sudah condong dari awal, lalu menyalahkan manusia atas hasilnya. | H12: 51 | I12: Konteks Sejarah: Periode penentangan kuat terhadap pesan Keadaan Psikologis: Defensif dan argumentatif tentang wahyu Motivasi Potensial: - Menggunakan konsep hukuman tertunda untuk menjelaskan kurangnya tanda-tanda langsung - Membangun narasi hikmat ilahi untuk wahyu bertahap - Menciptakan kerangka kesempatan pertobatan - Mengubah tuntutan lawan menjadi pelajaran teologis - Menetapkan fenomena alam sebagai tanda yang cukup | J12: =COUNTIFS(bedah!$C:$C,Surat!$B12,bedah!I:I,"<>") -> 1 | K12: =J12/$E12 -> 0.0091743119 | L12: =COUNTIFS(bedah!$C:$C,Surat!$B12,bedah!J:J,"<>") -> 109 | M12: =L12/$E12 -> 1 | N12: =COUNTIFS(bedah!$C:$C,Surat!$B12,bedah!K:K,"<>") -> 53 | O12: =N12/$E12 -> 0.48623853 | P12: =COUNTIFS(bedah!$C:$C,Surat!$B12,bedah!L:L,"<>") -> 10 | Q12: =P12/$E12 -> 0.091743119 | R12: =COUNTIFS(bedah!$C:$C,Surat!$B12,bedah!M:M,"<>") -> 2 | S12: =R12/$E12 -> 0.018348624 | T12: =COUNTIFS(bedah!$C:$C,Surat!$B12,bedah!N:N,"<>") -> 6 | U12: =T12/$E12 -> 0.055045872
A13: 11 | B13: هود | C13: Hud | D13: Hud | E13: 123 | F13: Historical Context: Facing tribal rejection and isolation Psychological State: Warning through detailed destruction narratives Potential Motivations: - Using multiple prophet rejection stories for current parallel - Building comprehensive warning narrative - Creating detailed destruction accounts for psychological impact - Converting known Arabian ruins into warning signs - Establishing pattern of minority salvation | G13: Hud: Surat ini berisi banyak kisah pembunuhan massal yang bermasalah. Kalau dilihat secara kritis, ada beberapa masalah besar: Allah sengaja ciptakan perbedaan lalu hukum yang berbeda: Surat ini menyatakan Allah sengaja membuat manusia berbeda-beda, tapi kemudian menghukum mereka yang berbeda keyakinan. Ini tidak adil — seperti merancang permainan dengan aturan yang sudah memastikan ada yang kalah. Banjir global Nuh tanpa bukti ilmiah: Cerita banjir yang merendam seluruh dunia tidak memiliki bukti geologis maupun arkeologis. Air sebanyak itu tidak mungkin ada di bumi, dan tidak ada jejak banjir global dalam catatan batuan. Pembunuhan massal berbagai kaum: Kaum 'Ad, Tsamud, Luth, dan Madyan semuanya dimusnahkan hanya karena menolak ajaran nabi mereka. Ini genosida yang dibenarkan atas nama agama. Mukjizat yang tidak masuk akal: Ada kisah unta yang keluar dari batu dan berbagai mukjizat lain tanpa bukti apapun. Ini lebih mirip dongeng daripada catatan sejarah yang bisa dipercaya. Menyalahkan istri Nuh dan Luth: Istri-istri nabi dihukum karena tidak mengikuti keyakinan suami mereka. Ini tidak adil — perempuan dipaksa tunduk pada keyakinan suami, lalu disalahkan kalau tidak setuju. Allah yang emosional dan reaktif: Allah digambarkan mudah marah dan langsung menjatuhkan hukuman berat hanya karena orang menolak ajaran tertentu. Ini tidak mencerminkan Tuhan yang bijak dan sabar. Hukuman kolektif yang tidak adil: Seluruh kaum dimusnahkan, termasuk anak-anak dan orang yang tidak bersalah. Keadilan yang sebenarnya bersifat individual, bukan kolektif. Mencontek cerita dari tradisi lain: Banyak kisah dalam surat ini sangat mirip dengan narasi dalam Kitab Kejadian dan tradisi Yahudi. Al-Quran tampak mengambil cerita yang sudah ada lalu memodifikasinya. Kesimpulan: Hud bukan wahyu tentang kasih dan pengertian — ini justifikasi untuk kekerasan massal dan intoleransi yang dibungkus sebagai "keadilan Tuhan." Setiap kali muncul perbedaan keyakinan, solusinya selalu pemusnahan. Ini template berbahaya untuk intoleransi dan pembersihan etnis. Spiritualitas sejati seharusnya mengajarkan perdamaian dan menghargai perbedaan, bukan membunuh orang yang berbeda keyakinan. | H13: 52 | I13: Konteks Sejarah: Menghadapi penolakan dan isolasi suku Kondisi Psikologis: Peringatan melalui narasi kehancuran yang terperinci Motivasi Potensial: - Menggunakan berbagai kisah penolakan nabi untuk paralel dengan situasi saat ini - Membangun narasi peringatan yang komprehensif - Menciptakan catatan kehancuran yang terperinci untuk dampak psikologis - Mengubah reruntuhan Arab yang dikenal menjadi tanda peringatan - Membangun pola penyelamatan minoritas | J13: =COUNTIFS(bedah!$C:$C,Surat!$B13,bedah!I:I,"<>") -> 1 | K13: =J13/$E13 -> 0.0081300813 | L13: =COUNTIFS(bedah!$C:$C,Surat!$B13,bedah!J:J,"<>") -> 123 | M13: =L13/$E13 -> 1 | N13: =COUNTIFS(bedah!$C:$C,Surat!$B13,bedah!K:K,"<>") -> 63 | O13: =N13/$E13 -> 0.51219512 | P13: =COUNTIFS(bedah!$C:$C,Surat!$B13,bedah!L:L,"<>") -> 23 | Q13: =P13/$E13 -> 0.18699187 | R13: =COUNTIFS(bedah!$C:$C,Surat!$B13,bedah!M:M,"<>") -> 4 | S13: =R13/$E13 -> 0.032520325 | T13: =COUNTIFS(bedah!$C:$C,Surat!$B13,bedah!N:N,"<>") -> 11 | U13: =T13/$E13 -> 0.089430894
A14: 12 | B14: يوسف | C14: Yusuf | D14: Yusuf | E14: 111 | F14: Historical Context: Period of family/tribal separation and betrayal Psychological State: Creating complex moral through extended narrative Potential Motivations: - Using detailed Joseph story to parallel current family divisions - Building long-term patience and triumph narrative - Creating complex moral lesson about betrayal and forgiveness - Converting family trauma into spiritual teaching - Establishing divine plan behind apparent misfortunes | G14: Yusuf: Surat ini mengklaim memuat "kisah terbaik." Kalau dilihat secara kritis, ada beberapa masalah besar: Mengambil cerita dari kitab lain tanpa mengakui: Kisah Yusuf hampir identik dengan kisah Joseph dalam Kitab Kejadian yang sudah ada berabad-abad sebelumnya. Detail-detailnya sangat mirip, tapi sumbernya tidak pernah diakui. Membenarkan perbudakan: Yusuf dijual sebagai budak dan ini digambarkan sebagai bagian dari rencana Allah yang baik. Perbudakan tampil sebagai sesuatu yang normal, bahkan direstui Tuhan — padahal ini pelanggaran hak asasi manusia. Menggambarkan perempuan secara negatif: Istri Potifar digambarkan sebagai perempuan penggoda yang menjadi sumber masalah. Ini stereotipe lama yang memperkuat prasangka bahwa perempuan adalah sumber fitnah. Allah pilih kasih pada Yusuf: Allah memberi Yusuf kemampuan khusus dan ketampanan, sementara orang lain harus menerima nasib yang sudah ditentukan tanpa kesempatan serupa. Ini bukan keadilan. Membenarkan kebohongan: Saudara-saudara Yusuf berbohong kepada ayah mereka, tapi kemudian dimaafkan begitu saja. Pesan yang tersampaikan: berbohong bisa dibenarkan dalam situasi tertentu. Mendukung sistem kekuasaan yang otoriter: Yusuf menjadi penguasa absolut di Mesir dan ini dipuji sebagai hal yang baik. Sistem monarki absolut tidak demokratis dan rentan menindas rakyat. Tafsir mimpi yang tidak ilmiah: Kemampuan menafsir mimpi disajikan sebagai ilmu dari Allah, padahal mimpi tidak bisa diprediksi secara ilmiah dan umumnya tidak berkaitan dengan masa depan. Hukuman yang tidak proporsional: Saudara-saudara Yusuf menanggung akibat bertahun-tahun atas kesalahan yang dilakukan waktu kecil. Ini tidak proporsional dan tidak memberi ruang untuk pertumbuhan yang wajar. Kesimpulan: Yusuf bukan wahyu tentang kebijaksanaan dan keadilan — ini pengambilan cerita lama yang membenarkan perbudakan, sistem otoriter, dan stereotipe negatif tentang perempuan. Lebih mirip hiburan daripada panduan spiritual yang mengajarkan nilai-nilai universal tentang keadilan dan kesetaraan. | H14: 53 | I14: Konteks Sejarah: Periode pemisahan keluarga/suku dan pengkhianatan Kondisi Psikologis: Menciptakan moral yang kompleks melalui narasi yang panjang Motivasi Potensial: - Menggunakan kisah Yusuf yang detail untuk membandingkan perpecahan keluarga saat ini - Membangun kesabaran jangka panjang dan narasi kemenangan - Menciptakan pelajaran moral yang kompleks tentang pengkhianatan dan pengampunan - Mengubah trauma keluarga menjadi ajaran spiritual - Menetapkan rencana ilahi di balik kemalangan yang tampak | J14: =COUNTIFS(bedah!$C:$C,Surat!$B14,bedah!I:I,"<>") -> 3 | K14: =J14/$E14 -> 0.027027027 | L14: =COUNTIFS(bedah!$C:$C,Surat!$B14,bedah!J:J,"<>") -> 111 | M14: =L14/$E14 -> 1 | N14: =COUNTIFS(bedah!$C:$C,Surat!$B14,bedah!K:K,"<>") -> 36 | O14: =N14/$E14 -> 0.32432432 | P14: =COUNTIFS(bedah!$C:$C,Surat!$B14,bedah!L:L,"<>") -> 8 | Q14: =P14/$E14 -> 0.072072072 | R14: =COUNTIFS(bedah!$C:$C,Surat!$B14,bedah!M:M,"<>") -> 4 | S14: =R14/$E14 -> 0.036036036 | T14: =COUNTIFS(bedah!$C:$C,Surat!$B14,bedah!N:N,"<>") -> 2 | U14: =T14/$E14 -> 0.018018018
... A116: 114 | B116: الناس | C116: An-Nas | D116: Manusia | E116: 6 | F116: Historical Context: Period when psychological/spiritual protection needed against hidden enemies. Psychological State: Establishing protective framework Context: Dealing with social/psychological threats Potential Motivations: - Creating hierarchical protection system (Lord, King, God of mankind) - Addressing widespread fears of jinn/whispers - Building psychological dependence through protection prayers - Establishing divine authority over all human levels - Converting common fears into religious adherence mechanism | G116: Kitab suci berakhir dengan mantra pengusir setan. Jin pra-Islam pakai baju Islam: Secara terang-terangan adopsi konsep "was-was" (bisikan jahat) yang identik dengan demonologi pra-Islam Timur Tengah, ngungkap kontinuitas langsung dengan tradisi pagan yang harusnya ditolaknya. "Bisikan" supernatural ini, yang masuk pikiran manusia, adalah duplikasi sempurna dari konsep "qarin" dalam folklor Arab pra-Islam dan analog dengan konsep daimon Yunani-Romawi. Alih-alih konsep orisinal, surat ini cuma rebranding entitas supernatural regional yang udah mapan. Jelasin pikiran lewat hantu: Ngungkap keterbatasan psikologis zamannya dengan reduksi kompleksitas pikiran manusia jadi model "bisikan" external dari entitas jahat. Alih-alih pahamin kondisi psikologis internal manusia, teks ini eksternalisasi konflik batin jadi pertarungan kosmik antara kekuatan baik dan jahat. Model naif ini karakteristik pemahaman pra-modern tentang psikologi manusia yang belum kenal konsep pikiran bawah sadar, kondisi neuropsikologis, atau pemrosesan kognitif kompleks. Tuhan vs Setan: perang tak berujung: Sajiin gambaran teologis yang secara logis nggak koheren - Tuhan omnipoten yang anehnya harus dimintai perlindungan dari entitas jahat yang Dia ciptain dan bisa dihancurin kapan aja. Kenapa Pencipta alam semesta nolerin keberadaan setan yang bisikkin kejahatan ke dalam hati manusia ciptaan-Nya? Kontradiksi logis fundamental ini - entitas maha kuasa yang butuh manusia buat minta perlindungan dari ciptaan-Nya sendiri - ngkhianatin asal-usulnya dalam dualisme mitologis manusia. Grand finale yang mengecewakan: Sebagai surat penutup Al-Quran, sajiin anti-klimaks yang mencengangkan - nggak ada ringkasan pesan moral utama, nggak ada penegasan final kebenaran universal, nggak ada visi eskatologis, cuma formula perlindungan terhadap "bisikan" jahat. Ketidakmampuan tutup "kitab final" dengan pernyataan komprehensif atau transformatif ngungkap karakternya sebagai kompilasi manusiawi yang nggak terencana. Akhir yang lemah ini mencerminkan susunan kronologis arbitrer dari editorial manusia. Kesimpulan: An-Nas mengekspos adopsi demonologi pra-Islam dalam kerangka monoteistik, pemahaman psikologi primitif yang mengeksternalisasi konflik batin, kontradiksi teologis fundamental, dan penutup yang terlalu lemah untuk kitab yang diklaim sebagai wahyu final kosmik. | H116: 21 | I116: Konteks Sejarah: Periode ketika perlindungan psikologis/spiritual dibutuhkan terhadap musuh tersembunyi. Keadaan Psikologis: Membangun kerangka perlindungan Konteks: Menangani ancaman sosial/psikologis Motivasi Potensial: - Menciptakan sistem perlindungan hierarkis (Tuhan, Raja, Tuhan umat manusia) - Mengatasi ketakutan yang meluas terhadap jin/bisikan - Membangun ketergantungan psikologis melalui doa perlindungan - Menetapkan otoritas ilahi atas semua tingkatan manusia - Mengubah ketakutan umum menjadi mekanisme kepatuhan keagamaan | J116: =COUNTIFS(bedah!$C:$C,Surat!$B116,bedah!I:I,"<>") -> 1 | K116: =J116/$E116 -> 0.16666667 | L116: =COUNTIFS(bedah!$C:$C,Surat!$B116,bedah!J:J,"<>") -> 6 | M116: =L116/$E116 -> 1 | N116: =COUNTIFS(bedah!$C:$C,Surat!$B116,bedah!K:K,"<>") -> 6 | O116: =N116/$E116 -> 1 | P116: =COUNTIFS(bedah!$C:$C,Surat!$B116,bedah!L:L,"<>") -> 0 | Q116: =P116/$E116 -> 0 | R116: =COUNTIFS(bedah!$C:$C,Surat!$B116,bedah!M:M,"<>") -> 0 | S116: =R116/$E116 -> 0 | T116: =COUNTIFS(bedah!$C:$C,Surat!$B116,bedah!N:N,"<>") -> 1 | U116: =T116/$E116 -> 0.16666667

Sheet bedah
A1: surat | B1: ayat | C1: Surat Arab | D1: Surat IDN | E1: Tempat | F1: Lafazh | G1: Terjemahan (Departemen Agama) | H1: Topik | I1: Kritik | J1: Asbabun Nuzul (Muchlis M Hanafi) | K1: LOGICAL FALLACIES | L1: MORAL CONCERNS | M1: SCIENTIFIC ERRORS | N1: CONTRADICTIONS | O1: Catatan Depag | P1: kritik notebook LM | Q1: Kritik
A2: 1 | B2: 1 | C2: الفاتحة | D2: Al-Fatihah (Pembukaan) | E2: Makkah | F2: بِسْمِ اللَّهِ الرَّحْمَٰنِ الرَّحِيمِ | G2: Dengan nama Allah Yang Maha Pengasih, Maha Penyayang. | H2: Basmalah (Pembukaan dengan Nama Allah) | I2: Masalah Pembicara dan Status Surat: Teks dalam Surat Al-Fatiha secara jelas ditujukan kepada Tuhan dalam bentuk doa (seperti "Hanya kepada Engkaulah kami menyembah") Ini adalah kata-kata manusia (Muhammad) yang memuji Tuhan, bukan firman Tuhan kepada manusia Untuk menutupi masalah teologis ini, kata perintah "Katakanlah" (Qul) sering diasumsikan ada oleh para penyusun Al-Qur'an di kemudian hari untuk menghilangkan kesulitan yang memalukan tersebut Penolakan oleh Sahabat Nabi: Karena sifatnya yang murni sebagai doa liturgis, Ibn Mas'ud (salah satu otoritas pembacaan Al-Qur'an terkemuka yang ditunjuk Nabi) secara tegas menolak Al-Fatiha (serta Surat 113 dan 114) sebagai bagian dari Al-Qur'an Di dalam naskah/kodeks asli milik Ibn Mas'ud, surat-surat ini tidak dimasukkan karena ia menganggapnya hanya sebagai tambahan doa | J2: Ayat ini turun ketika Nabi Muhammad SAW mendengar **suara gaib memanggil namanya** dan beliau sempat menghindar. Atas saran Waraqah bin Naufal, beliau mendengarkan panggilan tersebut yang kemudian menuntunnya membaca syahadat dan surah Al-Fatihah. Riwayat lain menyebutkan bahwa saat Nabi membacanya di Makkah, kaum Quraisy mengejeknya. | P2: (1:1) Surah ini tidak dianggap sebagai bagian riil dari Al-Qur'an oleh salah satu pencatat wahyu utama, Ibnu Mas'ud, yang secara sadar menolak memasukkannya ke dalam mushafnya. (Criticism of the Quran - Wikipedia; The Origins of the Koran) (1:1) Terdapat masalah sintaksis dan pergeseran narator yang kacau; teks ini secara logis adalah doa manusia yang ditujukan kepada Tuhan ("Hanya Engkaulah yang kami sembah"), bukan Tuhan yang sedang berbicara, menunjukkan kesalahan penyajian narasi ilahi. (Criticism of the Quran - Wikipedia)
A3: 1 | B3: 2 | C3: الفاتحة | D3: Al-Fatihah (Pembukaan) | E3: Makkah | F3: الْحَمْدُ لِلَّهِ رَبِّ الْعَالَمِينَ | G3: Segala puji bagi Allah, Tuhan seluruh alam, | H3: Pujian kepada Allah sebagai Tuhan Semesta Alam | J3: Ayat ini turun ketika Nabi Muhammad SAW mendengar **suara gaib memanggil namanya** dan beliau sempat menghindar. Atas saran Waraqah bin Naufal, beliau mendengarkan panggilan tersebut yang kemudian menuntunnya membaca syahadat dan surah Al-Fatihah. Riwayat lain menyebutkan bahwa saat Nabi membacanya di Makkah, kaum Quraisy mengejeknya. | P3: (1:2) Surah ini tidak dianggap sebagai bagian riil dari Al-Qur'an oleh salah satu pencatat wahyu utama, Ibnu Mas'ud, yang secara sadar menolak memasukkannya ke dalam mushafnya. (Criticism of the Quran - Wikipedia; The Origins of the Koran) (1:2) Terdapat masalah sintaksis dan pergeseran narator yang kacau; teks ini secara logis adalah doa manusia yang ditujukan kepada Tuhan ("Hanya Engkaulah yang kami sembah"), bukan Tuhan yang sedang berbicara, menunjukkan kesalahan penyajian narasi ilahi. (Criticism of the Quran - Wikipedia) (1:2) (12) Surah ini dikritik keras oleh kaum Khawarij purba sebagai sisipan palsu yang tak layak masuk kitab suci, dan cara penceritaannya dipenuhi lompatan irasional (seperti ketidakjelasan mengapa para wanita diberi pisau, atau mengapa Yusuf tetap dipenjara padahal istri Potifar mengaku salah).,, (Tidak dicantumkan)
A4: 1 | B4: 3 | C4: الفاتحة | D4: Al-Fatihah (Pembukaan) | E4: Makkah | F4: الرَّحْمَٰنِ الرَّحِيمِ | G4: Yang Maha Pengasih, Maha Penyayang, | H4: Sifat Allah: Pemurah dan Penyayang | J4: Ayat ini turun ketika Nabi Muhammad SAW mendengar **suara gaib memanggil namanya** dan beliau sempat menghindar. Atas saran Waraqah bin Naufal, beliau mendengarkan panggilan tersebut yang kemudian menuntunnya membaca syahadat dan surah Al-Fatihah. Riwayat lain menyebutkan bahwa saat Nabi membacanya di Makkah, kaum Quraisy mengejeknya. | N4: Kontradiksi Sifat Allah: Ayat ini menyebut Allah 'Maha Pengasih, Maha Penyayang' — bertentangan dengan 4:56 yang menggambarkan Allah mengganti kulit manusia agar terus merasakan siksa neraka; sifat rahmat dan kekejaman ilahi ini tidak dapat didamaikan secara logis. | P4: (1:3) Surah ini tidak dianggap sebagai bagian riil dari Al-Qur'an oleh salah satu pencatat wahyu utama, Ibnu Mas'ud, yang secara sadar menolak memasukkannya ke dalam mushafnya. (Criticism of the Quran - Wikipedia; The Origins of the Koran) (1:3) Terdapat masalah sintaksis dan pergeseran narator yang kacau; teks ini secara logis adalah doa manusia yang ditujukan kepada Tuhan ("Hanya Engkaulah yang kami sembah"), bukan Tuhan yang sedang berbicara, menunjukkan kesalahan penyajian narasi ilahi. (Criticism of the Quran - Wikipedia)
A5: 1 | B5: 4 | C5: الفاتحة | D5: Al-Fatihah (Pembukaan) | E5: Makkah | F5: مَالِكِ يَوْمِ الدِّينِ | G5: Pemilik hari pembalasan.1) | H5: Allah Penguasa Hari Pembalasan | J5: Ayat ini turun ketika Nabi Muhammad SAW mendengar **suara gaib memanggil namanya** dan beliau sempat menghindar. Atas saran Waraqah bin Naufal, beliau mendengarkan panggilan tersebut yang kemudian menuntunnya membaca syahadat dan surah Al-Fatihah. Riwayat lain menyebutkan bahwa saat Nabi membacanya di Makkah, kaum Quraisy mengejeknya. | K5: Argumentum ad Baculum (Appeal to Force): Penekanan pada "hari pembalasan" sebagai fondasi kepercayaan menggunakan ancaman hukuman ketimbang argumentasi rasional. | O5: *1) Yaumiddīn (hari pembalasan), hari waktu manusia menerima pembalasan amalnya, baik atau buruk. Disebut juga yaumul qiyāmah, yaumul hisab dan sebagainya. | P5: (1:4) Surah ini tidak dianggap sebagai bagian riil dari Al-Qur'an oleh salah satu pencatat wahyu utama, Ibnu Mas'ud, yang secara sadar menolak memasukkannya ke dalam mushafnya. (Criticism of the Quran - Wikipedia; The Origins of the Koran) (1:4) Terdapat masalah sintaksis dan pergeseran narator yang kacau; teks ini secara logis adalah doa manusia yang ditujukan kepada Tuhan ("Hanya Engkaulah yang kami sembah"), bukan Tuhan yang sedang berbicara, menunjukkan kesalahan penyajian narasi ilahi. (Criticism of the Quran - Wikipedia)
A6: 1 | B6: 5 | C6: الفاتحة | D6: Al-Fatihah (Pembukaan) | E6: Makkah | F6: إِيَّاكَ نَعْبُدُ وَإِيَّاكَ نَسْتَعِينُ | G6: Hanya kepada Engkaulah kami menyembah dan hanya kepada Engkaulah kami mohon pertolongan. | H6: Pengakuan Monoteisme dan Permohonan Bantuan | J6: Ayat ini turun ketika Nabi Muhammad SAW mendengar **suara gaib memanggil namanya** dan beliau sempat menghindar. Atas saran Waraqah bin Naufal, beliau mendengarkan panggilan tersebut yang kemudian menuntunnya membaca syahadat dan surah Al-Fatihah. Riwayat lain menyebutkan bahwa saat Nabi membacanya di Makkah, kaum Quraisy mengejeknya. | P6: (1:5) Surah ini tidak dianggap sebagai bagian riil dari Al-Qur'an oleh salah satu pencatat wahyu utama, Ibnu Mas'ud, yang secara sadar menolak memasukkannya ke dalam mushafnya. (Criticism of the Quran - Wikipedia; The Origins of the Koran) (1:5) Terdapat masalah sintaksis dan pergeseran narator yang kacau; teks ini secara logis adalah doa manusia yang ditujukan kepada Tuhan ("Hanya Engkaulah yang kami sembah"), bukan Tuhan yang sedang berbicara, menunjukkan kesalahan penyajian narasi ilahi. (Criticism of the Quran - Wikipedia) (1:5) Susunan kata diubah secara paksa demi estetika rima puitis Arab; frasa "iyyāka naʿbudu wa-iyyāka nastaʿīn" sebenarnya merupakan bentuk pemaksaan tata bahasa untuk "naʿbuduka wa-nastaʿīnuka". (The Qur'an: A Historical-Critical Introduction)
A7: 1 | B7: 6 | C7: الفاتحة | D7: Al-Fatihah (Pembukaan) | E7: Makkah | F7: اهْدِنَا الصِّرَاطَ الْمُسْتَقِيمَ | G7: Tunjukilah kami jalan yang lurus,2) | H7: Permohonan Bimbingan Menuju Jalan Lurus | J7: Ayat ini turun ketika Nabi Muhammad SAW mendengar **suara gaib memanggil namanya** dan beliau sempat menghindar. Atas saran Waraqah bin Naufal, beliau mendengarkan panggilan tersebut yang kemudian menuntunnya membaca syahadat dan surah Al-Fatihah. Riwayat lain menyebutkan bahwa saat Nabi membacanya di Makkah, kaum Quraisy mengejeknya. | O7: *2) Jalan yang lurus, yaitu jalan hidup yang benar, yang dapat membuat bahagia di dunia dan di akhirat. | P7: (1:6) Surah ini tidak dianggap sebagai bagian riil dari Al-Qur'an oleh salah satu pencatat wahyu utama, Ibnu Mas'ud, yang secara sadar menolak memasukkannya ke dalam mushafnya. (Criticism of the Quran - Wikipedia; The Origins of the Koran) (1:6) Terdapat masalah sintaksis dan pergeseran narator yang kacau; teks ini secara logis adalah doa manusia yang ditujukan kepada Tuhan ("Hanya Engkaulah yang kami sembah"), bukan Tuhan yang sedang berbicara, menunjukkan kesalahan penyajian narasi ilahi. (Criticism of the Quran - Wikipedia) (1:6) Manuskrip kuno milik Ibnu Mas'ud membuktikan ketidakstabilan teks dengan menggunakan varian "arshidnā" (arahkan kami) alih-alih versi standar "ihdinā" (tunjukilah kami), serta ayat ini menjiplak langsung rumusan doa dari Mazmur 27:11. (The Qur'an: A Historical-Critical Introduction,)
A8: 1 | B8: 7 | C8: الفاتحة | D8: Al-Fatihah (Pembukaan) | E8: Makkah | F8: صِرَاطَ الَّذِينَ أَنْعَمْتَ عَلَيْهِمْ غَيْرِ الْمَغْضُوبِ عَلَيْهِمْ وَلَا الضَّالِّينَ | G8: (yaitu) jalan orang-orang yang telah Engkau beri nikmat kepadanya; bukan (jalan) mereka yang dimurkai, dan bukan (pula jalan) mereka yang sesat.3) | H8: Pembagian Manusia: Orang Diberi Nikmat vs. Dimurkai dan Sesat | J8: Ayat ini turun ketika Nabi Muhammad SAW mendengar **suara gaib memanggil namanya** dan beliau sempat menghindar. Atas saran Waraqah bin Naufal, beliau mendengarkan panggilan tersebut yang kemudian menuntunnya membaca syahadat dan surah Al-Fatihah. Riwayat lain menyebutkan bahwa saat Nabi membacanya di Makkah, kaum Quraisy mengejeknya. | K8: False Dichotomy (False Dilemma): Ayat 1:7 membagi manusia menjadi tiga kategori mutlak yang saling eksklusif (orang diberi nikmat, orang dimurkai, orang sesat), mengabaikan spektrum kompleks kepercayaan, moralitas, dan pengalaman spiritual manusia. | L8: (Ayat 1:7): Teks sejak awal mengotakkan manusia ke dalam kelompok yang secara ilahi didiskriminasi, yakni mereka yang "dimurkai" dan "sesat", memupuk kebencian in-group/out-group hanya karena perbedaan arah spiritual. | O8: *3) Mereka yang dimurkai, adalah mereka yang sengaja menentang ajaran Islam. Mereka yang sesat adalah mereka yang sengaja mengambil jalan lain selain ajaran Islam. | P8: (1:7) Surah ini tidak dianggap sebagai bagian riil dari Al-Qur'an oleh salah satu pencatat wahyu utama, Ibnu Mas'ud, yang secara sadar menolak memasukkannya ke dalam mushafnya. (Criticism of the Quran - Wikipedia; The Origins of the Koran) (1:7) Terdapat masalah sintaksis dan pergeseran narator yang kacau; teks ini secara logis adalah doa manusia yang ditujukan kepada Tuhan ("Hanya Engkaulah yang kami sembah"), bukan Tuhan yang sedang berbicara, menunjukkan kesalahan penyajian narasi ilahi. (Criticism of the Quran - Wikipedia)
A9: 2 | B9: 1 | C9: البقرة | D9: Al-Baqarah (Sapi Betina) | E9: Madinah | F9: بِسْمِ اللَّهِ الرَّحْمَٰنِ الرَّحِيمِ الم | G9: Alif Lām Mīm.4) | H9: Pembukaan: Sifat Orang Beriman (1-5) | J9: Ayat ini turun untuk menjelaskan **tiga golongan umat manusia**: empat ayat pertama untuk orang-orang mukmin, dua ayat berikutnya untuk orang kafir, dan tiga belas ayat selanjutnya untuk orang-orang munafik. | K9: Argument from Mystery — Huruf muqatta'ah (Alif Lam Mim) yang tidak memiliki makna linguistik yang disepakati dijadikan pembuka kitab suci, menciptakan aura misteri yang menghambat evaluasi kritis sejak awal. | N9: Huruf Muqatta'at Tidak Bermakna: Ayat ini hanya berisi huruf 'Alif Lam Mim' tanpa makna jelas — bertentangan dengan klaim Quran sebagai 'kitab yang jelas' (16:89, 12:1) dan 'bahasa Arab yang nyata' (16:103); 29 surat mengandung huruf-huruf ini tanpa pernah dijelaskan maknanya oleh Quran itu sendiri. | O9: *4) Beberapa surah dalam Al-Qur`an dibuka dengan huruf abjad seperti Alif Lām Mīm, Alif Lām Rā`, dan sebagainya. Makna huruf-huruf itu hanya Allah yang tahu. Ada yang berpendapat bahwa huruf-huruf itu adalah nama surah dan ada pula yang berpendapat bahwa gunanya untuk menarik perhatian, atau untuk mengisyaratkan bahwa Al-Qur`an itu diturunkan dalam bahasa Arab yang tersusun dari huruf-huruf abjad tersebut.
A10: 2 | B10: 2 | C10: البقرة | D10: Al-Baqarah (Sapi Betina) | E10: Madinah | F10: ذَٰلِكَ الْكِتَابُ لَا رَيْبَ ۛ فِيهِ ۛ هُدًى لِلْمُتَّقِينَ | G10: Kitab (Al-Qur`an) ini tidak ada keraguan padanya; petunjuk bagi mereka yang bertakwa,5) | H10: Pembukaan: Sifat Orang Beriman (1-5) | J10: Ayat ini turun untuk menjelaskan **tiga golongan umat manusia**: empat ayat pertama untuk orang-orang mukmin, dua ayat berikutnya untuk orang kafir, dan tiga belas ayat selanjutnya untuk orang-orang munafik. | K10: Circular Reasoning (Penalaran Melingkar) — Pernyataan 'tidak ada keraguan pada kitab ini' menetapkan kesimpulan (kebenaran kitab) sebagai premis tanpa pembuktian eksternal yang independen. | O10: *5) Takwa yaitu mengikuti segala perintah Allah dan menjauhi segala larangan-Nya.
A11: 2 | B11: 3 | C11: البقرة | D11: Al-Baqarah (Sapi Betina) | E11: Madinah | F11: الَّذِينَ يُؤْمِنُونَ بِالْغَيْبِ وَيُقِيمُونَ الصَّلَاةَ وَمِمَّا رَزَقْنَاهُمْ يُنْفِقُونَ | G11: (Yaitu) mereka yang beriman kepada yang gaib, melaksanakan salat, dan menginfakkan6) sebagian rezeki yang Kami berikan kepada mereka, | H11: Pembukaan: Sifat Orang Beriman (1-5) | O11: *6) Pengertian menginfakkan harta di jalan Allah meliputi belanja untuk kepentingan jihad, pembangunan perguruan, rumah sakit, riset ilmiah dan lain-lain.
A12: 2 | B12: 4 | C12: البقرة | D12: Al-Baqarah (Sapi Betina) | E12: Madinah | F12: وَالَّذِينَ يُؤْمِنُونَ بِمَا أُنْزِلَ إِلَيْكَ وَمَا أُنْزِلَ مِنْ قَبْلِكَ وَبِالْآخِرَةِ هُمْ يُوقِنُونَ | G12: dan mereka beriman kepada (Al-Qur`an) yang diturunkan kepadamu (Muhammad) dan (kitab-kitab) yang telah diturunkan sebelum engkau,7) dan mereka yakin akan adanya akhirat. | H12: Pembukaan: Sifat Orang Beriman (1-5) | O12: *7) Yang diturunkan kepada Nabi-nabi sebelum Nabi Muhammad -ṣallallāhu 'alaihi wa sallam- ialah: Taurat, Zabur, Injil dan Suḥuf (lembaran-lembaran) yang tidak seperti Kitab.
A13: 2 | B13: 5 | C13: البقرة | D13: Al-Baqarah (Sapi Betina) | E13: Madinah | F13: أُولَٰئِكَ عَلَىٰ هُدًى مِنْ رَبِّهِمْ ۖ وَأُولَٰئِكَ هُمُ الْمُفْلِحُونَ | G13: Merekalah yang mendapat petunjuk dari Tuhannya, dan mereka itulah orang-orang yang beruntung. | H13: Pembukaan: Sifat Orang Beriman (1-5) | K13: False Dichotomy (Dikotomi Palsu) — Hanya mereka yang bertakwa yang mendapat petunjuk dan 'beruntung'; ini mengabaikan kemungkinan kebaikan dan kebenaran di luar parameter kelompok ini.
A14: 2 | B14: 6 | C14: البقرة | D14: Al-Baqarah (Sapi Betina) | E14: Madinah | F14: إِنَّ الَّذِينَ كَفَرُوا سَوَاءٌ عَلَيْهِمْ أَأَنْذَرْتَهُمْ أَمْ لَمْ تُنْذِرْهُمْ لَا يُؤْمِنُونَ | G14: Sesungguhnya orang-orang kafir,8) sama saja bagi mereka, engkau (Muhammad) beri peringatan atau tidak engkau beri peringatan, mereka tidak akan beriman. | H14: Sifat Orang Kafir dan Munafik (6-20) | J14: Ayat ini turun berkenaan dengan **Abu Jahal dan enam orang anggota keluarganya**. Pendapat lain menyebutkan ayat ini ditujukan kepada kaum Yahudi. | K14: Predestination Fallacy + Self-Fulfilling Prophecy — Menyatakan bahwa orang kafir 'sama saja diberi peringatan atau tidak' menjadikan kegagalan dakwah seolah sudah ditakdirkan; penolakan dianggap bukti kebenaran, bukan kelemahan argumen. | L14: (Ayat 2:6-7): Tuhan sendiri yang mengunci hati, pendengaran, dan penglihatan orang-orang kafir agar mereka tidak beriman, namun Tuhan pula yang akan menyiksa mereka dengan "azab yang berat". Ini adalah bentuk tirani di mana entitas tertinggi menghukum ciptaan-Nya atas ketidakmampuan yang Ia rekayasa sendiri. | O14: *8) Kafir, jamaknya kuffār, yaitu orang yang tidak percaya kepada Allah, Rasul-rasul-Nya, Malaikat-malaikat-Nya, Kitab-kitab-Nya dan hari Kiamat.
A15: 2 | B15: 7 | C15: البقرة | D15: Al-Baqarah (Sapi Betina) | E15: Madinah | F15: خَتَمَ اللَّهُ عَلَىٰ قُلُوبِهِمْ وَعَلَىٰ سَمْعِهِمْ ۖ وَعَلَىٰ أَبْصَارِهِمْ غِشَاوَةٌ ۖ وَلَهُمْ عَذَابٌ عَظِيمٌ | G15: Allah telah mengunci hati dan pendengaran mereka,9) penglihatan mereka telah tertutup, dan mereka akan mendapat azab yang berat. | H15: Sifat Orang Kafir dan Munafik (6-20) | K15: Argumentum ad Baculum (Ancaman) — Ancaman 'azab yang amat berat' digunakan sebagai persuasi, bukan argumen logis. Pernyataan Allah mengunci hati orang kafir juga menimbulkan pertanyaan tentang keadilan menghukum kondisi yang Allah sendiri ciptakan. | L15: (Ayat 2:6-7): Tuhan sendiri yang mengunci hati, pendengaran, dan penglihatan orang-orang kafir agar mereka tidak beriman, namun Tuhan pula yang akan menyiksa mereka dengan "azab yang berat". Ini adalah bentuk tirani di mana entitas tertinggi menghukum ciptaan-Nya atas ketidakmampuan yang Ia rekayasa sendiri. | O15: *9) Sehingga nasihat atau hidayah tersebut tidak bisa masuk ke dalam hati mereka.
A16: 2 | B16: 8 | C16: البقرة | D16: Al-Baqarah (Sapi Betina) | E16: Madinah | F16: وَمِنَ النَّاسِ مَنْ يَقُولُ آمَنَّا بِاللَّهِ وَبِالْيَوْمِ الْآخِرِ وَمَا هُمْ بِمُؤْمِنِينَ | G16: Dan di antara manusia ada yang berkata, "Kami beriman kepada Allah dan hari akhir," padahal sesungguhnya mereka itu bukanlah orang-orang yang beriman. | H16: Sifat Orang Kafir dan Munafik (6-20) | K16: Mind Reading Fallacy — Klaim bahwa mereka yang berkata 'kami beriman' sesungguhnya 'bukan orang beriman' adalah atribusi niat dan kondisi batin sepihak tanpa akses verifikasi.
A17: 2 | B17: 9 | C17: البقرة | D17: Al-Baqarah (Sapi Betina) | E17: Madinah | F17: يُخَادِعُونَ اللَّهَ وَالَّذِينَ آمَنُوا وَمَا يَخْدَعُونَ إِلَّا أَنْفُسَهُمْ وَمَا يَشْعُرُونَ | G17: Mereka menipu Allah dan orang-orang yang beriman, padahal mereka hanyalah menipu diri sendiri tanpa mereka sadari. | H17: Sifat Orang Kafir dan Munafik (6-20) | K17: Non Sequitur / Self-Contradiction — Tuduhan 'menipu Allah' secara logis kontradiktif dengan premis bahwa Allah Maha Mengetahui; tidak ada yang bisa menipu entitas yang omnisien.
A18: 2 | B18: 10 | C18: البقرة | D18: Al-Baqarah (Sapi Betina) | E18: Madinah | F18: فِي قُلُوبِهِمْ مَرَضٌ فَزَادَهُمُ اللَّهُ مَرَضًا ۖ وَلَهُمْ عَذَابٌ أَلِيمٌ بِمَا كَانُوا يَكْذِبُونَ | G18: Dalam hati mereka terdapat penyakit,10) lalu Allah menambah penyakitnya itu; dan mereka mendapat azab yang pedih, karena mereka berdusta. | H18: Sifat Orang Kafir dan Munafik (6-20) | K18: Argumentum ad Baculum + Victim Blaming — Allah 'menambah penyakit' pada hati yang sudah sakit lalu menghukum mereka; menghukum seseorang atas kondisi yang diperparah secara eksternal adalah kontradiksi etis. | L18: (Ayat 2:10): Alih-alih membimbing atau menyembuhkan, Tuhan dengan sengaja "menambah penyakit" di hati orang yang ragu, menunjukkan karakter Tuhan yang pendendam dan manipulatif terhadap kerentanan psikologis manusia. | O18: *10) Penyakit hati misalnya ragu dan tidak yakin akan kebenaran, munafik dan tidak beriman.
A19: 2 | B19: 11 | C19: البقرة | D19: Al-Baqarah (Sapi Betina) | E19: Madinah | F19: وَإِذَا قِيلَ لَهُمْ لَا تُفْسِدُوا فِي الْأَرْضِ قَالُوا إِنَّمَا نَحْنُ مُصْلِحُونَ | G19: Dan apabila dikatakan kepada mereka, "Janganlah berbuat kerusakan di bumi!"11) Mereka menjawab, "Sesungguhnya kami justru orang-orang yang melakukan perbaikan." | H19: Sifat Orang Kafir dan Munafik (6-20) | K19: Mind Reading Fallacy + Definist Fallacy — Mengklaim mereka 'tidak sadar sedang berbuat kerusakan' adalah atribusi niat sepihak; mendefinisikan perbedaan pandangan sebagai 'kerusakan di bumi' tanpa kriteria yang dapat diverifikasi. | O19: *11) Melanggar nilai-nilai yang ditetapkan agama akan mengakibatkan alam ini rusak bahkan hancur.
A20: 2 | B20: 12 | C20: البقرة | D20: Al-Baqarah (Sapi Betina) | E20: Madinah | F20: أَلَا إِنَّهُمْ هُمُ الْمُفْسِدُونَ وَلَٰكِنْ لَا يَشْعُرُونَ | G20: Ingatlah, sesungguhnya merekalah yang berbuat kerusakan, tetapi mereka tidak menyadari. | H20: Sifat Orang Kafir dan Munafik (6-20)
A21: 2 | B21: 13 | C21: البقرة | D21: Al-Baqarah (Sapi Betina) | E21: Madinah | F21: وَإِذَا قِيلَ لَهُمْ آمِنُوا كَمَا آمَنَ النَّاسُ قَالُوا أَنُؤْمِنُ كَمَا آمَنَ السُّفَهَاءُ ۗ أَلَا إِنَّهُمْ هُمُ السُّفَهَاءُ وَلَٰكِنْ لَا يَعْلَمُونَ | G21: Dan apabila dikatakan kepada mereka, "Berimanlah kamu sebagaimana orang lain yang telah beriman!" Mereka menjawab, "Apakah kami akan beriman seperti orang-orang yang kurang akal itu beriman?" Ingatlah, sesungguhnya mereka itulah orang-orang yang kurang akal, tetapi mereka tidak tahu. | H21: Sifat Orang Kafir dan Munafik (6-20) | K21: Ad Hominem — Menyebut mereka yang tidak mau beriman sebagai 'safaha' (bodoh/kurang akal) adalah serangan terhadap karakter penolak, bukan respons terhadap argumen penolakan.
A22: 2 | B22: 14 | C22: البقرة | D22: Al-Baqarah (Sapi Betina) | E22: Madinah | F22: وَإِذَا لَقُوا الَّذِينَ آمَنُوا قَالُوا آمَنَّا وَإِذَا خَلَوْا إِلَىٰ شَيَاطِينِهِمْ قَالُوا إِنَّا مَعَكُمْ إِنَّمَا نَحْنُ مُسْتَهْزِئُونَ | G22: Dan apabila mereka berjumpa dengan orang yang beriman, mereka berkata, "Kami telah beriman." Tetapi apabila mereka kembali kepada setan-setan (para pemimpin) mereka, mereka berkata, "Sesungguhnya kami bersama kamu, kami hanya berolok-olok." | H22: Sifat Orang Kafir dan Munafik (6-20) | J22: Ayat ini turun berkenaan dengan **Abdullah bin Ubay (tokoh munafik) dan para pengikutnya**. Saat berpapasan dengan sahabat seperti Abu Bakar, Umar, dan Ali, mereka berpura-pura memuji dan menyambut hangat, namun ketika kembali ke kelompoknya, mereka membanggakan kelicikan mereka menipu umat Islam.
A23: 2 | B23: 15 | C23: البقرة | D23: Al-Baqarah (Sapi Betina) | E23: Madinah | F23: اللَّهُ يَسْتَهْزِئُ بِهِمْ وَيَمُدُّهُمْ فِي طُغْيَانِهِمْ يَعْمَهُونَ | G23: Allah akan memperolok-olokkan mereka dan membiarkan mereka terombang-ambing dalam kesesatan. | H23: Sifat Orang Kafir dan Munafik (6-20) | K23: Argumentum ad Baculum — 'Allah memperolok-olokkan mereka dan membiarkan mereka terombang-ambing' menggambarkan respons ilahi sebagai retribusi dan ejekan, bukan argumen. | L23: (Ayat 2:15): Tuhan secara sewenang-wenang "memperolok-olok" manusia dan membiarkan mereka terombang-ambing. Ini merepresentasikan otoritas yang kekanak-kanakan dan gemar mempermainkan penderitaan ciptaannya.
A24: 2 | B24: 16 | C24: البقرة | D24: Al-Baqarah (Sapi Betina) | E24: Madinah | F24: أُولَٰئِكَ الَّذِينَ اشْتَرَوُا الضَّلَالَةَ بِالْهُدَىٰ فَمَا رَبِحَتْ تِجَارَتُهُمْ وَمَا كَانُوا مُهْتَدِينَ | G24: Mereka itulah yang membeli kesesatan dengan petunjuk. Maka perdagangan mereka itu tidak beruntung dan mereka tidak mendapat petunjuk. | H24: Sifat Orang Kafir dan Munafik (6-20)
A25: 2 | B25: 17 | C25: البقرة | D25: Al-Baqarah (Sapi Betina) | E25: Madinah | F25: مَثَلُهُمْ كَمَثَلِ الَّذِي اسْتَوْقَدَ نَارًا فَلَمَّا أَضَاءَتْ مَا حَوْلَهُ ذَهَبَ اللَّهُ بِنُورِهِمْ وَتَرَكَهُمْ فِي ظُلُمَاتٍ لَا يُبْصِرُونَ | G25: Perumpamaan mereka seperti orang-orang yang menyalakan api, setelah menerangi sekelilingnya, Allah melenyapkan cahaya (yang menyinari) mereka dan membiarkan mereka dalam kegelapan, tidak dapat melihat. | H25: Sifat Orang Kafir dan Munafik (6-20) | L25: (Ayat 2:17-20): Teks mendehumanisasi orang-orang yang tidak sepaham dengan melabeli mereka sebagai sosok yang tuli, bisu, dan buta, serta mengancam akan merampas fungsi indera mereka secara paksa. Ini adalah bentuk perendahan martabat kelompok oposisi.
A26: 2 | B26: 18 | C26: البقرة | D26: Al-Baqarah (Sapi Betina) | E26: Madinah | F26: صُمٌّ بُكْمٌ عُمْيٌ فَهُمْ لَا يَرْجِعُونَ | G26: Mereka tuli, bisu dan buta, sehingga mereka tidak dapat kembali. | H26: Sifat Orang Kafir dan Munafik (6-20) | L26: (Ayat 2:17-20): Teks mendehumanisasi orang-orang yang tidak sepaham dengan melabeli mereka sebagai sosok yang tuli, bisu, dan buta, serta mengancam akan merampas fungsi indera mereka secara paksa. Ini adalah bentuk perendahan martabat kelompok oposisi.
A27: 2 | B27: 19 | C27: البقرة | D27: Al-Baqarah (Sapi Betina) | E27: Madinah | F27: أَوْ كَصَيِّبٍ مِنَ السَّمَاءِ فِيهِ ظُلُمَاتٌ وَرَعْدٌ وَبَرْقٌ يَجْعَلُونَ أَصَابِعَهُمْ فِي آذَانِهِمْ مِنَ الصَّوَاعِقِ حَذَرَ الْمَوْتِ ۚ وَاللَّهُ مُحِيطٌ بِالْكَافِرِينَ | G27: Atau seperti (orang yang ditimpa) hujan lebat dari langit, yang disertai kegelapan, petir dan kilat. Mereka menyumbat telinga dengan jari-jarinya, (menghindari) suara petir itu karena takut mati. Allah meliputi orang-orang yang kafir.12) | H27: Sifat Orang Kafir dan Munafik (6-20) | I27: Ayat 19 (Kehilangan Rima): Secara analisis teks, pakar bahasa Jacob Barth mencatat bahwa ayat ini tampaknya tidak lengkap; ada kemungkinan bagian teks yang mengandung rima telah hilang atau terpotong | L27: (Ayat 2:17-20): Teks mendehumanisasi orang-orang yang tidak sepaham dengan melabeli mereka sebagai sosok yang tuli, bisu, dan buta, serta mengancam akan merampas fungsi indera mereka secara paksa. Ini adalah bentuk perendahan martabat kelompok oposisi. | O27: *12) Pengetahuan dan kekuasaan Allah meliputi orang-orang kafir.
A28: 2 | B28: 20 | C28: البقرة | D28: Al-Baqarah (Sapi Betina) | E28: Madinah | F28: يَكَادُ الْبَرْقُ يَخْطَفُ أَبْصَارَهُمْ ۖ كُلَّمَا أَضَاءَ لَهُمْ مَشَوْا فِيهِ وَإِذَا أَظْلَمَ عَلَيْهِمْ قَامُوا ۚ وَلَوْ شَاءَ اللَّهُ لَذَهَبَ بِسَمْعِهِمْ وَأَبْصَارِهِمْ ۚ إِنَّ اللَّهَ عَلَىٰ كُلِّ شَيْءٍ قَدِيرٌ | G28: Hampir saja kilat itu menyambar penglihatan mereka. Setiap kali (kilat itu) menyinari, mereka berjalan di bawah (sinar) itu, dan apabila gelap menerpa mereka, mereka berhenti. Sekiranya Allah menghendaki, niscaya Dia hilangkan pendengaran dan penglihatan mereka. Sungguh, Allah Mahakuasa atas segala sesuatu. | H28: Sifat Orang Kafir dan Munafik (6-20) | L28: (Ayat 2:17-20): Teks mendehumanisasi orang-orang yang tidak sepaham dengan melabeli mereka sebagai sosok yang tuli, bisu, dan buta, serta mengancam akan merampas fungsi indera mereka secara paksa. Ini adalah bentuk perendahan martabat kelompok oposisi.
A29: 2 | B29: 21 | C29: البقرة | D29: Al-Baqarah (Sapi Betina) | E29: Madinah | F29: يَا أَيُّهَا النَّاسُ اعْبُدُوا رَبَّكُمُ الَّذِي خَلَقَكُمْ وَالَّذِينَ مِنْ قَبْلِكُمْ لَعَلَّكُمْ تَتَّقُونَ | G29: Wahai manusia! Sembahlah Tuhanmu yang telah menciptakan kamu dan orang-orang yang sebelum kamu, agar kamu bertakwa. | H29: Seruan Tauhid dan Tantangan Al-Quran (21-24) | J29: Ayat ini turun sebagai **seruan langsung kepada kaum musyrik Makkah** untuk menyembah Tuhan mereka. | K29: Appeal to Authority + Circular Reasoning — Perintah menyembah Allah didasarkan pada klaim bahwa Allah adalah pencipta; mengikuti perintah karena yang memerintahkan adalah pencipta adalah circular tanpa standar evaluasi independen.
A30: 2 | B30: 22 | C30: البقرة | D30: Al-Baqarah (Sapi Betina) | E30: Madinah | F30: الَّذِي جَعَلَ لَكُمُ الْأَرْضَ فِرَاشًا وَالسَّمَاءَ بِنَاءً وَأَنْزَلَ مِنَ السَّمَاءِ مَاءً فَأَخْرَجَ بِهِ مِنَ الثَّمَرَاتِ رِزْقًا لَكُمْ ۖ فَلَا تَجْعَلُوا لِلَّهِ أَنْدَادًا وَأَنْتُمْ تَعْلَمُونَ | G30: (Dialah) yang menjadikan bumi sebagai hamparan bagimu dan langit sebagai atap, dan Dialah yang menurunkan air (hujan) dari langit, lalu Dia hasilkan dengan (hujan) itu buah-buahan sebagai rezeki untukmu. Karena itu janganlah kamu mengadakan tandingan-tandingan bagi Allah, padahal kamu mengetahui. | H30: Seruan Tauhid dan Tantangan Al-Quran (21-24) | K30: False Cosmology Embedded in Text — Langit digambarkan sebagai 'bangunan' (binaa) di atas bumi; ini mencerminkan kosmologi kuno (langit sebagai atap/kanopi) yang tidak sesuai dengan pemahaman sains tentang atmosfer dan ruang angkasa. | M30: Kosmologi Kuno: Langit sebagai Bangunan/Kanopi — Langit digambarkan sebagai 'bangunan' (binaa) yang dibangun di atas bumi; kosmologi ini konsisten dengan pandangan abad ke-7 tentang langit sebagai atap/kanopi, bertentangan dengan sains modern yang menunjukkan atmosfer adalah lapisan gas, bukan struktur bangunan. (Ref: Scientific Errors - Sky as Ceiling)
A31: 2 | B31: 23 | C31: البقرة | D31: Al-Baqarah (Sapi Betina) | E31: Madinah | F31: وَإِنْ كُنْتُمْ فِي رَيْبٍ مِمَّا نَزَّلْنَا عَلَىٰ عَبْدِنَا فَأْتُوا بِسُورَةٍ مِنْ مِثْلِهِ وَادْعُوا شُهَدَاءَكُمْ مِنْ دُونِ اللَّهِ إِنْ كُنْتُمْ صَادِقِينَ | G31: Dan jika kamu meragukan (Al-Qur`an) yang kami turunkan kepada hamba Kami (Muhammad), maka buatlah satu surah semisal dengannya dan ajaklah penolong-penolongmu selain Allah, jika kamu orang-orang yang benar. | H31: Seruan Tauhid dan Tantangan Al-Quran (21-24) | K31: Circular Reasoning + Begging the Question — Tantangan 'datangkan satu surat semisal' mengandaikan Quran sudah terbukti luar biasa sebagai premis; standar 'semisal' juga ditentukan sepihak oleh sumber yang menantang.
A32: 2 | B32: 24 | C32: البقرة | D32: Al-Baqarah (Sapi Betina) | E32: Madinah | F32: فَإِنْ لَمْ تَفْعَلُوا وَلَنْ تَفْعَلُوا فَاتَّقُوا النَّارَ الَّتِي وَقُودُهَا النَّاسُ وَالْحِجَارَةُ ۖ أُعِدَّتْ لِلْكَافِرِينَ | G32: Jika kamu tidak mampu membuatnya, dan (pasti) tidak akan mampu, maka takutlah kamu akan api neraka yang bahan bakarnya manusia dan batu yang disediakan bagi orang-orang kafir. | H32: Seruan Tauhid dan Tantangan Al-Quran (21-24) | K32: Argumentum ad Baculum — Ancaman neraka 'yang bahan bakarnya manusia dan batu' digunakan sebagai argumen untuk menerima kebenaran Al-Quran, bukan pembuktian logis. | L32: (Ayat 2:24): Teks mengeksploitasi teror psikologis yang ekstrem dengan mengancam orang-orang yang tidak percaya dengan api neraka yang bahan bakarnya adalah "manusia dan batu". Ini merupakan glorifikasi terhadap penyiksaan barbar.
A33: 2 | B33: 25 | C33: البقرة | D33: Al-Baqarah (Sapi Betina) | E33: Madinah | F33: وَبَشِّرِ الَّذِينَ آمَنُوا وَعَمِلُوا الصَّالِحَاتِ أَنَّ لَهُمْ جَنَّاتٍ تَجْرِي مِنْ تَحْتِهَا الْأَنْهَارُ ۖ كُلَّمَا رُزِقُوا مِنْهَا مِنْ ثَمَرَةٍ رِزْقًا ۙ قَالُوا هَٰذَا الَّذِي رُزِقْنَا مِنْ قَبْلُ ۖ وَأُتُوا بِهِ مُتَشَابِهًا ۖ وَلَهُمْ فِيهَا أَزْوَاجٌ مُطَهَّرَةٌ ۖ وَهُمْ فِيهَا خَالِدُونَ | G33: Dan sampaikanlah kabar gembira kepada orang-orang yang beriman dan berbuat kebajikan, bahwa untuk mereka (disediakan) surga-surga yang mengalir di bawahnya sungai-sungai. Setiap kali mereka diberi rezeki buah-buahan dari surga, mereka berkata, "Inilah rezeki yang diberikan kepada kami dahulu." Mereka telah diberi (buah-buahan) yang serupa. Dan di sana mereka (memperoleh) pasangan-pasangan yang suci. Mereka kekal di dalamnya. | H33: Kabar Surga, Perumpamaan, dan Penciptaan Alam (25-29)
A34: 2 | B34: 26 | C34: البقرة | D34: Al-Baqarah (Sapi Betina) | E34: Madinah | F34: إِنَّ اللَّهَ لَا يَسْتَحْيِي أَنْ يَضْرِبَ مَثَلًا مَا بَعُوضَةً فَمَا فَوْقَهَا ۚ فَأَمَّا الَّذِينَ آمَنُوا فَيَعْلَمُونَ أَنَّهُ الْحَقُّ مِنْ رَبِّهِمْ ۖ وَأَمَّا الَّذِينَ كَفَرُوا فَيَقُولُونَ مَاذَا أَرَادَ اللَّهُ بِهَٰذَا مَثَلًا ۘ يُضِلُّ بِهِ كَثِيرًا وَيَهْدِي بِهِ كَثِيرًا ۚ وَمَا يُضِلُّ بِهِ إِلَّا الْفَاسِقِينَ | G34: Sesungguhnya Allah tidak segan membuat perumpamaan seekor nyamuk atau yang lebih kecil dari itu. Adapun orang-orang yang beriman, mereka tahu bahwa itu kebenaran dari Tuhan. Tetapi mereka yang kafir berkata, "Apa maksud Allah dengan perumpamaan ini?" Dengan (perumpamaan) itu banyak orang yang disesatkan-Nya,13) dan dengan itu banyak (pula) orang yang diberi-Nya petunjuk. Tetapi tidak ada yang Dia sesatkan dengan (perumpamaan) itu selain orang-orang fasik,14) | H34: Kabar Surga, Perumpamaan, dan Penciptaan Alam (25-29) | J34: Ayat ini turun untuk menanggapi **ejekan orang-orang munafik dan Yahudi** yang menertawakan firman Allah karena menggunakan perumpamaan hewan kecil seperti lalat, nyamuk, dan laba-laba. | K34: Appeal to Ridicule + Circular Reasoning — Framing 'Allah tidak malu membuat perumpamaan nyamuk' mengantisipasi penolakan dengan merendahkan pihak yang meragukan, sekaligus mengasumsikan kebenaran sumber sebagai premis. | L34: (Ayat 2:26): Tuhan secara terbuka mengakui sengaja membuat perumpamaan untuk "menyesatkan" banyak orang. Menjadikan Tuhan sebagai agen penipuan (entrapment) yang kemudian menyalahkan korban kesesatan tersebut. | O34: *13) Orang itu sesat karena keingkarannya dan tidak mau memahami petunjuk-petunjuk Allah. Dalam ayat ini, karena mereka itu ingkar, dan tidak mau memahami apa sebabnya Allah menjadikan nyamuk sebagai perumpamaan, maka mereka itu menjadi sesat. *14) Orang fasik ialah orang yang melanggar ketentuan-ketentuan agama, baik berupa ucapan maupun perbuatan.
A35: 2 | B35: 27 | C35: البقرة | D35: Al-Baqarah (Sapi Betina) | E35: Madinah | F35: الَّذِينَ يَنْقُضُونَ عَهْدَ اللَّهِ مِنْ بَعْدِ مِيثَاقِهِ وَيَقْطَعُونَ مَا أَمَرَ اللَّهُ بِهِ أَنْ يُوصَلَ وَيُفْسِدُونَ فِي الْأَرْضِ ۚ أُولَٰئِكَ هُمُ الْخَاسِرُونَ | G35: (yaitu) orang–orang yang melanggar perjanjian Allah setelah (perjanjian) itu diteguhkan, dan memutuskan apa yang diperintahkan Allah untuk disambungkan dan berbuat kerusakan di bumi. Mereka itulah orang-orang yang rugi. | H35: Kabar Surga, Perumpamaan, dan Penciptaan Alam (25-29)
A36: 2 | B36: 28 | C36: البقرة | D36: Al-Baqarah (Sapi Betina) | E36: Madinah | F36: كَيْفَ تَكْفُرُونَ بِاللَّهِ وَكُنْتُمْ أَمْوَاتًا فَأَحْيَاكُمْ ۖ ثُمَّ يُمِيتُكُمْ ثُمَّ يُحْيِيكُمْ ثُمَّ إِلَيْهِ تُرْجَعُونَ | G36: Bagaimana kamu ingkar kepada Allah, padahal kamu (tadinya) mati, lalu Dia menghidupkan kamu, kemudian Dia mematikan kamu, lalu Dia menghidupkan kamu kembali. Kemudian kepada-Nyalah kamu dikembalikan. | H36: Kabar Surga, Perumpamaan, dan Penciptaan Alam (25-29) | K36: Rhetorical Question as Non Sequitur — 'Bagaimana kamu bisa ingkar kepada Allah?' adalah pertanyaan yang mengandaikan kebenaran klaim sebagai sudah terbukti, bukan argumen yang membuktikannya. | P36: (2:28) Kisah Adam yang lebih pintar karena bisa menamai binatang bukanlah sejarah kenabian yang murni, melainkan hasil jiplakan dari legenda Yahudi Midrash Rabbah dan Sanhedrin 38. (The Origins of the Koran)
A37: 2 | B37: 29 | C37: البقرة | D37: Al-Baqarah (Sapi Betina) | E37: Madinah | F37: هُوَ الَّذِي خَلَقَ لَكُمْ مَا فِي الْأَرْضِ جَمِيعًا ثُمَّ اسْتَوَىٰ إِلَى السَّمَاءِ فَسَوَّاهُنَّ سَبْعَ سَمَاوَاتٍ ۚ وَهُوَ بِكُلِّ شَيْءٍ عَلِيمٌ | G37: Dialah (Allah) yang menciptakan segala apa yang ada di bumi untuk kalian kemudian Dia menuju ke langit, lalu Dia menyempurnakannya menjadi tujuh langit. Dan Dia Maha Mengetahui segala sesuatu. | H37: Kabar Surga, Perumpamaan, dan Penciptaan Alam (25-29) | M37: Urutan Penciptaan Keliru: Bumi Lebih Dahulu dari Bintang — Ayat ini menyatakan Allah menciptakan semua yang ada di bumi, baru kemudian langit dijadikan tujuh lapis; bertentangan dengan kosmologi modern: alam semesta berusia 13,8 miliar tahun, bumi baru terbentuk 4,5 miliar tahun lalu dari materi yang sebelumnya ada di 'langit' (bintang). (Ref: Scientific Errors - Earth Created Before Stars) | N37: Kontradiksi Urutan Penciptaan — Ayat ini menyatakan bumi dan isinya diciptakan lebih dulu, baru langit dijadikan tujuh lapis; bertentangan dengan 79:27-33 yang menyatakan langit dibangun sebelum bumi dihamparkan. Kedua versi tidak dapat dikompromikan. (Ref: Kontradiksi - Urutan Penciptaan) | P37: (2:29) Kisah Adam yang lebih pintar karena bisa menamai binatang bukanlah sejarah kenabian yang murni, melainkan hasil jiplakan dari legenda Yahudi Midrash Rabbah dan Sanhedrin 38. (The Origins of the Koran)
A38: 2 | B38: 30 | C38: البقرة | D38: Al-Baqarah (Sapi Betina) | E38: Madinah | F38: وَإِذْ قَالَ رَبُّكَ لِلْمَلَائِكَةِ إِنِّي جَاعِلٌ فِي الْأَرْضِ خَلِيفَةً ۖ قَالُوا أَتَجْعَلُ فِيهَا مَنْ يُفْسِدُ فِيهَا وَيَسْفِكُ الدِّمَاءَ وَنَحْنُ نُسَبِّحُ بِحَمْدِكَ وَنُقَدِّسُ لَكَ ۖ قَالَ إِنِّي أَعْلَمُ مَا لَا تَعْلَمُونَ | G38: Dan (ingatlah) ketika Tuhanmu berfirman kepada para Malaikat, "Aku hendak menjadikan khalifah15) di bumi". Mereka berkata, "Apakah Engkau hendak menjadikan orang yang merusak dan menumpahkan darah di sana, sedangkan kami bertasbih memuji-Mu dan menyucikan nama-Mu?" Dia berfirman, "Sungguh, Aku mengetahui apa yang tidak kalian ketahui." | H38: Kisah Penciptaan Adam dan Turunnya ke Bumi (30-39) | O38: *15) Khalifah bermakna pengganti, pemimpin atau penguasa. | P38: (2:30) Kisah Adam yang lebih pintar karena bisa menamai binatang bukanlah sejarah kenabian yang murni, melainkan hasil jiplakan dari legenda Yahudi Midrash Rabbah dan Sanhedrin 38. (The Origins of the Koran) (2:30) Penggunaan kata "khalifah" keliru secara semantik mengubah citra teologis alkitabiah tentang penciptaan manusia dari "gambar/rupa Allah" menjadi sekadar "penerus" atau "pengganti" biologis di bumi. (The Qur'an: A Historical-Critical Introduction,) | Q38: Kisah Tuhan yang mengumumkan penciptaan manusia dan protes malaikat yang merespons "mereka akan menumpahkan darah" adalah jiplakan dan modifikasi dari literatur apokrifa Yahudi *Book of Watchers* (Kitab Henokh) serta legenda rabinik terkait generasi Air Bah, yang secara kikuk direlokasi menjadi narasi penciptaan awal umat manusia,.
A39: 2 | B39: 31 | C39: البقرة | D39: Al-Baqarah (Sapi Betina) | E39: Madinah | F39: وَعَلَّمَ آدَمَ الْأَسْمَاءَ كُلَّهَا ثُمَّ عَرَضَهُمْ عَلَى الْمَلَائِكَةِ فَقَالَ أَنْبِئُونِي بِأَسْمَاءِ هَٰؤُلَاءِ إِنْ كُنْتُمْ صَادِقِينَ | G39: Dan Dia ajarkan kepada Adam nama-nama (benda) semuanya, kemudian Dia perlihatkan kepada para malaikat, seraya berfirman, "Sebutkan kepada-Ku nama semua benda ini, jika kalian yang benar!" | H39: Kisah Penciptaan Adam dan Turunnya ke Bumi (30-39) | M39: Mitos Linguistik: Allah Mengajarkan Semua Nama kepada Adam — Klaim bahwa bahasa berasal dari pengajaran ilahi kepada satu manusia bertentangan dengan fakta bahwa bahasa manusia berkembang secara evolutif selama ratusan ribu tahun; lebih dari 7.000 bahasa yang ada di dunia menunjukkan perkembangan organik, bukan sumber tunggal ilahi. | P39: (2:31) Kisah Adam yang lebih pintar karena bisa menamai binatang bukanlah sejarah kenabian yang murni, melainkan hasil jiplakan dari legenda Yahudi Midrash Rabbah dan Sanhedrin 38. (The Origins of the Koran)
A40: 2 | B40: 32 | C40: البقرة | D40: Al-Baqarah (Sapi Betina) | E40: Madinah | F40: قَالُوا سُبْحَانَكَ لَا عِلْمَ لَنَا إِلَّا مَا عَلَّمْتَنَا ۖ إِنَّكَ أَنْتَ الْعَلِيمُ الْحَكِيمُ | G40: Mereka menjawab, "Mahasuci Engkau, tidak ada yang kami ketahui selain apa yang telah Engkau ajarkan kepada kami. Sungguh, Engkaulah Yang Maha Mengetahui, Mahabijaksana." | H40: Kisah Penciptaan Adam dan Turunnya ke Bumi (30-39) | P40: (2:32) Kisah Adam yang lebih pintar karena bisa menamai binatang bukanlah sejarah kenabian yang murni, melainkan hasil jiplakan dari legenda Yahudi Midrash Rabbah dan Sanhedrin 38. (The Origins of the Koran)
A41: 2 | B41: 33 | C41: البقرة | D41: Al-Baqarah (Sapi Betina) | E41: Madinah | F41: قَالَ يَا آدَمُ أَنْبِئْهُمْ بِأَسْمَائِهِمْ ۖ فَلَمَّا أَنْبَأَهُمْ بِأَسْمَائِهِمْ قَالَ أَلَمْ أَقُلْ لَكُمْ إِنِّي أَعْلَمُ غَيْبَ السَّمَاوَاتِ وَالْأَرْضِ وَأَعْلَمُ مَا تُبْدُونَ وَمَا كُنْتُمْ تَكْتُمُونَ | G41: Dia (Allah) berfirman, "Wahai Adam! Beritahukanlah kepada mereka nama-nama itu!" Setelah dia (Adam) menyebutkan nama-namanya, Dia berfirman, "Bukankah telah Aku katakan kepada kalian, bahwa Aku mengetahui rahasia langit dan bumi, dan Aku mengetahui apa yang kalian nyatakan dan apa yang kalian sembunyikan?" | H41: Kisah Penciptaan Adam dan Turunnya ke Bumi (30-39)
A42: 2 | B42: 34 | C42: البقرة | D42: Al-Baqarah (Sapi Betina) | E42: Madinah | F42: وَإِذْ قُلْنَا لِلْمَلَائِكَةِ اسْجُدُوا لِآدَمَ فَسَجَدُوا إِلَّا إِبْلِيسَ أَبَىٰ وَاسْتَكْبَرَ وَكَانَ مِنَ الْكَافِرِينَ | G42: Dan (ingatlah) ketika Kami berfirman kepada para malaikat, "Sujudlah kalian kepada Adam!" Maka mereka pun sujud kecuali Iblis.16) Ia menolak dan menyombongkan diri, dan ia termasuk golongan yang kafir. | H42: Kisah Penciptaan Adam dan Turunnya ke Bumi (30-39) | O42: *16) Iblis termasuk kelompok jin dan termasuk yang diperintah untuk sujud.
A43: 2 | B43: 35 | C43: البقرة | D43: Al-Baqarah (Sapi Betina) | E43: Madinah | F43: وَقُلْنَا يَا آدَمُ اسْكُنْ أَنْتَ وَزَوْجُكَ الْجَنَّةَ وَكُلَا مِنْهَا رَغَدًا حَيْثُ شِئْتُمَا وَلَا تَقْرَبَا هَٰذِهِ الشَّجَرَةَ فَتَكُونَا مِنَ الظَّالِمِينَ | G43: Dan Kami berfirman: "Wahai Adam! Tinggallah engkau dan istrimu di dalam surga, dan makanlah dengan nikmat (berbagai makanan) yang ada di sana sesukamu. (Tetapi) janganlah kamu dekati pohon ini,17) nanti kamu termasuk orang-orang yang zalim!"18) | H43: Kisah Penciptaan Adam dan Turunnya ke Bumi (30-39) | O43: *17) Menurut setan, siapa yang memakan buah pohon itu, akan kekal di dalam surga (lihat surah Ṭāhā (20): 120). 18) Zalim artinya aniaya. Orang yang zalim ialah orang yang melakukan perbuatan aniaya, yang merugikan dirinya sendiri maupun orang lain.
A44: 2 | B44: 36 | C44: البقرة | D44: Al-Baqarah (Sapi Betina) | E44: Madinah | F44: فَأَزَلَّهُمَا الشَّيْطَانُ عَنْهَا فَأَخْرَجَهُمَا مِمَّا كَانَا فِيهِ ۖ وَقُلْنَا اهْبِطُوا بَعْضُكُمْ لِبَعْضٍ عَدُوٌّ ۖ وَلَكُمْ فِي الْأَرْضِ مُسْتَقَرٌّ وَمَتَاعٌ إِلَىٰ حِينٍ | G44: Lalu setan menggelincirkan keduanya dari surga19) sehingga keduanya dikeluarkan dari (segala kenikmatan) ketika keduanya di sana (surga). Dan Kami berfirman, "Turunlah kalian! Sebagian kalian menjadi musuh bagi yang lain. Dan bagi kalian ada tempat tinggal dan kesenangan di bumi sampai waktu yang ditentukan." | H44: Kisah Penciptaan Adam dan Turunnya ke Bumi (30-39) | I44: Ayat 36a (Duplikasi/Salah Tempat): Kalimat pada bagian ini adalah doublet (pengulangan yang identik) dari ayat 34, yang tampaknya disisipkan secara keliru dan tidak pada tempatnya setelah ayat 35 | N44: Kontradiksi Narasi Turunnya Adam (1) — Perintah turun 'sebagai musuh satu sama lain' muncul di sini SEBELUM pengampunan Adam (37); sedangkan 20:121-123 menyatakan Allah mengampuni Adam SEBELUM memerintahkan turun. Urutan kronologis antara 2:36-37 dan 20:122-123 saling bertentangan. (Ref: Kontradiksi.txt - The Forgiveness of Adam) | O44: *19) Nabi Adam -'alaihissalām- dan Hawa memakan buah pohon yang dilarang itu, yang mengakibatkan mereka diusir Allah dari surga dan diturunkan ke dunia.
A45: 2 | B45: 37 | C45: البقرة | D45: Al-Baqarah (Sapi Betina) | E45: Madinah | F45: فَتَلَقَّىٰ آدَمُ مِنْ رَبِّهِ كَلِمَاتٍ فَتَابَ عَلَيْهِ ۚ إِنَّهُ هُوَ التَّوَّابُ الرَّحِيمُ | G45: Kemudian Adam menerima beberapa kalimat20) dari Tuhannya, lalu Dia pun menerima tobatnya. Sungguh, Allah Maha Penerima tobat, Maha Penyayang. | H45: Kisah Penciptaan Adam dan Turunnya ke Bumi (30-39) | N45: Kontradiksi Narasi Turunnya Adam (2) — Pengampunan Allah dicatat SETELAH perintah turun pertama (2:36); sedangkan 20:122 menyatakan pengampunan terjadi SEBELUM perintah turun. Surat 2 tampaknya menggabungkan dua versi berbeda dari Surat 7 dan Surat 20. (Ref: Kontradiksi.txt - The Forgiveness of Adam) | O45: *20) Kalimat itu menurut sebagian mufasir adalah ucapan untuk memohon ampunan (tobat).
A46: 2 | B46: 38 | C46: البقرة | D46: Al-Baqarah (Sapi Betina) | E46: Madinah | F46: قُلْنَا اهْبِطُوا مِنْهَا جَمِيعًا ۖ فَإِمَّا يَأْتِيَنَّكُمْ مِنِّي هُدًى فَمَنْ تَبِعَ هُدَايَ فَلَا خَوْفٌ عَلَيْهِمْ وَلَا هُمْ يَحْزَنُونَ | G46: Kami berfirman, "Turunlah kalian semua dari surga! Kemudian jika benar-benar datang petunjuk-Ku kepada kalian, maka siapa yang mengikuti petunjuk-Ku, tidak ada rasa takut bagi mereka dan mereka tidak bersedih hati." | H46: Kisah Penciptaan Adam dan Turunnya ke Bumi (30-39) | N46: Duplikasi Perintah Turun — Perintah untuk turun dari surga muncul dua kali dalam surat ini: 2:36 dan 2:38; ini adalah indikasi penggabungan dua versi cerita Adam yang berbeda (dari Surat 7 dan Surat 20) yang menghasilkan duplikasi narasi. (Ref: Kontradiksi.txt - The Forgiveness of Adam)
A47: 2 | B47: 39 | C47: البقرة | D47: Al-Baqarah (Sapi Betina) | E47: Madinah | F47: وَالَّذِينَ كَفَرُوا وَكَذَّبُوا بِآيَاتِنَا أُولَٰئِكَ أَصْحَابُ النَّارِ ۖ هُمْ فِيهَا خَالِدُونَ | G47: Adapun orang-orang yang kafir dan mendustakan ayat-ayat Kami, mereka itu penghuni neraka. Mereka kekal di dalamnya. | H47: Kisah Penciptaan Adam dan Turunnya ke Bumi (30-39) | K47: Argumentum ad Baculum — Ancaman kekal di neraka dijatuhkan pada mereka yang 'mendustakan tanda-tanda Kami'; konsekuensi ekstrem (keabadian azab) digunakan sebagai deterrence, bukan pembuktian. | L47: (Ayat 2:39): Memberikan vonis siksaan neraka yang kekal selamanya hanya karena "mendustakan ayat-ayat". Hukuman penyiksaan tanpa batas untuk kejahatan tanpa korban (victimless crime) berupa penolakan dogma adalah ketidakadilan yang absolut.
A48: 2 | B48: 40 | C48: البقرة | D48: Al-Baqarah (Sapi Betina) | E48: Madinah | F48: يَا بَنِي إِسْرَائِيلَ اذْكُرُوا نِعْمَتِيَ الَّتِي أَنْعَمْتُ عَلَيْكُمْ وَأَوْفُوا بِعَهْدِي أُوفِ بِعَهْدِكُمْ وَإِيَّايَ فَارْهَبُونِ | G48: Wahai Bani Israil!21) Ingatlah nikmat-Ku yang telah Aku berikan kepadamu. Dan penuhilah janjimu kepada-Ku,22) niscaya Aku penuhi janji-Ku kepadamu, dan takutlah kepada-Ku saja. | H48: Peringatan dan Seruan kepada Bani Israel (40-46) | K48: Appeal to Reciprocity tanpa Asimetri — 'Penuhilah janji kepada-Ku, Aku penuhi janji-Ku' membangun relasi transaksional yang asimetris: manusia dapat diverifikasi gagal, sedangkan pemenuhan janji Allah tidak dapat diverifikasi. | O48: *21) Israil adalah sebutan bagi Nabi Yakub -'alaihissalām-. Bani Israil adalah keturunan Nabi Yakub -'alaihissalām- dan sekarang dikenal dengan nama bangsa Yahudi. 22) Di antara janji Bani Israil kepada Allah ialah hanya menyembah Allah, tidak mengadakan tandingan bagi Allah, serta beriman kepada Nabi Muhammad -ṣallallāhu 'alaihi wa sallam- sebagaimana yang tersebut di dalam Taurat.
A49: 2 | B49: 41 | C49: البقرة | D49: Al-Baqarah (Sapi Betina) | E49: Madinah | F49: وَآمِنُوا بِمَا أَنْزَلْتُ مُصَدِّقًا لِمَا مَعَكُمْ وَلَا تَكُونُوا أَوَّلَ كَافِرٍ بِهِ ۖ وَلَا تَشْتَرُوا بِآيَاتِي ثَمَنًا قَلِيلًا وَإِيَّايَ فَاتَّقُونِ | G49: Dan berimanlah kalian kepada apa (Al-Qur`an) yang telah Aku turunkan, yang membenarkan apa (Taurat) yang ada pada kalian, dan janganlah kalian menjadi orang yang pertama kafir kepadanya. Janganlah kalian jual ayat-ayat-Ku dengan harga yang murah, dan bertakwalah hanya kepada-Ku. | H49: Peringatan dan Seruan kepada Bani Israel (40-46) | K49: Circular Reasoning — 'Berimanlah kepada Quran yang membenarkan apa yang ada pada kamu' mengandaikan bahwa kesesuaian dengan tradisi lain membuktikan kebenaran, tanpa argumen independen.
A50: 2 | B50: 42 | C50: البقرة | D50: Al-Baqarah (Sapi Betina) | E50: Madinah | F50: وَلَا تَلْبِسُوا الْحَقَّ بِالْبَاطِلِ وَتَكْتُمُوا الْحَقَّ وَأَنْتُمْ تَعْلَمُونَ | G50: Dan janganlah kalian campuradukkan kebenaran dengan kebatilan23) dan (janganlah) kalian sembunyikan kebenaran, sedangkan kalian mengetahuinya. | H50: Peringatan dan Seruan kepada Bani Israel (40-46) | K50: Equivocation (Kerancuan Makna) — 'Jangan mencampurkan kebenaran dengan kebatilan' tanpa mendefinisikan keduanya secara objektif memungkinkan siapa saja mengklaim posisi mereka sebagai 'kebenaran' dan pihak lain sebagai 'kebatilan.' | O50: *23) Batil artinya kesalahan, kejahatan, kemungkaran dan sebagainya.
A51: 2 | B51: 43 | C51: البقرة | D51: Al-Baqarah (Sapi Betina) | E51: Madinah | F51: وَأَقِيمُوا الصَّلَاةَ وَآتُوا الزَّكَاةَ وَارْكَعُوا مَعَ الرَّاكِعِينَ | G51: Dan laksanakanlah salat, tunaikanlah zakat dan rukuklah beserta orang yang rukuk. | H51: Peringatan dan Seruan kepada Bani Israel (40-46)
A52: 2 | B52: 44 | C52: البقرة | D52: Al-Baqarah (Sapi Betina) | E52: Madinah | F52: أَتَأْمُرُونَ النَّاسَ بِالْبِرِّ وَتَنْسَوْنَ أَنْفُسَكُمْ وَأَنْتُمْ تَتْلُونَ الْكِتَابَ ۚ أَفَلَا تَعْقِلُونَ | G52: Mengapa kalian menyuruh orang lain (mengerjakan) kebajikan, sedangkan kalian melupakan diri kalian sendiri, padahal kalian membaca Kitab (Taurat)? Tidakkah kalian mengerti? | H52: Peringatan dan Seruan kepada Bani Israel (40-46) | J52: Ayat ini turun berkenaan dengan **tokoh-tokoh Yahudi Madinah** yang sering menyuruh kerabat atau kenalan mereka untuk memeluk dan teguh pada ajaran Islam, namun mereka sendiri enggan melakukannya.
A53: 2 | B53: 45 | C53: البقرة | D53: Al-Baqarah (Sapi Betina) | E53: Madinah | F53: وَاسْتَعِينُوا بِالصَّبْرِ وَالصَّلَاةِ ۚ وَإِنَّهَا لَكَبِيرَةٌ إِلَّا عَلَى الْخَاشِعِينَ | G53: Dan mohonlah pertolongan (kepada Allah) dengan sabar dan salat. Dan (salat) itu sungguh berat, kecuali bagi orang-orang yang khusyuk, | H53: Peringatan dan Seruan kepada Bani Israel (40-46) | J53: Ayat ini turun sebagai **seruan dan peringatan khusus kepada Ahli Kitab** (Yahudi dan Nasrani) agar memohon pertolongan dengan sabar dan salat.
A54: 2 | B54: 46 | C54: البقرة | D54: Al-Baqarah (Sapi Betina) | E54: Madinah | F54: الَّذِينَ يَظُنُّونَ أَنَّهُمْ مُلَاقُو رَبِّهِمْ وَأَنَّهُمْ إِلَيْهِ رَاجِعُونَ | G54: (yaitu) mereka yang yakin, bahwa mereka akan menemui Tuhannya, dan bahwa mereka akan kembali kepada-Nya. | H54: Peringatan dan Seruan kepada Bani Israel (40-46)
A55: 2 | B55: 47 | C55: البقرة | D55: Al-Baqarah (Sapi Betina) | E55: Madinah | F55: يَا بَنِي إِسْرَائِيلَ اذْكُرُوا نِعْمَتِيَ الَّتِي أَنْعَمْتُ عَلَيْكُمْ وَأَنِّي فَضَّلْتُكُمْ عَلَى الْعَالَمِينَ | G55: Wahai Bani Israil! Ingatlah nikmat-Ku yang telah Aku berikan kepadamu, dan Aku telah melebihkan kamu dari semua umat yang lain di alam ini (pada masa itu). | H55: Pengingat Nikmat dan Cobaan Bani Israel (47-61) | N55: Kontradiksi tentang Syafaat — Ayat ini menegaskan 'tidak akan berguna syafaat' pada Hari Kiamat; bertentangan dengan 20:109 yang menyatakan syafaat diizinkan bagi mereka yang mendapat izin Allah, dan berbagai hadis yang mengakui syafaat Nabi.
A56: 2 | B56: 48 | C56: البقرة | D56: Al-Baqarah (Sapi Betina) | E56: Madinah | F56: وَاتَّقُوا يَوْمًا لَا تَجْزِي نَفْسٌ عَنْ نَفْسٍ شَيْئًا وَلَا يُقْبَلُ مِنْهَا شَفَاعَةٌ وَلَا يُؤْخَذُ مِنْهَا عَدْلٌ وَلَا هُمْ يُنْصَرُونَ | G56: Dan takutlah kamu pada hari (ketika) tidak seorang pun dapat membela orang lain sedikit pun. Sedangkan syafaat24) dan tebusan apa pun darinya tidak diterima dan mereka tidak akan ditolong. | H56: Pengingat Nikmat dan Cobaan Bani Israel (47-61) | O56: *24) Syafaat ialah pertolongan yang diberikan oleh rasul atau orang-orang tertentu untuk meringankan azab atau beban seseorang di akhirat, atas izin Allah.
A57: 2 | B57: 49 | C57: البقرة | D57: Al-Baqarah (Sapi Betina) | E57: Madinah | F57: وَإِذْ نَجَّيْنَاكُمْ مِنْ آلِ فِرْعَوْنَ يَسُومُونَكُمْ سُوءَ الْعَذَابِ يُذَبِّحُونَ أَبْنَاءَكُمْ وَيَسْتَحْيُونَ نِسَاءَكُمْ ۚ وَفِي ذَٰلِكُمْ بَلَاءٌ مِنْ رَبِّكُمْ عَظِيمٌ | G57: Dan (ingatlah) ketika Kami menyelamatkan kamu dari (Fir'aun dan) pengikut-pengikut Fir'aun.25) Mereka menimpakan siksaan yang sangat berat kepadamu. Mereka menyembelih anak-anak laki-lakimu dan membiarkan hidup anak-anak perempuanmu. Dan pada yang demikian itu merupakan cobaan yang besar dari Tuhanmu. | H57: Pengingat Nikmat dan Cobaan Bani Israel (47-61) | L57: (Ayat 2:49): Teks menyepelekan tragedi genosida dan trauma pembedahan massal—di mana anak-anak laki-laki disembelih—dengan mereduksinya sebatas "cobaan yang besar dari Tuhan", mencabut empati pada kejahatan kemanusiaan. | O57: *25) Fir'aun adalah gelar bagi Raja-raja Mesir pada masa lalu. Menurut sejarah, Fir'aun pada masa Nabi Musa -'alaihissalām- ialah Menephthan (1232-1224 SM) anak Ramses.
A58: 2 | B58: 50 | C58: البقرة | D58: Al-Baqarah (Sapi Betina) | E58: Madinah | F58: وَإِذْ فَرَقْنَا بِكُمُ الْبَحْرَ فَأَنْجَيْنَاكُمْ وَأَغْرَقْنَا آلَ فِرْعَوْنَ وَأَنْتُمْ تَنْظُرُونَ | G58: Dan (ingatlah) ketika Kami membelah laut untukmu, sehingga kamu dapat Kami selamatkan dan Kami tenggelamkan (Fir'aun dan) pengikut-pengikut Fir'aun sedang kamu menyaksikan. | H58: Pengingat Nikmat dan Cobaan Bani Israel (47-61) | M58: Mitos Pembelahan Laut Merah — Narasi Musa membelah laut tidak memiliki bukti arkeologis, geologis, atau catatan historis dari peradaban manapun (Mesir kuno, Yunani, Romawi) yang semestinya menyaksikan peristiwa kolosal ini; tidak ada mekanisme fisik yang dapat membelah lautan secara instan.
A59: 2 | B59: 51 | C59: البقرة | D59: Al-Baqarah (Sapi Betina) | E59: Madinah | F59: وَإِذْ وَاعَدْنَا مُوسَىٰ أَرْبَعِينَ لَيْلَةً ثُمَّ اتَّخَذْتُمُ الْعِجْلَ مِنْ بَعْدِهِ وَأَنْتُمْ ظَالِمُونَ | G59: Dan (ingatlah) ketika Kami menjanjikan kepada Musa empat puluh malam.26) Kemudian kamu (Bani Israil) menjadikan (patung) anak sapi (sebagai sesembahan) setelah (kepergian)nya, dan kamu (menjadi) orang yang zalim. | H59: Pengingat Nikmat dan Cobaan Bani Israel (47-61) | O59: *26) Suatu tenggang waktu yang dijanjikan Allah untuk menerima petunjuk (Taurat); tetapi umat Nabi Musa -'alaihissalām- tidak sabar menunggunya, sehingga mereka menyembah patung anak sapi yang dibuat oleh Samiri.
A60: 2 | B60: 52 | C60: البقرة | D60: Al-Baqarah (Sapi Betina) | E60: Madinah | F60: ثُمَّ عَفَوْنَا عَنْكُمْ مِنْ بَعْدِ ذَٰلِكَ لَعَلَّكُمْ تَشْكُرُونَ | G60: Kemudian Kami memaafkan kamu setelah itu, agar kamu bersyukur. | H60: Pengingat Nikmat dan Cobaan Bani Israel (47-61)
A61: 2 | B61: 53 | C61: البقرة | D61: Al-Baqarah (Sapi Betina) | E61: Madinah | F61: وَإِذْ آتَيْنَا مُوسَى الْكِتَابَ وَالْفُرْقَانَ لَعَلَّكُمْ تَهْتَدُونَ | G61: Dan (ingatlah), ketika Kami memberikan kepada Musa Kitab dan Furqan, agar kamu memperoleh petunjuk.27) | H61: Pengingat Nikmat dan Cobaan Bani Israel (47-61) | O61: *27) Yang dimaksud dengan Kitab adalah Taurat. Dan yang dimaksud dengan Furqan adalah keterangan-keterangan lain untuk membedakan yang baik dan yang buruk.
A62: 2 | B62: 54 | C62: البقرة | D62: Al-Baqarah (Sapi Betina) | E62: Madinah | F62: وَإِذْ قَالَ مُوسَىٰ لِقَوْمِهِ يَا قَوْمِ إِنَّكُمْ ظَلَمْتُمْ أَنْفُسَكُمْ بِاتِّخَاذِكُمُ الْعِجْلَ فَتُوبُوا إِلَىٰ بَارِئِكُمْ فَاقْتُلُوا أَنْفُسَكُمْ ذَٰلِكُمْ خَيْرٌ لَكُمْ عِنْدَ بَارِئِكُمْ فَتَابَ عَلَيْكُمْ ۚ إِنَّهُ هُوَ التَّوَّابُ الرَّحِيمُ | G62: Dan (ingatlah) ketika Musa berkata kepada kaumnya, "Wahai kaumku! Kamu benar-benar telah menzalimi dirimu sendiri dengan menjadikan (patung) anak sapi (sebagai sesembahan), karena itu bertobatlah kepada Penciptamu dan bunuhlah dirimu.28) Itu lebih baik bagimu di sisi Penciptamu. Dia akan menerima tobatmu. Sungguh, Dialah Yang Maha Penerima tobat, Maha Penyayang. | H62: Pengingat Nikmat dan Cobaan Bani Israel (47-61) | K62: Argumentum ad Baculum + False Dilemma — Perintah 'bertaubatlah dengan membunuh diri sendiri' menawarkan dua pilihan: patuh ekstrem atau tetap berdosa; standar pengampunan yang mensyaratkan kematian menimbulkan masalah logis tentang kesempatan bertobat. | L62: (Ayat 2:54): Memerintahkan pembunuhan massal atau bunuh diri ("bunuhlah dirimu") sebagai syarat mutlak agar tobat diterima setelah kasus penyembahan anak sapi. Ini adalah bentuk ekstrem dari radikalisasi dan glorifikasi pengorbanan darah demi kepuasan ilahi. | O62: *28) "Membunuh dirimu" ada yang mengartikan, orang-orang yang tidak menyembah patung anak sapi itu membunuh orang yang menyembahnya. Ada pula yang mengartikan, orang yang menyembah patung anak sapi itu saling membunuh, dan ada pula yang mengartikan, mereka disuruh membunuh diri mereka masing-masing untuk bertobat.
A63: 2 | B63: 55 | C63: البقرة | D63: Al-Baqarah (Sapi Betina) | E63: Madinah | F63: وَإِذْ قُلْتُمْ يَا مُوسَىٰ لَنْ نُؤْمِنَ لَكَ حَتَّىٰ نَرَى اللَّهَ جَهْرَةً فَأَخَذَتْكُمُ الصَّاعِقَةُ وَأَنْتُمْ تَنْظُرُونَ | G63: Dan (ingatlah) ketika kamu berkata, "Wahai Musa! Kami tidak akan beriman kepadamu sebelum kami melihat Allah dengan jelas," maka halilintar menyambarmu, sedang kamu menyaksikannya. | H63: Pengingat Nikmat dan Cobaan Bani Israel (47-61) | Q63: Narasi bahwa Bani Israel disambar petir (ṣāʿiqa) karena meminta untuk melihat Tuhan secara langsung dan kemudian dibangkitkan dari kematian adalah bentuk polemik dan distorsi bermusuhan terhadap catatan Alkitab tentang kemegahan pewahyuan di Gunung Sinai,.
A64: 2 | B64: 56 | C64: البقرة | D64: Al-Baqarah (Sapi Betina) | E64: Madinah | F64: ثُمَّ بَعَثْنَاكُمْ مِنْ بَعْدِ مَوْتِكُمْ لَعَلَّكُمْ تَشْكُرُونَ | G64: Kemudian, Kami membangkitkan kamu setelah kamu mati, agar kamu bersyukur. | H64: Pengingat Nikmat dan Cobaan Bani Israel (47-61) | Q64: Narasi bahwa Bani Israel disambar petir (ṣāʿiqa) karena meminta untuk melihat Tuhan secara langsung dan kemudian dibangkitkan dari kematian adalah bentuk polemik dan distorsi bermusuhan terhadap catatan Alkitab tentang kemegahan pewahyuan di Gunung Sinai,.
A65: 2 | B65: 57 | C65: البقرة | D65: Al-Baqarah (Sapi Betina) | E65: Madinah | F65: وَظَلَّلْنَا عَلَيْكُمُ الْغَمَامَ وَأَنْزَلْنَا عَلَيْكُمُ الْمَنَّ وَالسَّلْوَىٰ ۖ كُلُوا مِنْ طَيِّبَاتِ مَا رَزَقْنَاكُمْ ۖ وَمَا ظَلَمُونَا وَلَٰكِنْ كَانُوا أَنْفُسَهُمْ يَظْلِمُونَ | G65: Dan Kami menaungi kamu dengan awan, dan Kami menurunkan kepadamu manna dan salwa.29) Makanlah (makanan) yang baik-baik dari rezeki yang telah Kami berikan kepadamu. Mereka tidak menzalimi Kami, tetapi justru merekalah yang menzalimi diri sendiri. | H65: Pengingat Nikmat dan Cobaan Bani Israel (47-61) | O65: *29) Manna ialah sejenis madu. Salwa ialah sejenis burung puyuh.
A66: 2 | B66: 58 | C66: البقرة | D66: Al-Baqarah (Sapi Betina) | E66: Madinah | F66: وَإِذْ قُلْنَا ادْخُلُوا هَٰذِهِ الْقَرْيَةَ فَكُلُوا مِنْهَا حَيْثُ شِئْتُمْ رَغَدًا وَادْخُلُوا الْبَابَ سُجَّدًا وَقُولُوا حِطَّةٌ نَغْفِرْ لَكُمْ خَطَايَاكُمْ ۚ وَسَنَزِيدُ الْمُحْسِنِينَ | G66: Dan (ingatlah) ketika Kami berfirman, "Masuklah kamu ke negeri ini (Baitulmaqdis), maka makanlah dengan nikmat (berbagai makanan) yang ada di sana sesukamu. Dan masukilah pintu gerbangnya sambil membungkuk, dan katakanlah, "Bebaskanlah kami (dari dosa-dosa kami)," niscaya Kami ampuni kesalahan-kesalahanmu. Dan Kami akan menambah (karunia) bagi orang-orang yang berbuat kebaikan." | H66: Pengingat Nikmat dan Cobaan Bani Israel (47-61)
A67: 2 | B67: 59 | C67: البقرة | D67: Al-Baqarah (Sapi Betina) | E67: Madinah | F67: فَبَدَّلَ الَّذِينَ ظَلَمُوا قَوْلًا غَيْرَ الَّذِي قِيلَ لَهُمْ فَأَنْزَلْنَا عَلَى الَّذِينَ ظَلَمُوا رِجْزًا مِنَ السَّمَاءِ بِمَا كَانُوا يَفْسُقُونَ | G67: Lalu orang-orang yang zalim mengganti perintah dengan (perintah lain) yang tidak diperintahkan kepada mereka. Maka Kami turunkan malapetaka dari langit kepada orang-orang yang zalim itu, karena mereka (selalu) berbuat fasik. | H67: Pengingat Nikmat dan Cobaan Bani Israel (47-61) | I67: Ayat 59 (Varian Sekte): Dalam manuskrip kuno Syiah yang ditemukan di Bankipur, teksnya memiliki sisipan yang sangat berbeda. Alih-alih berbunyi "orang-orang yang zalim", naskah tersebut berbunyi "mereka yang menzalimi keluarga Muhammad" dan "yang merampas hak keluarga Muhammad" | L67: (Ayat 2:59): Menurunkan malapetaka mematikan dari langit secara buta kepada satu kelompok hanya karena mereka mengganti sebuah perintah verbal dengan hal lain. Menunjukkan pola hukuman kolektif yang reaktif dan tidak proporsional.
A68: 2 | B68: 60 | C68: البقرة | D68: Al-Baqarah (Sapi Betina) | E68: Madinah | F68: وَإِذِ اسْتَسْقَىٰ مُوسَىٰ لِقَوْمِهِ فَقُلْنَا اضْرِبْ بِعَصَاكَ الْحَجَرَ ۖ فَانْفَجَرَتْ مِنْهُ اثْنَتَا عَشْرَةَ عَيْنًا ۖ قَدْ عَلِمَ كُلُّ أُنَاسٍ مَشْرَبَهُمْ ۖ كُلُوا وَاشْرَبُوا مِنْ رِزْقِ اللَّهِ وَلَا تَعْثَوْا فِي الْأَرْضِ مُفْسِدِينَ | G68: Dan (ingatlah) ketika Musa memohon air untuk kaumnya, lalu Kami berfirman, "Pukullah batu itu dengan tongkatmu!" Maka memacarlah darinya dua belas mata air. Setiap suku telah mengetahui tempat minumnya (masing-masing).30) Makan dan minumlah dari rezeki (yang diberikan) Allah, dan janganlah kamu melakukan kejahatan di bumi dengan berbuat kerusakan. | H68: Pengingat Nikmat dan Cobaan Bani Israel (47-61) | O68: *30) Setiap suku dari 12 suku Bani Israil, sebagaimana tersebut dalam surat Al-A'raf (7) : 160. | P68: (2:60) Mengklaim bahwa Abraham diselamatkan dari api Nimrod merupakan sebuah kesalahan historis yang memalukan; mitos ini lahir murni dari salah terjemah kata "Ur" (kota) menjadi "Or" (api) di dalam literatur komentator Yahudi, Jonathan ben Uzziah. (The Origins of the Koran,)
A69: 2 | B69: 61 | C69: البقرة | D69: Al-Baqarah (Sapi Betina) | E69: Madinah | F69: وَإِذْ قُلْتُمْ يَا مُوسَىٰ لَنْ نَصْبِرَ عَلَىٰ طَعَامٍ وَاحِدٍ فَادْعُ لَنَا رَبَّكَ يُخْرِجْ لَنَا مِمَّا تُنْبِتُ الْأَرْضُ مِنْ بَقْلِهَا وَقِثَّائِهَا وَفُومِهَا وَعَدَسِهَا وَبَصَلِهَا ۖ قَالَ أَتَسْتَبْدِلُونَ الَّذِي هُوَ أَدْنَىٰ بِالَّذِي هُوَ خَيْرٌ ۚ اهْبِطُوا مِصْرًا فَإِنَّ لَكُمْ مَا سَأَلْتُمْ ۗ وَضُرِبَتْ عَلَيْهِمُ الذِّلَّةُ وَالْمَسْكَنَةُ وَبَاءُوا بِغَضَبٍ مِنَ اللَّهِ ۗ ذَٰلِكَ بِأَنَّهُمْ كَانُوا يَكْفُرُونَ بِآيَاتِ اللَّهِ وَيَقْتُلُونَ النَّبِيِّينَ بِغَيْرِ الْحَقِّ ۗ ذَٰلِكَ بِمَا عَصَوْا وَكَانُوا يَعْتَدُونَ | G69: Dan (ingatlah), ketika kamu berkata, "Wahai Musa! Kami tidak tahan hanya (makan) dengan satu macam makanan saja, maka mohonkanlah kepada Tuhanmu untuk kami, agar Dia memberi kami apa yang ditumbuhkan bumi, seperti: sayur-mayur, mentimun, bawang putih, kacang adas dan bawang merah." Dia (Musa) menjawab, "Apakah kamu meminta sesuatu yang buruk sebagai ganti dari sesuatu yang baik? Pergilah ke suatu kota, pasti kamu memperoleh apa yang kamu minta." Kemudian mereka ditimpa kenistaan dan kemiskinan, dan mereka (kembali) mendapat kemurkaan dari Allah. Hal itu (terjadi) karena mereka mengingkari ayat-ayat Allah dan membunuh para nabi tanpa hak (alasan yang benar). Yang demikian itu karena mereka durhaka dan melampaui batas. | H69: Pengingat Nikmat dan Cobaan Bani Israel (47-61) | K69: Ad Hominem + Hasty Generalization — Keluhan Bani Israel tentang monotoni makanan direspons dengan tuduhan 'kesombongan' dan histori membunuh nabi; penolakan permintaan wajar dengan serangan karakter kolektif. | L69: (Ayat 2:61): Menghukum sebuah bangsa dengan kenistaan, kemiskinan, dan kemurkaan mutlak hanya berawal dari keluhan bosan dengan satu jenis makanan dan meminta variasi sayuran (mentimun, bawang putih, bawang merah). Sebuah tirani yang anti-kritik terhadap keluhan manusiawi.
A70: 2 | B70: 62 | C70: البقرة | D70: Al-Baqarah (Sapi Betina) | E70: Madinah | F70: إِنَّ الَّذِينَ آمَنُوا وَالَّذِينَ هَادُوا وَالنَّصَارَىٰ وَالصَّابِئِينَ مَنْ آمَنَ بِاللَّهِ وَالْيَوْمِ الْآخِرِ وَعَمِلَ صَالِحًا فَلَهُمْ أَجْرُهُمْ عِنْدَ رَبِّهِمْ وَلَا خَوْفٌ عَلَيْهِمْ وَلَا هُمْ يَحْزَنُونَ | G70: Sesungguhnya orang-orang yang beriman, orang-orang Yahudi, orang-orang Nasrani dan orang-orang ṣābiīn,31) siapa saja (diantara mereka) yang beriman kepada Allah dan hari akhir, dan melakukan kebajikan, mereka mendapat pahala dari Tuhannya, tidak ada rasa takut pada mereka, dan mereka tidak bersedih hati. | H70: Keselamatan Ahli Kitab yang Beriman (62) | J70: Ayat ini turun terkait keluh kesah **Salman Al-Farisi** yang menceritakan ibadah dan kesalehan teman-temannya dari kalangan pendeta Nasrani di masa lalu. Awalnya Nabi menyebut mereka berada di neraka sehingga Salman bersedih, lalu turunlah ayat ini yang menjelaskan bahwa siapa pun (Yahudi atau Nasrani) yang beriman dengan benar akan terhindar dari ketakutan dan kesedihan. (Sumber: Asbab Al-Nuzul - Al-Wahidi) Ayat ini turun untuk menjawab pertanyaan Salmàn al-Fàrisiy tentang nasib kaum Nasrani yang tulus beriman kepada Allah dan meninggal sebelum diutusnya Nabi Muhammad êallallàhu ‘alaihi wasallam. (Sumber: Asbabun Nuzul - Muchlis M. Hanafi) | O70: *31) Ṣābiīn ialah umat sebelum Nabi Muhammad -ṣallallāhu 'alaihi wa sallam- yang mengetahui adanya Tuhan Yang Maha Esa, dan mempercayai adanya pengaruh bintang-bintang.
A71: 2 | B71: 63 | C71: البقرة | D71: Al-Baqarah (Sapi Betina) | E71: Madinah | F71: وَإِذْ أَخَذْنَا مِيثَاقَكُمْ وَرَفَعْنَا فَوْقَكُمُ الطُّورَ خُذُوا مَا آتَيْنَاكُمْ بِقُوَّةٍ وَاذْكُرُوا مَا فِيهِ لَعَلَّكُمْ تَتَّقُونَ | G71: Dan (ingatlah) ketika Kami mengambil janji kamu dan Kami angkat gunung (Sinai) di atasmu (seraya berfirman), "Pegang teguhlah apa yang telah Kami berikan kepadamu dan ingatlah apa yang ada di dalamnya, agar kamu bertakwa." | H71: Pengingat Perjanjian dan Kisah Bani Israel (63-74)
A72: 2 | B72: 64 | C72: البقرة | D72: Al-Baqarah (Sapi Betina) | E72: Madinah | F72: ثُمَّ تَوَلَّيْتُمْ مِنْ بَعْدِ ذَٰلِكَ ۖ فَلَوْلَا فَضْلُ اللَّهِ عَلَيْكُمْ وَرَحْمَتُهُ لَكُنْتُمْ مِنَ الْخَاسِرِينَ | G72: Kemudian setelah itu kamu berpaling. Maka sekiranya bukan karena karunia Allah dan rahmat-Nya kepadamu, pasti kamu termasuk orang yang rugi. | H72: Pengingat Perjanjian dan Kisah Bani Israel (63-74)
A73: 2 | B73: 65 | C73: البقرة | D73: Al-Baqarah (Sapi Betina) | E73: Madinah | F73: وَلَقَدْ عَلِمْتُمُ الَّذِينَ اعْتَدَوْا مِنْكُمْ فِي السَّبْتِ فَقُلْنَا لَهُمْ كُونُوا قِرَدَةً خَاسِئِينَ | G73: Dan sungguh, kamu telah mengetahui orang-orang yang melakukan pelanggaran di antara kamu pada hari Sabat,32) lalu Kami katakan kepada mereka, "Jadilah kamu kera yang hina!"33) | H73: Pengingat Perjanjian dan Kisah Bani Israel (63-74) | L73: (Ayat 2:65): Mengutuk pelanggar aturan hari Sabat dengan mengubah mereka wujudnya menjadi "kera yang hina". Hukuman kutukan fisik yang absurd dan mencabut keluhuran martabat manusia secara total. | M73: Mitos Metamorfosis Manusia menjadi Kera — Klaim manusia diubah menjadi kera sebagai hukuman bertentangan dengan genetika dan biologi evolusi; tidak ada mekanisme yang memungkinkan transformasi spesies instan, dan tidak ada catatan sejarah tentang manusia yang berubah menjadi primata lain. | O73: *32) Hari Sabat ialah hari Sabtu, hari khusus bagi orang Yahudi untuk beribadah. 33) Kera : Betul-betul menjadi kera sebagai kutukan Allah. Sebagian mufasir mengartikan memiliki sifat-sifat seperti kera.
A74: 2 | B74: 66 | C74: البقرة | D74: Al-Baqarah (Sapi Betina) | E74: Madinah | F74: فَجَعَلْنَاهَا نَكَالًا لِمَا بَيْنَ يَدَيْهَا وَمَا خَلْفَهَا وَمَوْعِظَةً لِلْمُتَّقِينَ | G74: Maka Kami jadikan (yang demikian) itu peringatan bagi orang-orang pada masa itu, dan bagi mereka yang datang kemudian, serta menjadi pelajaran bagi orang-orang yang bertakwa. | H74: Pengingat Perjanjian dan Kisah Bani Israel (63-74)
A75: 2 | B75: 67 | C75: البقرة | D75: Al-Baqarah (Sapi Betina) | E75: Madinah | F75: وَإِذْ قَالَ مُوسَىٰ لِقَوْمِهِ إِنَّ اللَّهَ يَأْمُرُكُمْ أَنْ تَذْبَحُوا بَقَرَةً ۖ قَالُوا أَتَتَّخِذُنَا هُزُوًا ۖ قَالَ أَعُوذُ بِاللَّهِ أَنْ أَكُونَ مِنَ الْجَاهِلِينَ | G75: Dan (ingatlah) ketika Musa berkata kepada kaumnya, "Allah memerintahkan kamu agar menyembelih seekor sapi betina." Mereka bertanya, "Apakah engkau akan menjadikan kami sebagai ejekan?" 34) Dia (Musa) menjawab, "Aku berlindung kepada Allah agar tidak menjadi orang-orang yang bodoh." | H75: Pengingat Perjanjian dan Kisah Bani Israel (63-74) | K75: False Dilemma + Abusive Demand — Perintah menyembelih sapi yang semakin diperinci (67-71) tanpa tujuan praktis yang jelas; kerumitan ritual progresif sebagai ujian kepatuhan buta, bukan tujuan substantif. | O75: *34) Hikmah Allah menyuruh menyembelih sapi ialah agar hilang rasa pengagungan mereka kepada patung anak sapi yang pernah mereka sembah.
A76: 2 | B76: 68 | C76: البقرة | D76: Al-Baqarah (Sapi Betina) | E76: Madinah | F76: قَالُوا ادْعُ لَنَا رَبَّكَ يُبَيِّنْ لَنَا مَا هِيَ ۚ قَالَ إِنَّهُ يَقُولُ إِنَّهَا بَقَرَةٌ لَا فَارِضٌ وَلَا بِكْرٌ عَوَانٌ بَيْنَ ذَٰلِكَ ۖ فَافْعَلُوا مَا تُؤْمَرُونَ | G76: Mereka berkata, "Mohonkanlah kepada Tuhanmu untuk kami agar Dia menjelaskan kepada kami tentang (sapi betina) itu." Dia (Musa) menjawab, "Dia (Allah) berfirman, bahwa sapi betina itu tidak tua dan tidak muda, (tetapi) pertengahan antara itu. Maka kerjakanlah apa yang diperintahkan kepadamu!" | H76: Pengingat Perjanjian dan Kisah Bani Israel (63-74)
A77: 2 | B77: 69 | C77: البقرة | D77: Al-Baqarah (Sapi Betina) | E77: Madinah | F77: قَالُوا ادْعُ لَنَا رَبَّكَ يُبَيِّنْ لَنَا مَا لَوْنُهَا ۚ قَالَ إِنَّهُ يَقُولُ إِنَّهَا بَقَرَةٌ صَفْرَاءُ فَاقِعٌ لَوْنُهَا تَسُرُّ النَّاظِرِينَ | G77: Mereka berkata, "Mohonkanlah kepada Tuhanmu untuk kami agar Dia menjelaskan kepada kami apa warnanya." Dia (Musa) menjawab, "Dia Allah berfirman, bahwa (sapi) itu adalah sapi betina yang kuning tua warnanya, yang menyenangkan orang-orang yang memandang(nya)." | H77: Pengingat Perjanjian dan Kisah Bani Israel (63-74)
A78: 2 | B78: 70 | C78: البقرة | D78: Al-Baqarah (Sapi Betina) | E78: Madinah | F78: قَالُوا ادْعُ لَنَا رَبَّكَ يُبَيِّنْ لَنَا مَا هِيَ إِنَّ الْبَقَرَ تَشَابَهَ عَلَيْنَا وَإِنَّا إِنْ شَاءَ اللَّهُ لَمُهْتَدُونَ | G78: Mereka berkata, "Mohonkanlah kepada Tuhanmu untuk kami agar Dia menjelaskan kepada kami tentang (sapi betina) itu. (Karena) sesungguhnya sapi itu belum jelas bagi kami, dan jika Allah menghendaki, niscaya kami mendapat petunjuk." | H78: Pengingat Perjanjian dan Kisah Bani Israel (63-74)
A79: 2 | B79: 71 | C79: البقرة | D79: Al-Baqarah (Sapi Betina) | E79: Madinah | F79: قَالَ إِنَّهُ يَقُولُ إِنَّهَا بَقَرَةٌ لَا ذَلُولٌ تُثِيرُ الْأَرْضَ وَلَا تَسْقِي الْحَرْثَ مُسَلَّمَةٌ لَا شِيَةَ فِيهَا ۚ قَالُوا الْآنَ جِئْتَ بِالْحَقِّ ۚ فَذَبَحُوهَا وَمَا كَادُوا يَفْعَلُونَ | G79: Dia (Musa) menjawab, "Dia (Allah) berfirman, (sapi) itu adalah sapi betina yang belum pernah dipakai untuk membajak tanah dan tidak (pula) untuk mengairi tanaman, sehat, dan tidak belang." Mereka berkata, "Sekarang barulah engkau menerangkan (hal) yang sebenarnya." Lalu mereka menyembelihnya, dan nyaris mereka tidak melaksanakan (perintah) itu. | H79: Pengingat Perjanjian dan Kisah Bani Israel (63-74)
A80: 2 | B80: 72 | C80: البقرة | D80: Al-Baqarah (Sapi Betina) | E80: Madinah | F80: وَإِذْ قَتَلْتُمْ نَفْسًا فَادَّارَأْتُمْ فِيهَا ۖ وَاللَّهُ مُخْرِجٌ مَا كُنْتُمْ تَكْتُمُونَ | G80: Dan (ingatlah) ketika kamu membunuh seseorang, lalu kamu tuduh-menuduh tentang itu. Tetapi Allah menyingkapkan apa yang kamu sembunyikan. | H80: Pengingat Perjanjian dan Kisah Bani Israel (63-74) | L80: (Ayat 2:72-73): Memerintahkan pemukulan mayat korban pembunuhan menggunakan potongan daging sapi agar mayat itu hidup lagi untuk menunjuk pelakunya. Memasukkan praktik magis (necromancy) yang tidak masuk akal sebagai jalan keluar penyelesaian kasus kriminal.
A81: 2 | B81: 73 | C81: البقرة | D81: Al-Baqarah (Sapi Betina) | E81: Madinah | F81: فَقُلْنَا اضْرِبُوهُ بِبَعْضِهَا ۚ كَذَٰلِكَ يُحْيِي اللَّهُ الْمَوْتَىٰ وَيُرِيكُمْ آيَاتِهِ لَعَلَّكُمْ تَعْقِلُونَ | G81: Lalu Kami berfirman, "Pukullah (mayat) itu dengan bagian dari (sapi) itu!" Demikianlah Allah menghidupkan (orang) yang telah mati, dan Dia memperlihatkan kepadamu tanda-tanda (kekuasaan-Nya) agar kamu mengerti. | H81: Pengingat Perjanjian dan Kisah Bani Israel (63-74) | L81: (Ayat 2:72-73): Memerintahkan pemukulan mayat korban pembunuhan menggunakan potongan daging sapi agar mayat itu hidup lagi untuk menunjuk pelakunya. Memasukkan praktik magis (necromancy) yang tidak masuk akal sebagai jalan keluar penyelesaian kasus kriminal. | M81: Mitos Kebangkitan Temporer melalui Kontak Fisik — Orang yang telah mati bangkit setelah dipukul bagian tubuh sapi yang disembelih; tidak ada mekanisme biologis yang dapat menjelaskan kebangkitan melalui kontak fisik dengan hewan. Ini mencerminkan pemahaman pra-ilmiah tentang kehidupan dan kematian.
A82: 2 | B82: 74 | C82: البقرة | D82: Al-Baqarah (Sapi Betina) | E82: Madinah | F82: ثُمَّ قَسَتْ قُلُوبُكُمْ مِنْ بَعْدِ ذَٰلِكَ فَهِيَ كَالْحِجَارَةِ أَوْ أَشَدُّ قَسْوَةً ۚ وَإِنَّ مِنَ الْحِجَارَةِ لَمَا يَتَفَجَّرُ مِنْهُ الْأَنْهَارُ ۚ وَإِنَّ مِنْهَا لَمَا يَشَّقَّقُ فَيَخْرُجُ مِنْهُ الْمَاءُ ۚ وَإِنَّ مِنْهَا لَمَا يَهْبِطُ مِنْ خَشْيَةِ اللَّهِ ۗ وَمَا اللَّهُ بِغَافِلٍ عَمَّا تَعْمَلُونَ | G82: Kemudian setelah itu hatimu menjadi keras, sehingga (hatimu) seperti batu, bahkan lebih keras. Padahal dari batu-batu itu pasti ada sungai-sungai yang (airnya) memancar darinya. Ada pula yang terbelah lalu keluarlah mata air darinya. Dan ada pula yang meluncur jatuh karena takut kepada Allah. Dan Allah tidaklah lengah terhadap apa yang kamu kerjakan. | H82: Pengingat Perjanjian dan Kisah Bani Israel (63-74) | K82: Ad Hominem + Hasty Generalization — Menggambarkan hati Bani Israel 'lebih keras dari batu' adalah karakterisasi merendahkan seluruh kelompok berdasarkan insiden tertentu.
A83: 2 | B83: 75 | C83: البقرة | D83: Al-Baqarah (Sapi Betina) | E83: Madinah | F83: أَفَتَطْمَعُونَ أَنْ يُؤْمِنُوا لَكُمْ وَقَدْ كَانَ فَرِيقٌ مِنْهُمْ يَسْمَعُونَ كَلَامَ اللَّهِ ثُمَّ يُحَرِّفُونَهُ مِنْ بَعْدِ مَا عَقَلُوهُ وَهُمْ يَعْلَمُونَ | G83: Maka apakah kamu (muslimin) sangat mengharapkan mereka akan percaya kepadamu, sedangkan segolongan dari mereka mendengar firman Allah, lalu mereka mengubahnya setelah memahaminya, padahal mereka mengetahuinya? 35) | H83: Kritik terhadap Sikap Ahli Kitab (75-82) | J83: Ayat ini turun berkenaan dengan **tujuh puluh orang utusan Nabi Musa** yang berkhianat dengan mengubah-ubah firman yang mereka dengar. Pendapat lain menyebutkan ayat ini ditujukan bagi kaum Yahudi yang mengubah hukum rajam dan menyembunyikan ciri-ciri kenabian Muhammad SAW. | K83: Hasty Generalization + Appeal to Motive — Mengklaim sebagian Bani Israel 'sengaja mengubah firman Allah setelah memahaminya' adalah atribusi niat jahat secara kolektif tanpa bukti individual. | O83: *35) Yang dimaksud adalah orang-orang Yahudi di Madinah yang mengubah-ubah isi Taurat terutama mengenai Nabi Muhammad -ṣallallāhu 'alaihi wa sallam- .
A84: 2 | B84: 76 | C84: البقرة | D84: Al-Baqarah (Sapi Betina) | E84: Madinah | F84: وَإِذَا لَقُوا الَّذِينَ آمَنُوا قَالُوا آمَنَّا وَإِذَا خَلَا بَعْضُهُمْ إِلَىٰ بَعْضٍ قَالُوا أَتُحَدِّثُونَهُمْ بِمَا فَتَحَ اللَّهُ عَلَيْكُمْ لِيُحَاجُّوكُمْ بِهِ عِنْدَ رَبِّكُمْ ۚ أَفَلَا تَعْقِلُونَ | G84: Dan apabila mereka berjumpa dengan orang-orang yang beriman, mereka berkata, "Kami telah beriman." Tetapi apabila kembali kepada sesamanya, mereka bertanya, "Apakah akan kamu ceritakan kepada mereka apa yang telah diterangkan Allah kepadamu, sehingga mereka dapat menyanggah kamu di hadapan Tuhanmu? Tidakkah kamu mengerti?" 36) | H84: Kritik terhadap Sikap Ahli Kitab (75-82) | J84: Sebagian kaum Yahudi menyatakan pengakuan mereka atas kenabian Nabi Muhammad di hadapan kaum mukmin. Hal ini membuat kawan-kawan mereka dari kalangan rahib kesal dan menegur mereka untuk tidak mengulanginya lagi. Itulah peristiwa yang melatarbelakangi turunnya ayat tersebut. (Sumber: Asbabun Nuzul - Muchlis M. Hanafi) | K84: Mind Reading Fallacy — Pertanyaan 'apakah kalian menceritakan kepada mereka apa yang Allah nyatakan?' mengandaikan informasi dibagikan dengan motif jahat, tanpa membuktikan niat tersebut. | O84: *36) Di dalam Taurat diterangkan tentang Nabi Muhammad -ṣallallāhu 'alaihi wa sallam- yang akan datang sebagai nabi terakhir, tetapi keterangan itu disembunyikan oleh orang Yahudi, karena takut akan menjadi bumerang bagi mereka.
A85: 2 | B85: 77 | C85: البقرة | D85: Al-Baqarah (Sapi Betina) | E85: Madinah | F85: أَوَلَا يَعْلَمُونَ أَنَّ اللَّهَ يَعْلَمُ مَا يُسِرُّونَ وَمَا يُعْلِنُونَ | G85: Dan tidakkah mereka tahu bahwa Allah mengetahui apa yang mereka sembunyikan dan apa yang mereka tampakkan? | H85: Kritik terhadap Sikap Ahli Kitab (75-82)
A86: 2 | B86: 78 | C86: البقرة | D86: Al-Baqarah (Sapi Betina) | E86: Madinah | F86: وَمِنْهُمْ أُمِّيُّونَ لَا يَعْلَمُونَ الْكِتَابَ إِلَّا أَمَانِيَّ وَإِنْ هُمْ إِلَّا يَظُنُّونَ | G86: Dan di antara mereka ada yang buta huruf, tidak memahami Kitab (Taurat), kecuali hanya berangan-angan dan mereka hanya menduga-duga. | H86: Kritik terhadap Sikap Ahli Kitab (75-82) | K86: Appeal to Ignorance — Karakterisasi sebagian Bani Israel sebagai 'buta huruf yang tidak mengetahui Kitab kecuali angan-angan' digunakan untuk mendiskreditkan posisi mereka tanpa merespons argumen substantifnya.
A87: 2 | B87: 79 | C87: البقرة | D87: Al-Baqarah (Sapi Betina) | E87: Madinah | F87: فَوَيْلٌ لِلَّذِينَ يَكْتُبُونَ الْكِتَابَ بِأَيْدِيهِمْ ثُمَّ يَقُولُونَ هَٰذَا مِنْ عِنْدِ اللَّهِ لِيَشْتَرُوا بِهِ ثَمَنًا قَلِيلًا ۖ فَوَيْلٌ لَهُمْ مِمَّا كَتَبَتْ أَيْدِيهِمْ وَوَيْلٌ لَهُمْ مِمَّا يَكْسِبُونَ | G87: Maka celakalah orang-orang yang menulis kitab dengan tangan mereka (sendiri), kemudian berkata, "Ini dari Allah," (dengan maksud) untuk menjualnya dengan harga murah. Maka celakalah mereka, karena tulisan tangan mereka, dan celakalah mereka karena apa yang mereka perbuat.37) | H87: Kritik terhadap Sikap Ahli Kitab (75-82) | I87: Ayat 79 (Keterputusan Teks): Frasa tentang menebus tawanan (wa-'in ya'tukum 'usara tufdu-hum) secara tata bahasa memutus hubungan kalimat sebelumnya, yang membuktikan bahwa frasa tersebut ditambahkan belakangan ke dalam teks asli | J87: Ayat ini turun karena tindakan para pendeta Yahudi yang dengan sengaja **mengubah ciri-ciri fisik Nabi Muhammad SAW** di dalam kitab mereka (dari kulit cokelat dan tinggi sedang, diubah menjadi putih dan tinggi) demi mempertahankan keuntungan materi dari pengikut mereka. | K87: Ad Hominem + Hasty Generalization — Tuduhan bahwa ulama menulis kitab lalu mengklaimnya sebagai firman Allah adalah serangan kolektif terhadap seluruh kelompok tanpa bukti spesifik per individu. | O87: *37) Memalsukan dan mengubah ayat untuk kepentingan dan keuntungan.
A88: 2 | B88: 80 | C88: البقرة | D88: Al-Baqarah (Sapi Betina) | E88: Madinah | F88: وَقَالُوا لَنْ تَمَسَّنَا النَّارُ إِلَّا أَيَّامًا مَعْدُودَةً ۚ قُلْ أَتَّخَذْتُمْ عِنْدَ اللَّهِ عَهْدًا فَلَنْ يُخْلِفَ اللَّهُ عَهْدَهُ ۖ أَمْ تَقُولُونَ عَلَى اللَّهِ مَا لَا تَعْلَمُونَ | G88: Dan mereka berkata, "Neraka tidak akan menyentuh kami, kecuali beberapa hari saja." Katakanlah, "Sudahkah kamu menerima janji dari Allah, sehingga Allah tidak akan mengingkari janji-Nya, ataukah kamu mengatakan tentang Allah, sesuatu yang tidak kamu ketahui?" | H88: Kritik terhadap Sikap Ahli Kitab (75-82) | J88: Ayat ini turun untuk menanggapi keyakinan keliru kaum Yahudi yang mengklaim bahwa mereka **hanya akan disentuh api neraka selama beberapa hari saja** (tujuh hari atau empat puluh hari) sesuai dengan perhitungan waktu yang mereka buat-buat sendiri. (Sumber: Asbab Al-Nuzul - Al-Wahidi) (80-81) Ayat ini menerangkan bagaimana kaum Yahudi yakin tidak akan disiksa di neraka kecuali beberapa hari saja. Hal tersebut dibantah oleh Allah dengan turunnya ayat ini. (Sumber: Asbabun Nuzul - Muchlis M. Hanafi) | P88: (2:80) Kritik intertekstual menyoroti frasa "Api neraka tidak akan menyentuh kami kecuali beberapa hari saja." Konsep ini dinilai meminjam tradisi dari literatur Talmud Yahudi (b. Rosh Hoshanah 16b–17a) yang mengidentifikasi adanya kelas pendosa menengah yang akan turun ke Gehinnom (neraka) dan menderita sementara waktu untuk disucikan sebelum bangkit kembali. (Sumber: buku The Qur'an and the Bible: Text and Commentary oleh Gabriel Said Reynolds)
A89: 2 | B89: 81 | C89: البقرة | D89: Al-Baqarah (Sapi Betina) | E89: Madinah | F89: بَلَىٰ مَنْ كَسَبَ سَيِّئَةً وَأَحَاطَتْ بِهِ خَطِيئَتُهُ فَأُولَٰئِكَ أَصْحَابُ النَّارِ ۖ هُمْ فِيهَا خَالِدُونَ | G89: Tidaklah demikian! Barang siapa berbuat keburukan dan dosanya telah menenggelamkannya, maka mereka itu penghuni neraka. Mereka kekal di dalamnya. | H89: Kritik terhadap Sikap Ahli Kitab (75-82) | K89: Argumentum ad Baculum — 'Siapa yang berbuat kejahatan dan dikepung dosanya maka dia penghuni neraka' menggunakan ancaman hukuman kekal sebagai argumen, bukan pembuktian etis. | P89: (2:81) Ayat ini menyalahi kaidah tata bahasa Arab; memakai kata kerja imperfek (taqtulūn) alih-alih bentuk perfek (qataltum) hanya untuk memaksakan rima sajak di akhir ayat. (The Qur'an: A Historical-Critical Introduction)
A90: 2 | B90: 82 | C90: البقرة | D90: Al-Baqarah (Sapi Betina) | E90: Madinah | F90: وَالَّذِينَ آمَنُوا وَعَمِلُوا الصَّالِحَاتِ أُولَٰئِكَ أَصْحَابُ الْجَنَّةِ ۖ هُمْ فِيهَا خَالِدُونَ | G90: Dan orang-orang yang beriman dan mengerjakan kebajikan, mereka itu penghuni surga. Mereka kekal di dalamnya. | H90: Kritik terhadap Sikap Ahli Kitab (75-82)
A91: 2 | B91: 83 | C91: البقرة | D91: Al-Baqarah (Sapi Betina) | E91: Madinah | F91: وَإِذْ أَخَذْنَا مِيثَاقَ بَنِي إِسْرَائِيلَ لَا تَعْبُدُونَ إِلَّا اللَّهَ وَبِالْوَالِدَيْنِ إِحْسَانًا وَذِي الْقُرْبَىٰ وَالْيَتَامَىٰ وَالْمَسَاكِينِ وَقُولُوا لِلنَّاسِ حُسْنًا وَأَقِيمُوا الصَّلَاةَ وَآتُوا الزَّكَاةَ ثُمَّ تَوَلَّيْتُمْ إِلَّا قَلِيلًا مِنْكُمْ وَأَنْتُمْ مُعْرِضُونَ | G91: Dan (ingatlah) ketika Kami mengambil janji dari Bani Israil, "Janganlah kamu menyembah selain Allah, dan berbuat baiklah kepada kedua orang tua, kerabat, anak-anak yatim, dan orang-orang miskin. Dan bertutur katalah yang baik kepada manusia, laksanakan salat dan tunaikanlah zakat." Tetapi kemudian kamu berpaling (mengingkari), kecuali sebagian kecil dari kamu, dan kamu (masih menjadi) pembangkang. | H91: Perjanjian Bani Israel dan Pelanggarannya (83-93)
A92: 2 | B92: 84 | C92: البقرة | D92: Al-Baqarah (Sapi Betina) | E92: Madinah | F92: وَإِذْ أَخَذْنَا مِيثَاقَكُمْ لَا تَسْفِكُونَ دِمَاءَكُمْ وَلَا تُخْرِجُونَ أَنْفُسَكُمْ مِنْ دِيَارِكُمْ ثُمَّ أَقْرَرْتُمْ وَأَنْتُمْ تَشْهَدُونَ | G92: Dan (ingatlah) ketika Kami mengambil janji kamu, "Janganlah kamu menumpahkan darahmu (membunuh orang), dan mengusir dirimu (saudara sebangsamu) dari kampung halamanmu." kemudian kamu berikrar dan bersaksi. | H92: Perjanjian Bani Israel dan Pelanggarannya (83-93)
A93: 2 | B93: 85 | C93: البقرة | D93: Al-Baqarah (Sapi Betina) | E93: Madinah | F93: ثُمَّ أَنْتُمْ هَٰؤُلَاءِ تَقْتُلُونَ أَنْفُسَكُمْ وَتُخْرِجُونَ فَرِيقًا مِنْكُمْ مِنْ دِيَارِهِمْ تَظَاهَرُونَ عَلَيْهِمْ بِالْإِثْمِ وَالْعُدْوَانِ وَإِنْ يَأْتُوكُمْ أُسَارَىٰ تُفَادُوهُمْ وَهُوَ مُحَرَّمٌ عَلَيْكُمْ إِخْرَاجُهُمْ ۚ أَفَتُؤْمِنُونَ بِبَعْضِ الْكِتَابِ وَتَكْفُرُونَ بِبَعْضٍ ۚ فَمَا جَزَاءُ مَنْ يَفْعَلُ ذَٰلِكَ مِنْكُمْ إِلَّا خِزْيٌ فِي الْحَيَاةِ الدُّنْيَا ۖ وَيَوْمَ الْقِيَامَةِ يُرَدُّونَ إِلَىٰ أَشَدِّ الْعَذَابِ ۗ وَمَا اللَّهُ بِغَافِلٍ عَمَّا تَعْمَلُونَ | G93: Kemudian kamu (Bani Israil) membunuh dirimu (sesamamu), dan mengusir segolongan dari kamu dari kampung halamannya. Kamu saling membantu (menghadapi) mereka dalam kejahatan dan permusuhan. Dan jika mereka datang kepadamu sebagai tawanan, kamu tebus mereka, padahal kamu dilarang mengusir mereka. Apakah kamu beriman kepada sebagian Kitab (Taurat) dan ingkar kepada sebagian (yang lain)? Maka tidak ada balasan (yang pantas) bagi orang yang berbuat demikian di antara kamu selain kenistaan dalam kehidupan dunia, dan pada hari Kiamat mereka dikembalikan kepada azab yang paling berat. Dan Allah tidak lengah terhadap apa yang kamu kerjakan.38) | H93: Perjanjian Bani Israel dan Pelanggarannya (83-93) | K93: Non Sequitur + False Equivalence — Mengusir setengah kelompok lalu menebus tawanan diklaim sebagai kontradiksi, namun penjelasannya tidak koheren; dua tindakan ini dinilai sama-sama salah tanpa analisis konteks. | O93: *38) Semua janji dan sumpah yang diikrarkan Bani Israil sebagaimana disebut dalam ayat 83 dan 84 di atas, mereka langgar. Kenyataan sejarah antara dua suku Yahudi di Madinah yaitu Bani Quraiẓah dan Bani Naẓīr selalu berperang. Tetapi jika ada orang Yahudi di antara kedua suku itu yang tertawan oleh suku lain, misalnya oleh suku Aus sekutu Bani Quraiẓah atau suku Khazraj sekutu Bani Naẓīr, mereka bersatu menebusnya. | P93: (2:85) Terdapat keragaman teks (qira'at) yang sangat radikal dan mengubah makna dasar: bacaan Hafs tertulis "ya'malūna" (mereka lakukan), sedangkan bacaan Warsh tertulis "ta'malūna" (kamu lakukan). (Criticism of the Quran - Wikipedia)
A94: 2 | B94: 86 | C94: البقرة | D94: Al-Baqarah (Sapi Betina) | E94: Madinah | F94: أُولَٰئِكَ الَّذِينَ اشْتَرَوُا الْحَيَاةَ الدُّنْيَا بِالْآخِرَةِ ۖ فَلَا يُخَفَّفُ عَنْهُمُ الْعَذَابُ وَلَا هُمْ يُنْصَرُونَ | G94: Mereka itulah orang-orang yang membeli kehidupan dunia dengan (kehidupan) akhirat. Maka tidak akan diringankan azabnya dan mereka tidak akan ditolong. | H94: Perjanjian Bani Israel dan Pelanggarannya (83-93)
A95: 2 | B95: 87 | C95: البقرة | D95: Al-Baqarah (Sapi Betina) | E95: Madinah | F95: وَلَقَدْ آتَيْنَا مُوسَى الْكِتَابَ وَقَفَّيْنَا مِنْ بَعْدِهِ بِالرُّسُلِ ۖ وَآتَيْنَا عِيسَى ابْنَ مَرْيَمَ الْبَيِّنَاتِ وَأَيَّدْنَاهُ بِرُوحِ الْقُدُسِ ۗ أَفَكُلَّمَا جَاءَكُمْ رَسُولٌ بِمَا لَا تَهْوَىٰ أَنْفُسُكُمُ اسْتَكْبَرْتُمْ فَفَرِيقًا كَذَّبْتُمْ وَفَرِيقًا تَقْتُلُونَ | G95: Dan sungguh, Kami telah memberikan Kitab (Taurat) kepada Musa, dan Kami susulkan setelahnya dengan Rasul-rasul, dan kami telah berikan kepada Isa putra Maryam bukti-bukti kebenaran serta Kami perkuat dia dengan Ruhulkudus (Jibril). Mengapa setiap Rasul yang datang kepadamu (membawa) sesuatu (pelajaran) yang tidak kamu inginkan, kamu menyombongkan diri, lalu sebagian kamu dustakan dan sebagian kamu bunuh? | H95: Perjanjian Bani Israel dan Pelanggarannya (83-93) | K95: Hasty Generalization + Ad Hominem — Mengkarakterisasi seluruh Bani Israel sebagai mereka yang 'membunuh para nabi' adalah generalisasi sejarah untuk mendiskreditkan komunitas masa kini. | P95: (2:87) Terdapat perbedaan kalimat dalam manuskrip Palimpsest Sana'a. Teks standar Utsmani berbunyi *wa-qaffayna min ba'dihi* (setelah dia), sedangkan teks lapisan bawah manuskrip Sana'a berbunyi *wa-qaffayna 'ala atharihi* (di atas jejaknya), yang menunjukkan idiom yang berbeda tentang suksesi kenabian di masa lisan awal. (Sumber: buku/studi Ṣan'ā' 1 and the Origins of the Qur'ān oleh Behnam Sadeghi & Mohsen Goudarzi) (2:87) Lapisan teks tersembunyi (palimpsest) dari Manuskrip Sanaa memaparkan varian tulisan kuno "wa-qaffaynā 'alā āthārihi" yang telah dihapus dan diganti menjadi versi standar Utsman saat ini, "wa-qaffaynā min ba'dihi". (Sanaa manuscript - Wikipedia)
A96: 2 | B96: 88 | C96: البقرة | D96: Al-Baqarah (Sapi Betina) | E96: Madinah | F96: وَقَالُوا قُلُوبُنَا غُلْفٌ ۚ بَلْ لَعَنَهُمُ اللَّهُ بِكُفْرِهِمْ فَقَلِيلًا مَا يُؤْمِنُونَ | G96: Dan mereka berkata, "Hati kami tertutup." Tidak! Allah telah melaknat mereka itu karena keingkaran mereka, tetapi sedikit sekali mereka yang beriman. | H96: Perjanjian Bani Israel dan Pelanggarannya (83-93) | K96: Circular Reasoning — Pernyataan 'hati kami tertutup' ditolak dengan mengklaim itu adalah tanda kekufuran; ini melingkar tanpa menyentuh substansi argumen yang ditolak.
A97: 2 | B97: 89 | C97: البقرة | D97: Al-Baqarah (Sapi Betina) | E97: Madinah | F97: وَلَمَّا جَاءَهُمْ كِتَابٌ مِنْ عِنْدِ اللَّهِ مُصَدِّقٌ لِمَا مَعَهُمْ وَكَانُوا مِنْ قَبْلُ يَسْتَفْتِحُونَ عَلَى الَّذِينَ كَفَرُوا فَلَمَّا جَاءَهُمْ مَا عَرَفُوا كَفَرُوا بِهِ ۚ فَلَعْنَةُ اللَّهِ عَلَى الْكَافِرِينَ | G97: Dan setelah sampai kepada mereka Kitab (Al-Qur`an) dari Allah yang membenarkan apa yang ada pada mereka39) sedangkan sebelumnya mereka memohon kemenangan atas orang-orang kafir, ternyata setelah sampai kepada mereka apa yang telah mereka ketahui itu, mereka mengingkarinya. Maka laknat Allah bagi orang-orang yang ingkar. | H97: Perjanjian Bani Israel dan Pelanggarannya (83-93) | J97: Ayat ini turun berkenaan dengan kaum **Yahudi Khaibar**. Sebelum Nabi Muhammad SAW diutus, mereka sering berdoa meminta kemenangan atas musuh mereka dengan menyebut nama nabi akhir zaman. Namun, ketika Nabi Muhammad SAW benar-benar diutus, mereka justru mengingkarinya karena dengki. (Sumber: Asbab Al-Nuzul - Al-Wahidi) Kerasulan Muhammad adalah hal yang sangat ditunggu-tunggu oleh kaum Yahudi, namun ketika Nabi Muhammad diutus, mereka malah mengingkarinya karena Muhammad berasal dari bangsa Arab, bukan dari bangsa Yahudi. Itulah sebab nuzul ayat di atas. (Sumber: Asbabun Nuzul - Muchlis M. Hanafi) | K97: Begging the Question — 'Laknat Allah atas orang kafir' menggunakan kesimpulan (mereka terkutuk) sebagai asumsi; labelisasi 'kafir' dan 'terkutuk' sudah mengandung keputusan tanpa pembuktian. | L97: (Ayat 2:89-90): Tuhan melaknat dan menimpakan kemurkaan bertubi-tubi kepada sebuah kelompok semata-mata karena mereka mendustakan kitab yang baru turun. Menunjukkan intoleransi Tuhan terhadap kebebasan berpikir dan perbedaan keyakinan teologis. | O97: *39) Al-Qur`an juga mengajarkan tauhid yang diajarkan Taurat.
A98: 2 | B98: 90 | C98: البقرة | D98: Al-Baqarah (Sapi Betina) | E98: Madinah | F98: بِئْسَمَا اشْتَرَوْا بِهِ أَنْفُسَهُمْ أَنْ يَكْفُرُوا بِمَا أَنْزَلَ اللَّهُ بَغْيًا أَنْ يُنَزِّلَ اللَّهُ مِنْ فَضْلِهِ عَلَىٰ مَنْ يَشَاءُ مِنْ عِبَادِهِ ۖ فَبَاءُوا بِغَضَبٍ عَلَىٰ غَضَبٍ ۚ وَلِلْكَافِرِينَ عَذَابٌ مُهِينٌ | G98: Sangatlah buruk (perbuatan) mereka menjual dirinya, dengan mengingkari apa yang diturunkan Allah karena dengki, bahwa Allah menurunkan karunia-Nya kepada siapa yang Dia kehendaki di antara hamba-hamba-Nya.40) Karena itulah mereka menanggung kemurkaan demi kemurkaan.41) Dan kepada orang-orang kafir (ditimpakan) azab yang menghinakan. | H98: Perjanjian Bani Israel dan Pelanggarannya (83-93) | L98: (Ayat 2:89-90): Tuhan melaknat dan menimpakan kemurkaan bertubi-tubi kepada sebuah kelompok semata-mata karena mereka mendustakan kitab yang baru turun. Menunjukkan intoleransi Tuhan terhadap kebebasan berpikir dan perbedaan keyakinan teologis. | O98: *40) Wahyu (kenabian) kepada Nabi Muhammad -ṣallallāhu 'alaihi wa sallam-. 41) Murka pertama karena membangkang kepada Nabi Musa -'alaihissalām- dan murka kedua karena mengingkari Nabi Muhammad -ṣallallāhu 'alaihi wa sallam-. | P98: (2:90) Kisah tentang patung anak lembu emas yang bisa melenguh diambil mentah-mentah dari cerita fiksi dongeng Yahudi, Pirke Rabbi Eleazer. (The Origins of the Koran)
A99: 2 | B99: 91 | C99: البقرة | D99: Al-Baqarah (Sapi Betina) | E99: Madinah | F99: وَإِذَا قِيلَ لَهُمْ آمِنُوا بِمَا أَنْزَلَ اللَّهُ قَالُوا نُؤْمِنُ بِمَا أُنْزِلَ عَلَيْنَا وَيَكْفُرُونَ بِمَا وَرَاءَهُ وَهُوَ الْحَقُّ مُصَدِّقًا لِمَا مَعَهُمْ ۗ قُلْ فَلِمَ تَقْتُلُونَ أَنْبِيَاءَ اللَّهِ مِنْ قَبْلُ إِنْ كُنْتُمْ مُؤْمِنِينَ | G99: Dan apabila dikatakan kepada mereka, "Berimanlah kepada apa yang diturunkan Allah (Al-Qur`an)," mereka menjawab, "Kami beriman kepada apa yang diturunkan kepada kami." Dan mereka ingkar kepada apa yang setelahnya, padahal (Al-Qur`an) itu adalah yang hak, yang membenarkan apa yang ada pada mereka. Katakanlah (Muhammad), "Mengapa kamu dahulu membunuh nabi-nabi Allah jika kamu orang-orang beriman?" | H99: Perjanjian Bani Israel dan Pelanggarannya (83-93) | K99: Guilt by Association + Hasty Generalization — Pembunuhan para nabi oleh leluhur Bani Israel dijadikan argumen melawan generasi masa kini; kesalahan masa lalu tidak dapat diwariskan kepada komunitas saat ini. | N99: Kontradiksi Tanggung Jawab Individual — Menyiratkan generasi Bani Israel masa kini menanggung beban membunuh para nabi oleh leluhur mereka; bertentangan dengan 6:164, 17:15, 35:18, dan 39:7 yang secara tegas menyatakan 'tidak ada yang menanggung beban orang lain.'
A100: 2 | B100: 92 | C100: البقرة | D100: Al-Baqarah (Sapi Betina) | E100: Madinah | F100: وَلَقَدْ جَاءَكُمْ مُوسَىٰ بِالْبَيِّنَاتِ ثُمَّ اتَّخَذْتُمُ الْعِجْلَ مِنْ بَعْدِهِ وَأَنْتُمْ ظَالِمُونَ | G100: Dan sungguh, Musa telah datang kepadamu dengan bukti-bukti kebenaran, kemudian kamu mengambil (patung) anak sapi (sebagai sesembahan) setelah (kepergian) nya, dan kamu (menjadi) orang-orang zalim. | H100: Perjanjian Bani Israel dan Pelanggarannya (83-93)
...
